Workbook
Name IQ_CH: 110000
Name IQ_CQ: 5000
Name IQ_CY: 10000
Name IQ_DAILY: 500000
Name IQ_FH: 100000
Name IQ_FQ: 500
Name IQ_FY: 1000
Name IQ_LTM: 2000
Name IQ_MONTH: 15000
Name IQ_NTM: 6000
Name IQ_WEEK: 50000
Name IQ_YTD: 3000

Sheet WIP list
B5: Pending Items
A7: 1 | B7: Add a decision type " Avoid Revenue Loss" | C7: Done
A8: 2 | B8: Update Decision logics | C8: Done
A9: 3 | B9: Change Continuing Value to value driver formula | C9: Done
A10: 4 | B10: Assign fundamentals to decisions | C10: In progress
A11: 5 | B11: Explain the model and assumptions to Client | C11: Done
A12: 6 | B12: Swap size and fundaments for Cost Savings | C12: Done
A13: 7 | B13: Add margin constraint | C13: Critical
A14: 8 | B14: Run Monte-Carlo | C14: Waiting for the licence
A15: 9 | B15: Add operating cash allowance | C15: Done
A16: 10 | B16: Add inorganic growth and divestment decisions | C16: In progress
A17: 11 | B17: Add manufacturing OH | C17: Done
A18: 12 | B18: Long-term Growth? | C18: No need
A19: 13 | B19: Implementation costs do not impact IC | C19: Done
A20: 14 | B20: List of cards' inputs
A21: 15 | B21: Clean up

Sheet Decision logic
B2: Common Structure (all levers) | K2: Types of Value Creation Decisions
B3: 5 rounds (years), 5 decisions per round
B4: Each decision tied to:
C5: Guiding principle | K5: Overall | M5: Size 1-5 is a differentiation by scale; Fundamentals 1-5 is a diffirentiation by value creation potential and impacts ROIC
C6: Decision category | M6: The amount of cash available for investments is a SUM: ending non-operating cash (allowance for cash on hand) + Debt Raising capacity
C7: Capital / organizational action | M7: Debt raising capacity is based on Credit Rating and DEBT/EBITDA <= 2.0
B8: Impact scored 1–5 to reflect timing, risk, and TSR contribution | M8: Except for SG&A savings, Round 1-3 decisions are impacted by Recession and Recovery scenarios, Round 4 decisions are impacted by Recovery scenario
B10: Grow — Create future value | K10: 1 | L10: Organic | M10: New business, R&D, JVs and Partnerships
B12: Intent: Expand scope, platforms, and long-term TSR upside | K12: 1 | L12: Impact on cash flows: | M12: Revenue, COGS, SGA, Capex
B13: Logic: Capability → commitment → scale → platform leadership | K13: 2 | L13: Investment
B14: Early rounds: R&D, partnerships, bolt-ons (option creation) | M14: Capex as % of base Revenue
B15: Mid rounds: capacity, geography, industrialization (commitment) | M15: Size of investment vary from 1-5 (1-2.5% of Base Revenue)
B16: Late rounds: system integration, ecosystems, large M&A (step-change) | K16: 3 | L16: Value drivers:
B17: Impact: Higher variance; late-round 4–5s | M17: Gross Margin (COGS impact, SGA 5% by defualt)
M18: Short-term growth
M19: Capital Efficiency
K20: 3 | L20: Assumptions and Differentiation
M21: Investment period 1-3 years
M22: Value Drivers are ranked from 1-5 depending on value creation potential
M23: 1 year Revenue = Investment * Capital turns
K25: 2 | L25: Inorganic | M25: In Progress | R25: David: | S25: link synergies to premium paid
S26: % premium paid
S27: % synergies created
B29: Optimize — Improve efficiency and returns
K30: 3 | L30: SG&A/COGS savings | M30: Cost Savings
B31: Intent: Reset cost base and ROIC to fund growth
B32: Logic: Friction removal → structural reset → portfolio cleanup | K32: 1 | L32: Impact on cash flows: | M32: COGS and SGA; Non-operating implementation costs
K33: 2 | L33: Investment | M33: Costs X:1 to full annual savings. For SGA and COGS decisions costs are not capitalized and treated as non-operating expense, do not increase IC, meaning pure increase in ROIC
B34: Early rounds: SG&A, systems, footprint rationalization | M34: For MOH - represent CAPEX and increse IC
B35: Mid rounds: operating model and group turnarounds | M35: Size of Implementation Cost vary from 1-5 (1.0 - 2.5x of Annual savings)
B36: Late rounds: divestments, full automation, capital discipline | K36: 3 | L36: Value drivers: | M36: COGS savings (% of Base revenue)
B37: Impact: Medium risk; consistent 3–4s | M37: SG&A savings (% of Base revenue)
K38: 4 | L38: Assumptions and Differentiation
M39: Investment period 1-3 years
M40: Value Drivers are ranked from 1-5 depending on value creation potential
M41: SG&A are not impacted by macro scenarios
M42: Total SG&A and COGS saving shold not exceed the gap to best-in class margin: 500 bps.
M43: If they do, no incremental increase in margin, only money spent
M44: Savings are not indexed. Decision now values more than next period
K48: 4 | L48: Divestments | M48: Divestments
M49: In Progress
B52: Sustain — Protect value and resilience
K53: 5 | M53: Cost savings or Actions to avoid revenue loss
B54: Intent: Preserve license to operate and TSR stability
B55: Logic: Baseline protection → resilience → capital signaling | L55: Sustain Topline
K56: 1 | L56: Impact on cash flows: | M56: Magna BaU revenue, Capex,
B57: Early rounds: safety, compliance, talent, baseline cyber | K57: 2 | L57: Investment | M57: Capex as % of base Revenue
B58: Mid rounds: advanced risk controls, dividend posture | M58: Size of investment vary from 1-5 (1-2.5% of Base Revenue)
B59: Late rounds: institutionalized resilience, counter-cyclical returns | K59: 3 | L59: Value drivers: | M59: Failure to take 1 decision leads to 0.X% decline in Revenue
B60: Impact: Lower upside; reduces downside volatility (1–3, few 4s)
K61: 4 | L61: Assumptions and Differentiation | M61: Investment period 1-3 years
M62: Decisions are not differenciated by fundamentals
B63: Game Insight
B65: Grow creates upside
B66: Optimize funds and de-risks Grow
B67: Sustain prevents value destruction
B68: Over-weighting any one lever reduces long-term TSR

Sheet Cards
C3: DECISION | D3: =Decisions!U6 -> 1
C5: Organic growth / JV / Partnership | D5: =Decisions!AD6 -> 4
C7: Investments (total) | D7: =-Decisions!AG6 -> 800 | E7: $m
C8: Investment period | D8: =Decisions!AE6 -> 2 | E8: years
C9: Revenue 1 year | D9: =INDEX(Decisions!$F$20:$F$24,MATCH($D$5,Decisions!$E$20:$E$24,))*D7 -> 1600 | E9: $m
C10: 5-year growth | D10: =INDEX(Decisions!$H$20:$H$24,MATCH($D$5,Decisions!$E$20:$E$24,)) -> 0.05 | E10: y-o-y
C11: EBITDA | D11: =INDEX(Decisions!$G$20:$G$24,MATCH($D$5,Decisions!$E$20:$E$24,))-Decisions!F44 -> 0.15
C16: DECISION | D16: =Decisions!U12 -> 7
C18: =Decisions!W12 -> SGA savings | D18: =Decisions!AD12 -> 2
C20: Implementation cost | D20: =INDEX(Decisions!L20:L24,MATCH($D$18,Decisions!$E$10:$E$14,)) -> 2.5 | E20: of Annual savings
C21: Investment period | D21: =Decisions!AE12 -> 1 | E21: year
C22: Annual cost savings | D22: =Decisions!AJ12 -> 40 | E22: $m
C29: DECISION | D29: =Decisions!U19 -> 14
C31: =Decisions!W19 -> Sustain Topline
C33: Investments (total) | D33: =-Decisions!AG16 -> 40 | E33: =E7 -> $m
C34: =C8 -> Investment period | D34: =Decisions!AE19 -> 1 | E34: year
C35: No incremental cash flow created
C36: Avoid losing business-as-usual revenue | D36: -0.001 | E36: to the last year

Sheet _CIQHiddenCacheSheet
A1: 2 | B1: BAABTAVMT0NBTAFI/////wFQAQAAAB5DSVEuVFNYOk1HLklRX1NQX0lTU1VFUl9SQVRJTkcBAAAAuFwEAAMAAAACQS0A6jWZ4VNi3ggpTrvhU2LeCA==

Sheet Decisions
E2: Value Drivers | U2: Decision | AS2: For Cards
W3: To be assigned/updated once decisions are confirmed | AB3: Do not change the round order | AC3: Magnifies the scale | AD3: Impact ROI | AH3: Cumulative NPV may not be tied to totals due to Sustain decisions | AS3: Organic Growth | AY3: Optimise (SGA and COGS) | BD3: Sustain
A5: Do not delete | U5: # | V5: Lever | W5: Type of Value Drivers | X5: lesson Learned | Y5: Decision Type | Z5: Decision Name | AA5: Decision Detail | AB5: Round | AC5: Size | AD5: Fundamentals | AE5: Investment period | AF5: Selected | AG5: Investments | AH5: NPV | AI5: ROIC Y10 | AJ5: EBITDA_Y10 | AK5: Archetype | AN5: Impact on share price | AO5: $ | AP5: 5-year TSR | AS5: Revenue 1 year | AT5: 5-year growth | AU5: Investments (total) | AV5: Investment period | AW5: EBIT margin | AY5: Implementation cost | AZ5: Investments | BA5: Investment period | BB5: Annual cost savings | BD5: Implementation cost | BE5: Investments | BF5: Investment period | BG5: Annual cost savings
A6: Organic | E6: Size | U6: 1 | V6: Grow | W6: Organic | X6: 1. Grow profitably | Y6: Expand Manufacturing Footprint | Z6: Mexico Capacity Expansion | AA6: Expand existing Mexican operations to increase capacity for North American OEMs. Nearshoring trend favors this investment with relatively predictable returns. | AB6: 1 | AC6: 3 | AD6: 4 | AE6: 2 | AF6: 0 | AG6: -800 | AH6: 1319.2498 | AI6: 0.21900992 | AJ6: 306.30757 | AK6: accretive with ROIC 15% | AL6: Accretive | AS6: 1600 | AT6: 0.05 | AU6: -800 | AV6: 2 | AW6: 0.11 | AY6: 0 | AZ6: 0 | BA6: 0 | BB6: 0 | BD6: 0 | BE6: 0 | BF6: 0 | BG6: 0
A7: M&A / Divestments | E7: Type | F7: Organic | G7: M&A / Divestments | K7: COGS savings | L7: SGA savings | M7: Manufacturing OH savings | O7: Sustain Topline | U7: 2 | V7: Grow | W7: Organic | X7: 1. Grow profitably | Y7: Scale R&D for Next-Gen Portfolio | Z7: Advanced Powertrain R&D Expansion | AA7: Invest in expanding R&D capabilities for next-generation vehicle powertrains and propulsion systems. This positions Magna to capture growing market share in advanced mobility but requires significant upfront investment with returns materializing over 2-3 years. | AB7: 1 | AC7: 4 | AD7: 4 | AE7: 3 | AF7: 0 | AG7: -1000 | AH7: 1515.6118 | AI7: 0.21900992 | AJ7: 382.88447 | AK7: accretive with ROIC 15% | AL7: Accretive | AN7: Share price as of today | AO7: 52.265643 | AS7: 2000 | AT7: 0.05 | AU7: -1000 | AV7: 3 | AW7: 0.11 | AY7: 0 | AZ7: 0 | BA7: 0 | BB7: 0 | BD7: 0 | BE7: 0 | BF7: 0 | BG7: 0
A8: COGS savings | F8: Investments (Capex) | G8: Inorganic / Discontinued revenue | I8: Premium | K8: COGS savings | O8: Cost | U8: 3 | V8: Grow | W8: Organic | X8: 1. Grow profitably | Y8: Enter New Geography / Market | Z8: Southeast Asia Market Entry | AA8: Establish manufacturing presence in Thailand/Vietnam to serve growing ASEAN automotive market. Lower labor costs and proximity to emerging markets, but execution risk in new geography. | AB8: 1 | AC8: 3 | AD8: 1 | AE8: 2 | AF8: 0 | AG8: -800 | AH8: -161.16516 | AI8: 0.067817533 | AJ8: 125.2016 | AK8: high growth low margin | AL8: Dilutive | AN8: Share price w/o decision as of today | AO8: 49.110547 | AQ8: margin contraction 50 bps revenue decline 1%, recession/recovery offset each other | AS8: 1200 | AT8: 0.03 | AU8: -800 | AV8: 2 | AW8: 0.05 | AY8: 0 | AZ8: 0 | BA8: 0 | BB8: 0 | BD8: 0 | BE8: 0 | BF8: 0 | BG8: 0
A9: SGA savings | F9: as % of Base Revenue | G9: as % of Base Revenue | I9: As % of Base Price (NPV) | K9: as % of Base Revenue | L9: as % of Base Revenue | M9: as % of Base Revenue | O9: as % of Base Revenue | U9: 4 | V9: Grow | W9: Organic | X9: 3. Stay flexible | Y9: JV / Strategic Partnership | Z9: Battery Technology JV | AA9: Form joint venture with battery cell manufacturer to secure supply and develop integrated battery systems. Strategic hedge against vertical integration by OEMs. | AB9: 1 | AC9: 5 | AD9: 2 | AE9: 2 | AF9: 0 | AG9: -1000 | AH9: -250.32915 | AI9: 0.0624 | AJ9: 112 | AK9: low growth bad capital turnover but high margin | AL9: Dilutive | AN9: Future value w/ decisions | AO9: 76.608257 | AP9: 0.079473179 | AS9: 800 | AT9: 0 | AU9: -1000 | AV9: 2 | AW9: 0.1 | AY9: 0 | AZ9: 0 | BA9: 0 | BB9: 0 | BD9: 0 | BE9: 0 | BF9: 0 | BG9: 0
A10: Sustain Topline | E10: 1 | F10: 0.01 | G10: -0.03 | H10: Divestment | K10: 0.001 | L10: 0.001 | M10: 0.001 | O10: 0.001 | U10: 5 | V10: Grow | W10: Organic | X10: 1. Grow profitably | Y10: Expand Manufacturing Footprint | Z10: Concentrated OEM Capacity Investment | AA10: Major capacity investment for an OEM's flagship vehicle program. The OEM has committed to unprecedented volumes and offered favorable terms for exclusive supply. Higher projected returns than diversified approach, with dedicated production lines and simpler logistics. | AB10: 1 | AC10: 4 | AD10: 1 | AE10: 2 | AF10: 0 | AG10: -1000 | AH10: -201.45646 | AI10: 0.067817533 | AJ10: 156.502 | AK10: high growth low margin | AL10: Dilutive | AN10: Future value w/o decisions | AO10: 55.727563 | AP10: 0.012909748 | AS10: 1500 | AT10: 0.03 | AU10: -1000 | AV10: 2 | AW10: 0.05 | AY10: 0 | AZ10: 0 | BA10: 0 | BB10: 0 | BD10: 0 | BE10: 0 | BF10: 0 | BG10: 0
A11: Manufacturing OH savings | E11: 2 | F11: 0.015 | G11: 0.03 | H11: Acquisition | I11: 0.21272727 | J11: 0.21272727 | K11: 0.001 | L11: 0.001 | M11: 0.001 | O11: 0.002 | U11: 6 | V11: Optimize | W11: Manufacturing OH savings | X11: 1. Grow profitably | Y11: Factory of the Future | Z11: Smart Factory Pilot Program | AA11: Implement Industry 4.0 technologies in flagship facility. IoT sensors, AI-driven quality control, and predictive maintenance. Proof of concept for broader rollout. | AB11: 1 | AC11: 2 | AD11: 1 | AE11: 2 | AF11: 0 | AG11: -120 | AH11: 273.50033 | AI11: 0.26 | AJ11: 40 | AK11: Size impacts the amount of savings, Fundamentals - ROI | AL11: Accretive | AS11: 0 | AT11: 0 | AU11: 0 | AV11: 0 | AY11: 0 | AZ11: -120 | BA11: 2 | BB11: 40 | BD11: 0 | BE11: 0 | BF11: 0 | BG11: 0
A12: Share repurchase | E12: 3 | F12: 0.02 | G12: 0.05 | H12: Acquisition | I12: 0.21272727 | K12: 0.002 | L12: 0.002 | M12: 0.002 | O12: 0.003 | U12: 7 | V12: Optimize | W12: SGA savings | X12: 1. Grow profitably | Y12: SG&A Optimization | Z12: Shared Services Consolidation | AA12: Consolidate back-office functions (finance, HR, IT) into regional shared services centers. Upfront investment yields ongoing cost savings. | AB12: 1 | AC12: 2 | AD12: 2 | AE12: 1 | AF12: 0 | AG12: -100 | AH12: 317.80231 | AI12: 0.312 | AJ12: 40 | AK12: Size impacts the amount of savings, Fundamentals - ROI | AL12: Accretive | AS12: 0 | AT12: 0 | AU12: 0 | AV12: 0 | AY12: 2.5 | AZ12: 0 | BA12: 1 | BB12: 40 | BD12: 0 | BE12: 0 | BF12: 0 | BG12: 0
A13: Dividends | E13: 4 | F13: 0.025 | G13: 0.1 | H13: Acquisition | I13: 0.21272727 | K13: 0.003 | L13: 0.003 | M13: 0.003 | O13: 0.004 | U13: 8 | V13: Optimize | W13: COGS savings | X13: 1. Grow profitably | Y13: Global Supply Chain Redesign | Z13: Supplier Dual-Sourcing Initiative | AA13: Establish secondary suppliers for critical components. Increases supply chain resilience and negotiating leverage. Small cost premium offset by risk reduction. | AB13: 1 | AC13: 3 | AD13: 3 | AE13: 1 | AF13: 0 | AG13: -160 | AH13: 678.94108 | AI13: 0.39 | AJ13: 80 | AK13: Size impacts the amount of savings, Fundamentals - ROI | AL13: Accretive | AS13: 0 | AT13: 0 | AU13: 0 | AV13: 0 | AY13: 2 | AZ13: 0 | BA13: 1 | BB13: 80 | BD13: 0 | BE13: 0 | BF13: 0 | BG13: 0
E14: 5 | F14: 0.025 | G14: 0.2 | H14: Acquisition | I14: 0.21272727 | K14: 0.004 | L14: 0.004 | M14: 0.004 | O14: 0.005 | U14: 9 | V14: Optimize | W14: Manufacturing OH savings | X14: 2. Cash is king | Y14: Enterprise Digital Transformation | Z14: ERP System Upgrade | AA14: Launch enterprise-wide Data & ERP Transformation, migrating core ERP to a modern cloud platform while redesigning data architecture, analytics, and end-to-end processes. Enables advanced analytics, AI-driven automation, and materially improved decision-making across the business. | AB14: 1 | AC14: 2 | AD14: 1 | AE14: 2 | AF14: 0 | AG14: -120 | AH14: 273.50033 | AI14: 0.26 | AJ14: 40 | AK14: Size impacts the amount of savings, Fundamentals - ROI | AL14: Accretive | AS14: 0 | AT14: 0 | AU14: 0 | AV14: 0 | AY14: 0 | AZ14: -120 | BA14: 2 | BB14: 40 | BD14: 0 | BE14: 0 | BF14: 0 | BG14: 0
E15: step | F15: 0.005 | K15: 0.001 | L15: 0.001 | M15: 0.001 | O15: 0.001 | U15: 10 | V15: Optimize | W15: SGA savings | X15: 3. Stay flexible | Y15: Organizational Restructure | Z15: Management Delayering | AA15: Execute a management reorganization to de-layer the organization, accelerating decision-making, clarifying accountability, and sustainably reducing overhead. | AB15: 1 | AC15: 2 | AD15: 5 | AE15: 1 | AF15: 0 | AG15: -40 | AH15: 382.80701 | AI15: 0.78 | AJ15: 40 | AK15: Size impacts the amount of savings, Fundamentals - ROI | AL15: Accretive | AS15: 0 | AT15: 0 | AU15: 0 | AV15: 0 | AY15: 1 | AZ15: 0 | BA15: 1 | BB15: 40 | BD15: 0 | BE15: 0 | BF15: 0 | BG15: 0
U16: 11 | V16: Sustain | W16: Sustain Topline | X16: 1. Grow profitably | Y16: Portfolio management (maintenance) | Z16: Customer Diversification Initiative | AA16: Allocate incremental investment to expand sales coverage and key-account capabilities beyond top customers, deliberately diversifying the revenue base and mitigating concentration risk. | AB16: 1 | AC16: 1 | AD16: 1 | AE16: 1 | AF16: 0 | AG16: -40 | AH16: -37.037037 | AI16: 0 | AJ16: 0 | AL16: Accretive | AS16: 0 | AT16: 0 | AU16: 0 | AV16: 0 | AY16: 0 | AZ16: 0 | BA16: 0 | BB16: 0 | BD16: 0 | BE16: -40 | BF16: 1 | BG16: 0 | BH16: No incremental cash flow created Avoid losing business-as-usual revenue -0.1% y-o-y
E17: Fundamentals | F17: Organic | G17: Organic | H17: Organic | K17: COGS savings | L17: SGA savings | M17: Manufacturing OH savings | P17: Organic | Q17: Inorganic | R17: COGS savings | S17: Manufacturing OH savings | U17: 12 | V17: Sustain | W17: COGS savings | X17: 1. Grow profitably | Y17: Talent & Leadership Upskilling | Z17: Technical Talent Development | AA17: Investment in training and development for engineering workforce. Essential to maintain competitive capabilities. Retention and capability building. | AB17: 1 | AC17: 2 | AD17: 1 | AE17: 1 | AF17: 0 | AG17: -120 | AH17: 296.13407 | AI17: 0.26 | AJ17: 40 | AL17: Accretive | AS17: 0 | AT17: 0 | AU17: 0 | AV17: 0 | AY17: 3 | AZ17: 0 | BA17: 0 | BB17: 0 | BD17: 3 | BE17: 0 | BF17: 1 | BG17: 40
F18: Capital efficiency | G18: Gross Margin (only COGS impact) | H18: 5-year growth | I18: EBIT margin | K18: Cost / Annual savings | L18: Cost / Annual savings | M18: Cost / Annual savings | P18: ROIC | Q18: ROIC | R18: ROIC | S18: ROIC | U18: 13 | V18: Sustain | W18: Sustain Topline | X18: 3. Stay flexible | Y18: Risk & Compliance Upgrade | Z18: Cybersecurity Enhancement | AA18: Comprehensive cybersecurity upgrade across IT infrastructure. Essential protection against growing cyber threats. No direct return but prevents catastrophic risk. | AB18: 1 | AC18: 2 | AD18: 1 | AE18: 1 | AF18: 0 | AG18: -80 | AH18: -74.074074 | AI18: 0 | AJ18: 0 | AL18: Accretive | AS18: 0 | AT18: 0 | AU18: 0 | AV18: 0 | AY18: 0 | AZ18: 0 | BA18: 0 | BB18: 0 | BD18: 0 | BE18: -80 | BF18: 1 | BG18: 0 | BH18: No incremental cash flow created Avoid losing business-as-usual revenue -0.1% y-o-y
C19: Note | F19: capital turns | G19: % | H19: CAGR | K19: x | L19: x | U19: 14 | V19: Sustain | W19: Sustain Topline | X19: 1. Grow profitably | Y19: Capital allocation strategy (maintenance) | Z19: Equipment Refresh Program | AA19: Scheduled replacement of aging manufacturing equipment. Maintains reliability and quality. Deferred investment risks production disruptions. | AB19: 1 | AC19: 2 | AD19: 1 | AE19: 1 | AF19: 0 | AG19: -80 | AH19: -74.074074 | AI19: 0 | AJ19: 0 | AL19: Accretive | AS19: 0 | AT19: 0 | AU19: 0 | AV19: 0 | AY19: 0 | AZ19: 0 | BA19: 0 | BB19: 0 | BD19: 0 | BE19: -80 | BF19: 1 | BG19: 0 | BH19: No incremental cash flow created Avoid losing business-as-usual revenue -0.1% y-o-y
C20: high growth low margin | E20: 1 | F20: 1.5 | G20: 0.14 | H20: 0.03 | I20: 0.05 | K20: 3 | L20: 3 | M20: 3 | P20: 0.067817533 | Q20: in progress | R20: 0.26 | S20: 0.26 | U20: 15 | V20: Sustain | W20: SGA savings | X20: 3. Stay flexible | Y20: Risk & Compliance Upgrade | Z20: Environmental Compliance Investment | AA20: Proactive investment to meet upcoming environmental regulations. Mandatory compliance but early investment avoids rushed future spending. | AB20: 1 | AC20: 1 | AD20: 1 | AE20: 1 | AF20: 0 | AG20: -120 | AH20: 296.13407 | AI20: 0.26 | AJ20: 40 | AL20: Accretive | AS20: 0 | AT20: 0 | AU20: 0 | AV20: 0 | AY20: 3 | AZ20: 0 | BA20: 0 | BB20: 0 | BD20: 3 | BE20: 0 | BF20: 1 | BG20: 40
C21: low growth bad capital turnover but high margin | E21: 2 | F21: 0.8 | G21: 0.19 | H21: 0 | I21: 0.1 | K21: 2.5 | L21: 2.5 | M21: 2.5 | P21: 0.0624 | Q21: in progress | R21: 0.312 | S21: 0.312 | U21: 16 | V21: Grow | W21: Organic | X21: 1. Grow profitably | Y21: Launch a New Business | Z21: Autonomous Driving Systems Unit | AA21: Launch dedicated business unit for advanced driver assistance systems (ADAS) and autonomous driving technology. High potential but uncertain returns as technology evolves rapidly. | AB21: 2 | AC21: 4 | AD21: 2 | AE21: 2 | AF21: 0 | AG21: -1000 | AH21: -233.81744 | AI21: 0.0624 | AJ21: 112 | AK21: low growth bad capital turnover but high margin | AL21: Dilutive | AS21: 800 | AT21: 0 | AU21: -1000 | AV21: 2 | AW21: 0.1 | AY21: 0 | AZ21: 0 | BA21: 0 | BB21: 0 | BD21: 0 | BE21: 0 | BF21: 0 | BG21: 0
C22: close to cost of capital: 0% growth, 6% EBIT | E22: 3 | F22: 2 | G22: 0.15 | H22: 0 | I22: 0.06 | K22: 2 | L22: 2 | M22: 2 | P22: 0.0936 | Q22: in progress | R22: 0.39 | S22: 0.39 | U22: 17 | V22: Grow | W22: Organic | X22: 3. Stay flexible | Y22: Expand Manufacturing Footprint | Z22: Diversified OEM Capacity Investment | AA22: Invest in flexible powertrain manufacturing capacity additions across existing facilities globally to serve multiple OEM customers. Spreads investment across GM, Ford, Honda, and BMW programs. Lower per-unit returns but diversified risk exposure. Requires more coordination but provides insurance against customer-specific disruptions. | AB22: 2 | AC22: 3 | AD22: 3 | AE22: 2 | AF22: 0 | AG22: -800 | AH22: 112.6476 | AI22: 0.0936 | AJ22: 160 | AK22: close to cost of capital: 0% growth, 6% EBIT | AL22: Accretive | AS22: 1600 | AT22: 0 | AU22: -800 | AV22: 2 | AW22: 0.06 | AY22: 0 | AZ22: 0 | BA22: 0 | BB22: 0 | BD22: 0 | BE22: 0 | BF22: 0 | BG22: 0
C23: accretive with ROIC 15% | E23: 4 | F23: 2 | G23: 0.2 | H23: 0.05 | I23: 0.11 | K23: 1.5 | L23: 1.5 | M23: 1.5 | P23: 0.21900992 | Q23: in progress | R23: 0.52 | S23: 0.52 | U23: 18 | V23: Grow | W23: M&A / Divestments | X23: 1. Grow profitably | Y23: Acquire a Business | Z23: Bolt-on Sensor Acquisition | AA23: Acquire small sensor technology company to enhance ADAS capabilities. Adds specialized engineering talent and IP. Integration risk exists but accelerates time-to-market. | AB23: 2 | AC23: 3 | AD23: 2 | AE23: 1 | AF23: 0 | AG23: -3941.5797 | AH23: 6.5086523 | AI23: 0.081988325 | AJ23: 483.153 | AK23: M&A (1 for Divestments) | AL23: Accretive | AS23: 2000 | AT23: 0.1 | AU23: 0 | AV23: 0 | AW23: 0.11 | AY23: 0 | AZ23: 0 | BA23: 1 | BB23: 0 | BD23: 0 | BE23: 0 | BF23: 0 | BG23: 0
C24: accretive with ROIC 20% | E24: 5 | F24: 2.5 | G24: 0.2 | H24: 0.03 | I24: 0.11 | K24: 1 | L24: 1 | M24: 1 | P24: 0.24866429 | R24: 0.78 | S24: 0.78 | U24: 19 | V24: Grow | W24: Organic | X24: 1. Grow profitably | Y24: Platform-Level Technology Bets | Z24: Software-Defined Vehicle Platform | AA24: Make a targeted technology bet on modular, software-defined vehicle architectures, reflecting OEM demand for faster feature deployment, lower lifecycle cost, and vendor-agnostic platforms. | AB24: 2 | AC24: 5 | AD24: 2 | AE24: 2 | AF24: 0 | AG24: -1000 | AH24: -233.81744 | AI24: 0.0624 | AJ24: 112 | AK24: low growth bad capital turnover but high margin | AL24: Dilutive | AS24: 800 | AT24: 0 | AU24: -1000 | AV24: 2 | AW24: 0.1 | AY24: 0 | AZ24: 0 | BA24: 0 | BB24: 0 | BD24: 0 | BE24: 0 | BF24: 0 | BG24: 0
E25: step | K25: 0.5 | L25: 0.5 | M25: 0.5 | P25: Note: ROIC can be slighly different due to short-term growth | U25: 20 | V25: Grow | W25: Organic | X25: 3. Stay flexible | Y25: Expand Manufacturing Footprint | Z25: European Advanced Assembly Facility | AA25: Build dedicated advanced vehicle assembly plant in Eastern Europe. Positions for European regulatory requirements and next-gen vehicle platforms. Significant investment with long payback period. | AB25: 2 | AC25: 4 | AD25: 1 | AE25: 3 | AF25: 0 | AG25: -1000 | AH25: -205.98667 | AI25: 0.067817533 | AJ25: 156.502 | AK25: high growth low margin | AL25: Dilutive | AS25: 1500 | AT25: 0.03 | AU25: -1000 | AV25: 3 | AW25: 0.05 | AY25: 0 | AZ25: 0 | BA25: 0 | BB25: 0 | BD25: 0 | BE25: 0 | BF25: 0 | BG25: 0
U26: 21 | V26: Optimize | W26: COGS savings | X26: 1. Grow profitably | Y26: Enterprise Digital Transformation | Z26: Advanced Analytics Platform | AA26: Deploy enterprise analytics platform to improve decision-making across operations. Predictive insights for demand planning, quality, and maintenance. | AB26: 2 | AC26: 2 | AD26: 1 | AE26: 1 | AF26: 0 | AG26: -120 | AH26: 277.61555 | AI26: 0.26 | AJ26: 40 | AL26: Accretive | AS26: 0 | AT26: 0 | AU26: 0 | AV26: 0 | AY26: 3 | AZ26: 0 | BA26: 1 | BB26: 40 | BD26: 0 | BE26: 0 | BF26: 0 | BG26: 0
G27: M&A / Divestments | H27: M&A / Divestments | U27: 22 | V27: Optimize | W27: Manufacturing OH savings | X27: 2. Cash is king | Y27: Factory of the Future | Z27: Automation Expansion Program | AA27: Expand robotic automation across manufacturing facilities. Higher upfront cost but significant labor cost reduction and quality improvement. | AB27: 2 | AC27: 4 | AD27: 1 | AE27: 1 | AF27: 0 | AG27: -360 | AH27: 832.84666 | AI27: 0.26 | AJ27: 120 | AL27: Accretive | AS27: 0 | AT27: 0 | AU27: 0 | AV27: 0 | AY27: 0 | AZ27: -360 | BA27: 1 | BB27: 120 | BD27: 0 | BE27: 0 | BF27: 0 | BG27: 0
F28: Synergies | G28: Gross Margin (only COGS impact) | H28: 5-year growth | U28: 23 | V28: Optimize | W28: COGS savings | X28: 1. Grow profitably | Y28: Select Group Transformation | Z28: Underperforming Division Turnaround | AA28: Comprehensive operational improvement program for underperforming business unit. New leadership, process redesign, and targeted investments. | AB28: 2 | AC28: 3 | AD28: 1 | AE28: 1 | AF28: 0 | AG28: -240 | AH28: 555.23111 | AI28: 0.26 | AJ28: 80 | AL28: Accretive | AS28: 0 | AT28: 0 | AU28: 0 | AV28: 0 | AY28: 3 | AZ28: 0 | BA28: 1 | BB28: 80 | BD28: 0 | BE28: 0 | BF28: 0 | BG28: 0
F29: as % of Acquired Revenue | G29: % | H29: CAGR | U29: 24 | V29: Optimize | W29: COGS savings | X29: 1. Grow profitably | Y29: Global Supply Chain Redesign | Z29: Logistics Network Optimization | AA29: Redesign global logistics network to reduce transportation costs and improve delivery times. Consolidate warehouses and optimize routes. | AB29: 2 | AC29: 3 | AD29: 1 | AE29: 1 | AF29: 0 | AG29: -240 | AH29: 555.23111 | AI29: 0.26 | AJ29: 80 | AL29: Accretive | AS29: 0 | AT29: 0 | AU29: 0 | AV29: 0 | AY29: 3 | AZ29: 0 | BA29: 1 | BB29: 80 | BD29: 0 | BE29: 0 | BF29: 0 | BG29: 0
E30: 1 | G30: 0.14 | H30: 0 | I30: Divestment | U30: 25 | V30: Optimize | W30: SGA savings | X30: 1. Grow profitably | Y30: SG&A Optimization | Z30: Procurement Excellence Program | AA30: Implement strategic sourcing and supplier management program. Leverage scale for better pricing and terms on indirect spend. | AB30: 2 | AC30: 2 | AD30: 1 | AE30: 1 | AF30: 0 | AG30: -120 | AH30: 277.61555 | AI30: 0.26 | AJ30: 40 | AL30: Accretive | AS30: 0 | AT30: 0 | AU30: 0 | AV30: 0 | AY30: 3 | AZ30: 0 | BA30: 1 | BB30: 40 | BD30: 0 | BE30: 0 | BF30: 0 | BG30: 0
E31: 2 | F31: 0.03 | G31: 0.2 | H31: 0.1 | I31: Acquisition | U31: 26 | V31: Sustain | W31: SGA savings | X31: 1. Grow profitably | Y31: Talent & Leadership Upskilling | Z31: Leadership Development Program | AA31: Comprehensive leadership development for high-potential managers. Builds succession pipeline and organizational capability. Long-term investment in human capital. | AB31: 2 | AC31: 2 | AD31: 1 | AE31: 1 | AF31: 0 | AG31: -120 | AH31: 277.61555 | AI31: 0.26 | AJ31: 40 | AL31: Accretive | AS31: 0 | AT31: 0 | AU31: 0 | AV31: 0 | AY31: 3 | AZ31: 0 | BA31: 0 | BB31: 0 | BD31: 3 | BE31: 0 | BF31: 1 | BG31: 40
E32: 3 | F32: 0.03 | G32: 0.2 | H32: 0.1 | I32: Acquisition | U32: 27 | V32: Sustain | W32: Sustain Topline | X32: 1. Grow profitably | Y32: Risk & Compliance Upgrade | Z32: Quality Management System Upgrade | AA32: Upgrade quality management systems to meet evolving OEM requirements. Essential for maintaining key customer relationships. Prevents costly quality escapes. | AB32: 2 | AC32: 2 | AD32: 1 | AE32: 1 | AF32: 0 | AG32: -80 | AH32: -68.587106 | AI32: 0 | AJ32: 0 | AL32: Accretive | AS32: 0 | AT32: 0 | AU32: 0 | AV32: 0 | AY32: 0 | AZ32: 0 | BA32: 0 | BB32: 0 | BD32: 0 | BE32: -80 | BF32: 1 | BG32: 0 | BH32: No incremental cash flow created Avoid losing business-as-usual revenue -0.1% y-o-y
E33: 4 | F33: 0.03 | G33: 0.2 | H33: 0.1 | I33: Acquisition | U33: 28 | V33: Sustain | W33: COGS savings | X33: 1. Grow profitably | Y33: Capital allocation strategy (maintenance) | Z33: IT Infrastructure Modernization | AA33: Update core IT systems and infrastructure. Addresses technical debt and security vulnerabilities. Foundational investment enabling future digital initiatives. | AB33: 2 | AC33: 2 | AD33: 1 | AE33: 1 | AF33: 0 | AG33: -120 | AH33: 277.61555 | AI33: 0.26 | AJ33: 40 | AL33: Accretive | AS33: 0 | AT33: 0 | AU33: 0 | AV33: 0 | AY33: 3 | AZ33: 0 | BA33: 0 | BB33: 0 | BD33: 3 | BE33: 0 | BF33: 1 | BG33: 40
E34: 5 | F34: 0.03 | G34: 0.2 | H34: 0.1 | I34: Acquisition | U34: 29 | V34: Sustain | W34: Sustain Topline | X34: 3. Stay flexible | Y34: Risk & Compliance Upgrade | Z34: Health & Safety Investment | AA34: Enhanced workplace safety equipment and training programs. Essential for employee welfare and regulatory compliance. Reduces accident-related costs. | AB34: 2 | AC34: 1 | AD34: 1 | AE34: 1 | AF34: 0 | AG34: -40 | AH34: -34.293553 | AI34: 0 | AJ34: 0 | AL34: Accretive | AS34: 0 | AT34: 0 | AU34: 0 | AV34: 0 | AY34: 0 | AZ34: 0 | BA34: 0 | BB34: 0 | BD34: 0 | BE34: -40 | BF34: 1 | BG34: 0 | BH34: No incremental cash flow created Avoid losing business-as-usual revenue -0.1% y-o-y
U35: 30 | V35: Sustain | W35: COGS savings | X35: 1. Grow profitably | Y35: Portfolio management (maintenance) | Z35: Supplier Relationship Investment | AA35: Strengthen relationships with strategic suppliers through joint development and long-term agreements. Improves supply security and preferential allocation. | AB35: 2 | AC35: 2 | AD35: 1 | AE35: 1 | AF35: 0 | AG35: -120 | AH35: 277.61555 | AI35: 0.26 | AJ35: 40 | AL35: Dilutive | AS35: 0 | AT35: 0 | AU35: 0 | AV35: 0 | AY35: 3 | AZ35: 0 | BA35: 0 | BB35: 0 | BD35: 3 | BE35: 0 | BF35: 1 | BG35: 40
U36: 31 | V36: Grow | W36: Organic | X36: 1. Grow profitably | Y36: Expand Manufacturing Footprint | Z36: North America Advanced Component Hub | AA36: Consolidate advanced component manufacturing across business units into a single, dedicated cross-group facility, capturing scale efficiencies and capability depth while requiring a significant fixed-asset commitment amid uncertain market demand. | AB36: 3 | AC36: 4 | AD36: 1 | AE36: 1 | AF36: 0 | AG36: -1000 | AH36: -155.9752 | AI36: 0.067817533 | AJ36: 156.502 | AK36: high growth low margin | AL36: Dilutive | AS36: 1500 | AT36: 0.03 | AU36: -1000 | AV36: 1 | AW36: 0.05 | AY36: 0 | AZ36: 0 | BA36: 0 | BB36: 0 | BD36: 0 | BE36: 0 | BF36: 0 | BG36: 0
U37: 32 | V37: Grow | W37: Organic | X37: 1. Grow profitably | Y37: JV / Strategic Partnership | Z37: Chinese OEM Partnership | AA37: Strategic partnership with leading Chinese automotive manufacturer. Access to largest automotive growth market but geopolitical and IP concerns. High reward potential with elevated risk. | AB37: 3 | AC37: 4 | AD37: 1 | AE37: 1 | AF37: 0 | AG37: -1000 | AH37: -155.9752 | AI37: 0.067817533 | AJ37: 156.502 | AL37: Accretive | AS37: 1500 | AT37: 0.03 | AU37: -1000 | AV37: 1 | AW37: 0.05 | AY37: 0 | AZ37: 0 | BA37: 0 | BB37: 0 | BD37: 0 | BE37: 0 | BF37: 0 | BG37: 0
E38: General assumptions | U38: 33 | V38: Grow | W38: M&A / Divestments | X38: 1. Grow profitably | Y38: Acquire a Business | Z38: Distressed Competitor Acquisition | AA38: Opportunity to acquire struggling competitor at attractive valuation. Significant capacity and customer relationships, but integration complexity and some legacy issues. | AB38: 3 | AC38: 5 | AD38: 2 | AE38: 1 | AF38: 0 | AG38: -15795.29 | AH38: 45.266863 | AI38: 0.081837943 | AJ38: 1932.612 | AK38: low growth bad capital turnover but high margin | AL38: Dilutive | AS38: 8000 | AT38: 0.1 | AU38: 0 | AV38: 0 | AW38: 0.11 | AY38: 0 | AZ38: 0 | BA38: 1 | BB38: 0 | BD38: 0 | BE38: 0 | BF38: 0 | BG38: 0
E39: Base Revenue | F39: 40000 | G39: Actual revenue rounded | K39: Inorganic | U39: 34 | V39: Grow | W39: Organic | X39: 1. Grow profitably | Y39: Scale R&D for Next-Gen Portfolio | Z39: Solid-State Battery Research | AA39: Invest in next-generation solid-state battery technology research. Could leapfrog current technology but commercialization timeline uncertain. | AB39: 3 | AC39: 4 | AD39: 1 | AE39: 1 | AF39: 0 | AG39: -1000 | AH39: -155.9752 | AI39: 0.067817533 | AJ39: 156.502 | AK39: high growth low margin | AL39: Dilutive | AS39: 1500 | AT39: 0.03 | AU39: -1000 | AV39: 1 | AW39: 0.05 | AY39: 0 | AZ39: 0 | BA39: 0 | BB39: 0 | BD39: 0 | BE39: 0 | BF39: 0 | BG39: 0
E40: Capex maintenance | F40: 0.04 | G40: In line with peer average | U40: 35 | V40: Grow | W40: Organic | X40: 1. Grow profitably | Y40: Revenue Diversification | Z40: Expand Beyond OEMs into Non-Traditional Customers | AA40: Pursue revenue opportunities with non-OEM customers (e.g., Amazon, fleet operators, mobility platforms) by adapting Magna’s manufacturing and engineering capabilities to adjacent use cases. | AB40: 3 | AC40: 2 | AD40: 1 | AE40: 1 | AF40: 0 | AG40: -600 | AH40: -93.585119 | AI40: 0.067817533 | AJ40: 93.9012 | AK40: high growth low margin | AL40: Accretive | AS40: 900 | AT40: 0.03 | AU40: -600 | AV40: 1 | AW40: 0.05 | AY40: 0 | AZ40: 0 | BA40: 0 | BB40: 0 | BD40: 0 | BE40: 0 | BF40: 0 | BG40: 0
E41: Taxes | F41: 0.22 | U41: 36 | V41: Optimize | W41: M&A / Divestments | X41: 2. Cash is king | Y41: Divest Group | Z41: Non-Core Division Divestiture | AA41: Divest underperforming non-core business unit. Generates cash and allows focus on strategic priorities. May face valuation pressure in current market. | AB41: 3 | AC41: 1 | AD41: 1 | AE41: 1 | AF41: 0 | AG41: 598.65368 | AH41: -150.92639 | AI41: 0.10022489 | AJ41: -108 | AK41: M&A (1 for Divestments) | AL41: Accretive | AS41: -1200 | AT41: 0 | AU41: 0 | AV41: 0 | AW41: 0.05 | AY41: 0 | AZ41: 0 | BA41: 1 | BB41: 0 | BD41: 0 | BE41: 0 | BF41: 0 | BG41: 0
E42: WACC | F42: 0.08 | G42: Based on a 9.3% cost of equity, a 4.9% pre-tax cost of debt (A- rating), and a 75/25 capital structure | U42: 37 | V42: Optimize | W42: COGS savings | X42: 3. Stay flexible | Y42: Program Governance | Z42: Bypass Standard Launch Gates to Meet SOP Deadline | AA42: Streamline or bypass select internal approval and validation steps to meet OEM SOP deadlines and avoid penalties, accepting higher rework risk in exchange for schedule adherence and cost savings. | AB42: 3 | AC42: 3 | AD42: 1 | AE42: 1 | AF42: 0 | AG42: -240 | AH42: 520.93755 | AI42: 0.26 | AJ42: 80 | AL42: Dilutive | AS42: 0 | AT42: 0 | AU42: 0 | AV42: 0 | AY42: 3 | AZ42: 0 | BA42: 1 | BB42: 80 | BD42: 0 | BE42: 0 | BF42: 0 | BG42: 0
E43: Cost of Equity | F43: 0.093 | G43: Assumes 0.9 beta | U43: 38 | V43: Optimize | W43: Manufacturing OH savings | X43: 1. Grow profitably | Y43: Factory of the Future | Z43: Energy Efficiency Program | AA43: Comprehensive energy efficiency upgrades across facilities. LED lighting, smart HVAC, and energy recovery systems. Strong ROI with added ESG benefits. | AB43: 3 | AC43: 1 | AD43: 1 | AE43: 2 | AF43: 0 | AG43: -120 | AH43: 241.06399 | AI43: 0.26 | AJ43: 40 | AL43: Accretive | AS43: 0 | AT43: 0 | AU43: 0 | AV43: 0 | AY43: 0 | AZ43: -120 | BA43: 2 | BB43: 40 | BD43: 0 | BE43: 0 | BF43: 0 | BG43: 0
E44: SG&A (default for growth decisions) | F44: 0.05 | G44: Based on 2024 Magna's levels | U44: 39 | V44: Optimize | W44: COGS savings | X44: 2. Cash is king | Y44: Organizational Restructure | Z44: Workforce Right-Sizing | AA44: Reduce headcount through voluntary separation and selective layoffs in response to cost pressures. Immediate savings but risk of losing key talent. | AB44: 3 | AC44: 4 | AD44: 1 | AE44: 1 | AF44: 0 | AG44: -360 | AH44: 781.40633 | AI44: 0.26 | AJ44: 120 | AL44: Accretive | AS44: 0 | AT44: 0 | AU44: 0 | AV44: 0 | AY44: 3 | AZ44: 0 | BA44: 1 | BB44: 120 | BD44: 0 | BE44: 0 | BF44: 0 | BG44: 0
E45: Long-term growth | F45: 0.02 | G45: Implied in the current share price | U45: 40 | V45: Optimize | W45: COGS savings | X45: 1. Grow profitably | Y45: Select Group Transformation | Z45: Plant Footprint Rationalization | AA45: Close underutilized manufacturing facilities and consolidate production. Significant restructuring cost but lasting margin improvement. | AB45: 3 | AC45: 4 | AD45: 4 | AE45: 1 | AF45: 0 | AG45: -180 | AH45: 952.64357 | AI45: 0.52 | AJ45: 120 | AL45: Accretive | AS45: 0 | AT45: 0 | AU45: 0 | AV45: 0 | AY45: 1.5 | AZ45: 0 | BA45: 1 | BB45: 120 | BD45: 0 | BE45: 0 | BF45: 0 | BG45: 0
E46: ROIC (M&A) | F46: 0.085 | U46: 41 | V46: Sustain | W46: Sustain Topline | X46: 1. Grow profitably | Y46: Portfolio management (maintenance) | Z46: Contract Renewal Defense | AA46: Invest in proactive retention programs—including dedicated renewal teams, pricing/offer analytics, and targeted customer incentives—to secure contract renewals in a more competitive environment and protect at-risk revenue. | AB46: 3 | AC46: 2 | AD46: 1 | AE46: 1 | AF46: 0 | AG46: -80 | AH46: -63.506579 | AI46: 0 | AJ46: 0 | AL46: Accretive | AS46: 0 | AT46: 0 | AU46: 0 | AV46: 0 | AY46: 0 | AZ46: 0 | BA46: 0 | BB46: 0 | BD46: 0 | BE46: -80 | BF46: 1 | BG46: 0 | BH46: No incremental cash flow created Avoid losing business-as-usual revenue -0.1% y-o-y
U47: 42 | V47: Sustain | W47: COGS savings | X47: 3. Stay flexible | Y47: Capital allocation strategy (maintenance) | Z47: Critical Equipment Maintenance | AA47: Essential maintenance program for production-critical equipment. Tempting to defer during cost pressure but failure would be catastrophic. | AB47: 3 | AC47: 3 | AD47: 1 | AE47: 1 | AF47: 0 | AG47: -240 | AH47: 520.93755 | AI47: 0.26 | AJ47: 80 | AL47: Accretive | AS47: 0 | AT47: 0 | AU47: 0 | AV47: 0 | AY47: 3 | AZ47: 0 | BA47: 0 | BB47: 0 | BD47: 3 | BE47: 0 | BF47: 1 | BG47: 80
U48: 43 | V48: Sustain | W48: Sustain Topline | X48: 1. Grow profitably | Y48: Talent & Leadership Upskilling | Z48: Key Talent Retention Program | AA48: Targeted retention incentives for critical technical and leadership talent. Important to maintain during cost pressures when competitors may poach. | AB48: 3 | AC48: 3 | AD48: 1 | AE48: 1 | AF48: 0 | AG48: -120 | AH48: -95.259869 | AI48: 0 | AJ48: 0 | AL48: Accretive | AS48: 0 | AT48: 0 | AU48: 0 | AV48: 0 | AY48: 0 | AZ48: 0 | BA48: 0 | BB48: 0 | BD48: 0 | BE48: -120 | BF48: 1 | BG48: 0 | BH48: No incremental cash flow created Avoid losing business-as-usual revenue -0.1% y-o-y
E49: Decision CF | U49: 44 | V49: Sustain | W49: Sustain Topline | X49: 3. Stay flexible | Y49: Risk & Compliance Upgrade | Z49: Business Continuity Enhancement | AA49: Strengthen business continuity planning and backup capabilities. Particularly important as risks increase during economic uncertainty. | AB49: 3 | AC49: 2 | AD49: 1 | AE49: 1 | AF49: 0 | AG49: -80 | AH49: -63.506579 | AI49: 0 | AJ49: 0 | AL49: Accretive | AS49: 0 | AT49: 0 | AU49: 0 | AV49: 0 | AY49: 0 | AZ49: 0 | BA49: 0 | BB49: 0 | BD49: 0 | BE49: -80 | BF49: 1 | BG49: 0 | BH49: No incremental cash flow created Avoid losing business-as-usual revenue -0.1% y-o-y
U50: 45 | V50: Sustain | W50: Sustain Topline | X50: 3. Stay flexible | Y50: Risk & Compliance Upgrade | Z50: Insurance Coverage Upgrade | AA50: Enhance insurance coverage for key operational and financial risks. Higher premiums but better protection against tail risks during uncertain times. | AB50: 3 | AC50: 1 | AD50: 1 | AE50: 1 | AF50: 0 | AG50: -40 | AH50: -31.75329 | AI50: 0 | AJ50: 0 | AL50: Accretive | AS50: 0 | AT50: 0 | AU50: 0 | AV50: 0 | AY50: 0 | AZ50: 0 | BA50: 0 | BB50: 0 | BD50: 0 | BE50: -40 | BF50: 1 | BG50: 0 | BH50: No incremental cash flow created Avoid losing business-as-usual revenue -0.1% y-o-y
U51: 46 | V51: Grow | W51: M&A / Divestments | X51: 1. Grow profitably | Y51: Acquire a Business | Z51: Opportunistic Acquisition - Premium Supplier | AA51: Rare opportunity to acquire premium supplier at recession-driven valuation. Strong customer relationships and margins. Requires significant capital during challenging times. | AB51: 4 | AC51: 5 | AD51: 4 | AE51: 1 | AF51: 1 | AG51: -15826.58 | AH51: 62.494834 | AI51: 0.081676148 | AJ51: 1932.612 | AK51: accretive with ROIC 15% | AL51: Accretive | AS51: 8000 | AT51: 0.1 | AU51: 0 | AV51: 0 | AW51: 0.11 | AY51: 0 | AZ51: 0 | BA51: 1 | BB51: 0 | BD51: 0 | BE51: 0 | BF51: 0 | BG51: 0
E52: Decision number | F52: 46 | U52: 47 | V52: Grow | W52: Organic | X52: 1. Grow profitably | Y52: Pricing Strategy | Z52: Aggressive pricing to win new business | AA52: Pursue new business using aggressive pricing mechanisms, accepting near-term dilution to drive volume growth and market entry. | AB52: 4 | AC52: 3 | AD52: 2 | AE52: 2 | AF52: 0 | AG52: -800 | AH52: -163.49815 | AI52: 0.0624 | AJ52: 89.6 | AK52: low growth bad capital turnover but high margin | AL52: Dilutive | AS52: 640 | AT52: 0 | AU52: -800 | AV52: 2 | AW52: 0.1 | AY52: 0 | AZ52: 0 | BA52: 0 | BB52: 0 | BD52: 0 | BE52: 0 | BF52: 0 | BG52: 0
D53: Do not delete | E53: Decision FCF | F53: Base Inputs | G53: R1 | H53: R2 | I53: R3 | J53: R4 | K53: R5 | L53: R6 | M53: R7 | N53: R8 | O53: R9 | P53: R10 | Q53: Long-Term | R53: Total | U53: 48 | V53: Grow | W53: Organic | X53: 1. Grow profitably | Y53: Enter New Geography / Market | Z53: Middle East Manufacturing Partnership | AA53: Partnership with Gulf state sovereign wealth fund for new manufacturing hub. Diversifies geographic exposure and provides capital, but execution complexity. | AB53: 4 | AC53: 3 | AD53: 1 | AE53: 2 | AF53: 0 | AG53: -800 | AH53: -143.04138 | AI53: 0.065842265 | AJ53: 121.55495 | AK53: high growth low margin | AL53: Accretive | AS53: 1200 | AT53: 0.03 | AU53: -800 | AV53: 2 | AW53: 0.05 | AY53: 0 | AZ53: 0 | BA53: 0 | BB53: 0 | BD53: 0 | BE53: 0 | BF53: 0 | BG53: 0
D54: 46 | E54: Investment | F54: 0 | G54: 0 | H54: 0 | I54: 0 | J54: 0 | K54: 0 | L54: 0 | M54: 0 | N54: 0 | O54: 0 | P54: 0 | R54: 0 | U54: 49 | V54: Grow | W54: Organic | X54: 1. Grow profitably | Y54: JV / Strategic Partnership | Z54: Hydrogen Fuel Cell Alliance | AA54: Join consortium developing hydrogen fuel cell technology for commercial vehicles. Hedges powertrain technology bets but requires ongoing investment with uncertain payoff timeline. | AB54: 4 | AC54: 2 | AD54: 3 | AE54: 2 | AF54: 0 | AG54: -600 | AH54: 75.652276 | AI54: 0.0936 | AJ54: 120 | AK54: close to cost of capital: 0% growth, 6% EBIT | AL54: Dilutive | AS54: 1200 | AT54: 0 | AU54: -600 | AV54: 2 | AW54: 0.06 | AY54: 0 | AZ54: 0 | BA54: 0 | BB54: 0 | BD54: 0 | BE54: 0 | BF54: 0 | BG54: 0
D55: 46 | E55: Implementation Cost | F55: 0 | G55: 0 | H55: 0 | I55: 0 | J55: 0 | K55: 0 | L55: 0 | M55: 0 | N55: 0 | O55: 0 | P55: 0 | R55: 0 | U55: 50 | V55: Grow | W55: Organic | X55: 1. Grow profitably | Y55: Expand Manufacturing Footprint | Z55: Underutilized Capacity Purchase | AA55: Purchase underutilized manufacturing facility from distressed competitor at significant discount. Ready infrastructure but requires investment to modernize. | AB55: 4 | AC55: 3 | AD55: 1 | AE55: 2 | AF55: 0 | AG55: -800 | AH55: -143.04138 | AI55: 0.065842265 | AJ55: 121.55495 | AK55: high growth low margin | AL55: Dilutive | AS55: 1200 | AT55: 0.03 | AU55: -800 | AV55: 2 | AW55: 0.05 | AY55: 0 | AZ55: 0 | BA55: 0 | BB55: 0 | BD55: 0 | BE55: 0 | BF55: 0 | BG55: 0
D56: 46 | E56: Acquision | F56: -13050.403 | G56: 0 | H56: 0 | I56: 0 | J56: -13050.403 | K56: 0 | L56: 0 | M56: 0 | N56: 0 | O56: 0 | P56: 0 | R56: -13050.403 | U56: 51 | V56: Optimize | W56: COGS savings | X56: 3. Stay flexible | Y56: Capital Timing | Z56: Material process flow automation | AA56: Execute material end-to-end process flow optimization, simplifying handoffs and eliminating waste to reduce cost, cycle time, and operational friction. | AB56: 4 | AC56: 2 | AD56: 1 | AE56: 1 | AF56: 0 | AG56: -120 | AH56: 244.59213 | AI56: 0.26 | AJ56: 40 | AL56: Accretive | AS56: 0 | AT56: 0 | AU56: 0 | AV56: 0 | AY56: 3 | AZ56: 0 | BA56: 1 | BB56: 40 | BD56: 0 | BE56: 0 | BF56: 0 | BG56: 0
D57: 46 | E57: Premium | F57: -2776.1767 | G57: 0 | H57: 0 | I57: 0 | J57: -2776.1767 | K57: 0 | L57: 0 | M57: 0 | N57: 0 | O57: 0 | P57: 0 | R57: -2776.1767 | U57: 52 | V57: Optimize | W57: M&A / Divestments | X57: 2. Cash is king | Y57: Divest Group | Z57: Strategic Asset Sale | AA57: Sell non-strategic real estate and equipment at recession-impacted valuations. Generates needed liquidity but may sell below intrinsic value. | AB57: 4 | AC57: 1 | AD57: 1 | AE57: 1 | AF57: 0 | AG57: 599.74597 | AH57: -141.05197 | AI57: 0.10004236 | AJ57: -108 | AK57: M&A (1 for Divestments) | AL57: Accretive | AS57: -1200 | AT57: 0 | AU57: 0 | AV57: 0 | AW57: 0.05 | AY57: 0 | AZ57: 0 | BA57: 1 | BB57: 0 | BD57: 0 | BE57: 0 | BF57: 0 | BG57: 0
D58: 46 | E58: Investments Total | F58: -13050.403 | G58: 0 | H58: 0 | I58: 0 | J58: -15826.58 | K58: 0 | L58: 0 | M58: 0 | N58: 0 | O58: 0 | P58: 0 | R58: -15826.58 | U58: 53 | V58: Optimize | W58: SGA savings | X58: 2. Cash is king | Y58: SG&A Optimization | Z58: Working from Home Optimization | AA58: Make remote work permanent for applicable roles. Reduce office space and associated costs. Maintains productivity while cutting real estate expenses. | AB58: 4 | AC58: 1 | AD58: 1 | AE58: 1 | AF58: 0 | AG58: -120 | AH58: 244.59213 | AI58: 0.26 | AJ58: 40 | AL58: Dilutive | AS58: 0 | AT58: 0 | AU58: 0 | AV58: 0 | AY58: 3 | AZ58: 0 | BA58: 1 | BB58: 40 | BD58: 0 | BE58: 0 | BF58: 0 | BG58: 0
D59: 46 | E59: Revenue | G59: 0 | H59: 0 | I59: 0 | J59: 0 | K59: 8000 | L59: 8000 | M59: 8000 | N59: 8000 | O59: 8000 | P59: 8000 | U59: 54 | V59: Optimize | W59: COGS savings | X59: 2. Cash is king | Y59: Global Supply Chain Redesign | Z59: Supplier Renegotiation Program | AA59: Leverage recession conditions to renegotiate supplier contracts. Risk of supplier relationship damage but significant cost reduction opportunity. | AB59: 4 | AC59: 3 | AD59: 1 | AE59: 1 | AF59: 0 | AG59: -240 | AH59: 489.18426 | AI59: 0.26 | AJ59: 80 | AL59: Accretive | AS59: 0 | AT59: 0 | AU59: 0 | AV59: 0 | AY59: 3 | AZ59: 0 | BA59: 1 | BB59: 80 | BD59: 0 | BE59: 0 | BF59: 0 | BG59: 0
D60: 46 | E60: Growth | G60: 0 | H60: 0 | I60: 0 | J60: 0 | K60: 0 | L60: 800 | M60: 1680 | N60: 2648 | O60: 3712.8 | P60: 4884.08 | U60: 55 | V60: Optimize | W60: Manufacturing OH savings | X60: 2. Cash is king | Y60: Enterprise Digital Transformation | Z60: Process Automation Acceleration | AA60: Accelerate robotic process automation for administrative tasks. Reduced headcount needs align with downturn-driven workforce reduction. | AB60: 4 | AC60: 2 | AD60: 1 | AE60: 1 | AF60: 0 | AG60: -120 | AH60: 244.59213 | AI60: 0.26 | AJ60: 40 | AL60: Accretive | AS60: 0 | AT60: 0 | AU60: 0 | AV60: 0 | AY60: 0 | AZ60: -120 | BA60: 1 | BB60: 40 | BD60: 0 | BE60: 0 | BF60: 0 | BG60: 0
D61: 46 | E61: Revenue Total | G61: 0 | H61: 0 | I61: 0 | J61: 0 | K61: 8000 | L61: 8800 | M61: 9680 | N61: 10648 | O61: 11712.8 | P61: 12884.08 | U61: 56 | V61: Sustain | W61: COGS savings | X61: 2. Cash is king | Y61: Organizational Restructure | Z61: Deep Cost Restructuring | AA61: Aggressive cost reduction program across all functions. Difficult decisions but necessary for survival in prolonged downturn. Risk of capability damage. | AB61: 4 | AC61: 5 | AD61: 1 | AE61: 1 | AF61: 0 | AG61: -480 | AH61: 978.36853 | AI61: 0.26 | AJ61: 160 | AL61: Dilutive | AS61: 0 | AT61: 0 | AU61: 0 | AV61: 0 | AY61: 3 | AZ61: 0 | BA61: 0 | BB61: 0 | BD61: 3 | BE61: 0 | BF61: 1 | BG61: 160
D62: 46 | E62: COGS | H62: 0 | I62: 0 | J62: 0 | K62: -6400 | L62: -7040 | M62: -7744 | N62: -8518.4 | O62: -9370.24 | P62: -10307.264 | U62: 57 | V62: Sustain | W62: COGS savings | X62: 3. Stay flexible | Y62: Risk & Compliance Upgrade | Z62: Regulatory Compliance Baseline | AA62: Fund mandatory regulatory compliance at the minimum required level, deliberately limiting scope to avoid incremental spend while maintaining license to operate. | AB62: 4 | AC62: 2 | AD62: 1 | AE62: 1 | AF62: 0 | AG62: -120 | AH62: 244.59213 | AI62: 0.26 | AJ62: 40 | AL62: Accretive | AS62: 0 | AT62: 0 | AU62: 0 | AV62: 0 | AY62: 3 | AZ62: 0 | BA62: 0 | BB62: 0 | BD62: 3 | BE62: 0 | BF62: 1 | BG62: 40
D63: 46 | E63: SG&A | H63: 0 | I63: 0 | J63: 0 | K63: -400 | L63: -440 | M63: -484 | N63: -532.4 | O63: -585.64 | P63: -644.204 | U63: 58 | V63: Sustain | W63: Sustain Topline | X63: 1. Grow profitably | Y63: Capital allocation strategy (maintenance) | Z63: Minimum Viable Maintenance | AA63: Bare minimum maintenance investment to keep operations running. Risk of equipment failure but preserves cash during severe downturn. | AB63: 4 | AC63: 2 | AD63: 1 | AE63: 1 | AF63: 0 | AG63: -80 | AH63: -58.802388 | AI63: 0 | AJ63: 0 | AL63: Accretive | AS63: 0 | AT63: 0 | AU63: 0 | AV63: 0 | AY63: 0 | AZ63: 0 | BA63: 0 | BB63: 0 | BD63: 0 | BE63: -80 | BF63: 1 | BG63: 0 | BH63: No incremental cash flow created Avoid losing business-as-usual revenue -0.1% y-o-y
D64: 46 | E64: EBITDA | G64: 0 | H64: 0 | I64: 0 | J64: 0 | K64: 1200 | L64: 1320 | M64: 1452 | N64: 1597.2 | O64: 1756.92 | P64: 1932.612 | U64: 59 | V64: Sustain | W64: Sustain Topline | X64: 1. Grow profitably | Y64: Talent & Leadership Upskilling | Z64: Core Team Preservation | AA64: Investment to retain absolutely critical talent through recession. Skeletal but essential team for recovery. Others may be rehired post-downturn. | AB64: 4 | AC64: 3 | AD64: 1 | AE64: 1 | AF64: 0 | AG64: -120 | AH64: -88.203582 | AI64: 0 | AJ64: 0 | AL64: Accretive | AS64: 0 | AT64: 0 | AU64: 0 | AV64: 0 | AY64: 0 | AZ64: 0 | BA64: 0 | BB64: 0 | BD64: 0 | BE64: -120 | BF64: 1 | BG64: 0 | BH64: No incremental cash flow created Avoid losing business-as-usual revenue -0.1% y-o-y
D65: 46 | E65: COGS savings | H65: 0 | I65: 0 | J65: 0 | K65: 0 | L65: 0 | M65: 0 | N65: 0 | O65: 0 | P65: 0 | U65: 60 | V65: Sustain | W65: SGA savings | X65: 3. Stay flexible | Y65: Risk & Compliance Upgrade | Z65: Financial Risk Management | AA65: Enhanced treasury and financial risk management during volatile conditions. Hedge exposures and manage liquidity carefully. | AB65: 4 | AC65: 2 | AD65: 1 | AE65: 1 | AF65: 0 | AG65: -120 | AH65: 244.59213 | AI65: 0.26 | AJ65: 40 | AL65: Accretive | AS65: 0 | AT65: 0 | AU65: 0 | AV65: 0 | AY65: 3 | AZ65: 0 | BA65: 0 | BB65: 0 | BD65: 3 | BE65: 0 | BF65: 1 | BG65: 40
D66: 46 | E66: Manufacturing OH savings | H66: 0 | I66: 0 | J66: 0 | K66: 0 | L66: 0 | M66: 0 | N66: 0 | O66: 0 | P66: 0 | U66: 61 | V66: Grow | W66: Organic | X66: 2. Cash is king | Y66: Commercial Prioritization | Z66: Prioritize Commercial Recoveries to win business | AA66: Leverage commercial recoveries as negotiation tools to win new business, using offset economics to secure contracts while remaining net-accretive. | AB66: 5 | AC66: 3 | AD66: 4 | AE66: 2 | AF66: 0 | AG66: -800 | AH66: 908.38403 | AI66: 0.19864845 | AJ66: 277.83 | AK66: accretive with ROIC 15% | AL66: Accretive | AS66: 1600 | AT66: 0.05 | AU66: -800 | AV66: 2 | AW66: 0.11 | AY66: 0 | AZ66: 0 | BA66: 0 | BB66: 0 | BD66: 0 | BE66: 0 | BF66: 0 | BG66: 0
D67: 46 | E67: SG&A savings | H67: 0 | I67: 0 | J67: 0 | K67: 0 | L67: 0 | M67: 0 | N67: 0 | O67: 0 | P67: 0 | U67: 62 | V67: Grow | W67: Organic | X67: 1. Grow profitably | Y67: Expand Manufacturing Footprint | Z67: Global Capacity Expansion Program | AA67: Comprehensive capacity expansion across multiple regions to meet recovering demand. Significant investment but positions for sustainable growth trajectory. | AB67: 5 | AC67: 5 | AD67: 2 | AE67: 2 | AF67: 0 | AG67: -1000 | AH67: -191.26516 | AI67: 0.0624 | AJ67: 112 | AK67: low growth bad capital turnover but high margin | AL67: Accretive | AS67: 800 | AT67: 0 | AU67: -1000 | AV67: 2 | AW67: 0.1 | AY67: 0 | AZ67: 0 | BA67: 0 | BB67: 0 | BD67: 0 | BE67: 0 | BF67: 0 | BG67: 0
D68: 46 | E68: Synergies | H68: 0 | I68: 0 | J68: 0 | K68: 240 | L68: 240 | M68: 240 | N68: 240 | O68: 240 | P68: 240 | U68: 63 | V68: Grow | W68: M&A / Divestments | X68: 1. Grow profitably | Y68: Acquire a Business | Z68: Strategic Technology Acquisition | AA68: Acquire emerging technology company with breakthrough thermal management system for advanced vehicles. Positions for next-generation vehicle requirements. Premium valuation as market recovers. | AB68: 5 | AC68: 4 | AD68: 2 | AE68: 1 | AF68: 0 | AG68: -7391.041 | AH68: 80.190721 | AI68: 0.080648872 | AJ68: 878.46 | AK68: low growth bad capital turnover but high margin | AL68: Dilutive | AS68: 4000 | AT68: 0.1 | AU68: 0 | AV68: 0 | AW68: 0.11 | AY68: 0 | AZ68: 0 | BA68: 1 | BB68: 0 | BD68: 0 | BE68: 0 | BF68: 0 | BG68: 0
D69: 46 | E69: EBITDA | G69: 0 | H69: 0 | I69: 0 | J69: 0 | K69: 1440 | L69: 1560 | M69: 1692 | N69: 1837.2 | O69: 1996.92 | P69: 2172.612 | U69: 64 | V69: Grow | W69: Organic | X69: 1. Grow profitably | Y69: JV / Strategic Partnership | Z69: OEM Strategic Alliance | AA69: Deep strategic partnership with major OEM for exclusive supply arrangements. Secures significant volume but concentration risk. Attractive terms as OEM seeks reliable supplier. | AB69: 5 | AC69: 4 | AD69: 3 | AE69: 2 | AF69: 0 | AG69: -1000 | AH69: 119.53336 | AI69: 0.0936 | AJ69: 200 | AK69: close to cost of capital: 0% growth, 6% EBIT | AL69: Dilutive | AS69: 2000 | AT69: 0 | AU69: -1000 | AV69: 2 | AW69: 0.06 | AY69: 0 | AZ69: 0 | BA69: 0 | BB69: 0 | BD69: 0 | BE69: 0 | BF69: 0 | BG69: 0
D70: 46 | E70: Taxes | F70: 0.22 | G70: 0 | H70: 0 | I70: 0 | J70: 0 | K70: -246.4 | L70: -265.76 | M70: -287.056 | N70: -310.4816 | O70: -336.24976 | P70: -364.59474 | U70: 65 | V70: Grow | W70: Organic | X70: 1. Grow profitably | Y70: Launch a New Business | Z70: Mobility Services Platform | AA70: Launch platform to support fleet operators and mobility-as-a-service providers. Diversifies revenue model and creates recurring revenue streams. | AB70: 5 | AC70: 3 | AD70: 1 | AE70: 1 | AF70: 0 | AG70: -800 | AH70: -121.26271 | AI70: 0.065842265 | AJ70: 121.55495 | AK70: high growth low margin | AL70: Dilutive | AS70: 1200 | AT70: 0.03 | AU70: -800 | AV70: 1 | AW70: 0.05 | AY70: 0 | AZ70: 0 | BA70: 0 | BB70: 0 | BD70: 0 | BE70: 0 | BF70: 0 | BG70: 0
D71: 46 | E71: Capex maintenance | F71: 0.04 | H71: 0 | I71: 0 | J71: 0 | K71: -320 | L71: -352 | M71: -387.2 | N71: -425.92 | O71: -468.512 | P71: -515.3632 | U71: 66 | V71: Grow | W71: Organic | X71: 1. Grow profitably | Y71: Scale R&D for Next-Gen Portfolio | Z71: Next-Gen ADAS Development | AA71: Accelerate development of Level 4 autonomous driving capabilities. Recovery enables increased R&D spending. Positions for 2030s autonomous vehicle requirements. | AB71: 5 | AC71: 4 | AD71: 4 | AE71: 1 | AF71: 0 | AG71: -1000 | AH71: 1315.8275 | AI71: 0.20858087 | AJ71: 364.65187 | AK71: accretive with ROIC 15% | AL71: Accretive | AS71: 2000 | AT71: 0.05 | AU71: -1000 | AV71: 1 | AW71: 0.11 | AY71: 0 | AZ71: 0 | BA71: 0 | BB71: 0 | BD71: 0 | BE71: 0 | BF71: 0 | BG71: 0
D72: 46 | E72: Free Cash Flow | G72: 0 | H72: 0 | I72: 0 | J72: -15826.58 | K72: 873.6 | L72: 942.24 | M72: 1017.744 | N72: 1100.7984 | O72: 1192.1582 | P72: 1292.6541 | Q72: 1318.5071 | R72: -9407.3851 | U72: 67 | V72: Optimize | W72: COGS savings | X72: 1. Grow profitably | Y72: Enterprise Digital Transformation | Z72: AI Operations Platform | AA72: Deploy AI-powered operations management platform. Advanced demand forecasting, production scheduling, and quality prediction. Next-level efficiency. | AB72: 5 | AC72: 3 | AD72: 2 | AE72: 1 | AF72: 0 | AG72: -200 | AH72: 493.30583 | AI72: 0.312 | AJ72: 80 | AL72: Accretive | AS72: 0 | AT72: 0 | AU72: 0 | AV72: 0 | AY72: 2.5 | AZ72: 0 | BA72: 1 | BB72: 80 | BD72: 0 | BE72: 0 | BF72: 0 | BG72: 0
D73: 46 | E73: Continuing Value (growth) | F73: 0.02 | P73: 17537.982 | R73: 17537.982 | U73: 68 | V73: Optimize | W73: COGS savings | X73: 2. Cash is king | Y73: Global Supply Chain Redesign | Z73: Inventory Optimization | AA73: Implement advanced inventory management to reduce working capital requirements. Risk of stockouts during supply disruptions but significant cash release. | AB73: 5 | AC73: 2 | AD73: 3 | AE73: 1 | AF73: 0 | AG73: -80 | AH73: 263.41429 | AI73: 0.39 | AJ73: 40 | AK73: Looks like one-time cash release? | AL73: Accretive | AS73: 0 | AT73: 0 | AU73: 0 | AV73: 0 | AY73: 2 | AZ73: 0 | BA73: 1 | BB73: 40 | BD73: 0 | BE73: 0 | BF73: 0 | BG73: 0
D74: 46 | E74: WACC | F74: 0.08 | U74: 69 | V74: Optimize | W74: SGA savings | X74: 2. Cash is king | Y74: SG&A Optimization | Z74: Sales Force Effectiveness | AA74: Restructure the sales organization with targeted investment in CRM, analytics, and coverage model redesign, shifting from relationship-led to data-driven account management to improve customer coverage while reducing overall sales headcount. | AB74: 5 | AC74: 2 | AD74: 1 | AE74: 1 | AF74: 0 | AG74: -120 | AH74: 229.89153 | AI74: 0.26 | AJ74: 40 | AL74: Accretive | AS74: 0 | AT74: 0 | AU74: 0 | AV74: 0 | AY74: 3 | AZ74: 0 | BA74: 1 | BB74: 40 | BD74: 0 | BE74: 0 | BF74: 0 | BG74: 0
E75: NPV | F75: 62.494834 | U75: 70 | V75: Optimize | W75: COGS savings | X75: 3. Stay flexible | Y75: Global Supply Chain Redesign | Z75: Near-Shoring Initiative | AA75: Shift supply chain closer to end markets. Higher unit costs offset by reduced logistics, inventory, and disruption risk. Resilience investment. | AB75: 5 | AC75: 3 | AD75: 1 | AE75: 1 | AF75: 0 | AG75: -240 | AH75: 459.78307 | AI75: 0.26 | AJ75: 80 | AL75: Accretive | AS75: 0 | AT75: 0 | AU75: 0 | AV75: 0 | AY75: 3 | AZ75: 0 | BA75: 1 | BB75: 80 | BD75: 0 | BE75: 0 | BF75: 0 | BG75: 0
E76: ROI | F76: 0.099050892 | U76: 71 | V76: Optimize | W76: Manufacturing OH savings | X76: 1. Grow profitably | Y76: Factory of the Future | Z76: Full Smart Factory Rollout | AA76: Expand proven smart factory technologies across global manufacturing footprint. Recovery positions for investment. Strong ROI from scale. | AB76: 5 | AC76: 4 | AD76: 1 | AE76: 1 | AF76: 0 | AG76: -360 | AH76: 689.6746 | AI76: 0.26 | AJ76: 120 | AL76: Accretive | AS76: 0 | AT76: 0 | AU76: 0 | AV76: 0 | AY76: 0 | AZ76: -360 | BA76: 1 | BB76: 120 | BD76: 0 | BE76: 0 | BF76: 0 | BG76: 0
U77: 72 | V77: Sustain | W77: Sustain Topline | X77: 1. Grow profitably | Y77: Capital allocation strategy (maintenance) | Z77: Deferred Maintenance Catch-Up | AA77: Address deferred maintenance from recession period. Essential to restore equipment reliability for recovery. May require higher spend than normal. | AB77: 5 | AC77: 3 | AD77: 1 | AE77: 1 | AF77: 0 | AG77: -120 | AH77: -81.669984 | AI77: 0 | AJ77: 0 | AL77: Accretive | AS77: 0 | AT77: 0 | AU77: 0 | AV77: 0 | AY77: 0 | AZ77: 0 | BA77: 0 | BB77: 0 | BD77: 0 | BE77: -120 | BF77: 1 | BG77: 0 | BH77: No incremental cash flow created Avoid losing business-as-usual revenue -0.1% y-o-y
E78: Revenue growth | L78: 0.1 | M78: 0.1 | N78: 0.1 | O78: 0.1 | P78: 0.1 | U78: 73 | V78: Sustain | W78: Sustain Topline | X78: 1. Grow profitably | Y78: Talent & Leadership Upskilling | Z78: Workforce Rebuilding Program | AA78: Rehire and retrain workforce for recovery volumes. Compete for talent returning to job market. Investment in recruiting and onboarding. | AB78: 5 | AC78: 3 | AD78: 1 | AE78: 1 | AF78: 0 | AG78: -120 | AH78: -81.669984 | AI78: 0 | AJ78: 0 | AL78: Accretive | AS78: 0 | AT78: 0 | AU78: 0 | AV78: 0 | AY78: 0 | AZ78: 0 | BA78: 0 | BB78: 0 | BD78: 0 | BE78: -120 | BF78: 1 | BG78: 0 | BH78: No incremental cash flow created Avoid losing business-as-usual revenue -0.1% y-o-y
E79: EBITDA margin | K79: 0.18 | L79: 0.17727273 | M79: 0.17479339 | N79: 0.17253944 | O79: 0.1704904 | P79: 0.16862764 | U79: 74 | V79: Sustain | W79: Sustain Topline | X79: 1. Grow profitably | Y79: Risk & Compliance Upgrade | Z79: ESG & Sustainability Investment | AA79: Comprehensive ESG program to meet growing stakeholder expectations. Carbon reduction, sustainable materials, and governance enhancement. | AB79: 5 | AC79: 1 | AD79: 1 | AE79: 1 | AF79: 0 | AG79: -40 | AH79: -27.223328 | AI79: 0 | AJ79: 0 | AL79: Accretive | AS79: 0 | AT79: 0 | AU79: 0 | AV79: 0 | AY79: 0 | AZ79: 0 | BA79: 0 | BB79: 0 | BD79: 0 | BE79: -40 | BF79: 1 | BG79: 0 | BH79: No incremental cash flow created Avoid losing business-as-usual revenue -0.1% y-o-y
E80: ROIC | J80: -1 | K80: 0.066940461 | L80: 0.072200069 | M80: 0.077985637 | N80: 0.084349762 | O80: 0.0913503 | P80: 0.099050892 | U80: 75 | V80: Sustain | W80: Sustain Topline | X80: 1. Grow profitably | Y80: Risk & Compliance Upgrade | Z80: Post-Crisis Risk Assessment | AA80: Comprehensive review and update of risk management framework based on lessons learned. Prepare for next downturn while positioned for recovery. | AB80: 5 | AC80: 1 | AD80: 2 | AE80: 1 | AF80: 0 | AG80: -40 | AH80: -27.223328 | AI80: 0 | AJ80: 0 | AL80: Accretive | AS80: 0 | AT80: 0 | AU80: 0 | AV80: 0 | AY80: 0 | AZ80: 0 | BA80: 0 | BB80: 0 | BD80: 0 | BE80: -40 | BF80: 1 | BG80: 0 | BH80: No incremental cash flow created Avoid losing business-as-usual revenue -0.1% y-o-y
AG82: -68196.091 | AH82: 15446.09 | AJ82: 10766.389
E83: Consolidated CF | AO83: Revenue change | AP83: 0 | AQ83: 0 | AR83: 0 | AS83: 0 | AT83: 0 | AU83: 0 | AV83: 0 | AW83: 0 | AX83: 0 | AY83: 0 | BF83: Revenue change | BG83: 0 | BH83: 0 | BI83: 0 | BJ83: 0 | BK83: 0 | BL83: 0 | BM83: 0 | BN83: 0 | BO83: 0 | BP83: 0
E84: Base scenario | AN84: Recession | AP84: 1 | AQ84: 1 | AR84: 1 | AS84: 1 | AT84: 1 | AU84: 1 | AV84: 1 | AW84: 1 | AX84: 1 | AY84: 1 | BE84: Recovery | BG84: 1 | BH84: 1 | BI84: 1 | BJ84: 1 | BK84: 1 | BL84: 1 | BM84: 1 | BN84: 1 | BO84: 1 | BP84: 1 | BQ84: 1
E86: Consolidated Decision FCF | F86: Base Inputs | G86: R1 | H86: R2 | I86: R3 | J86: R4 | K86: R5 | L86: R6 | M86: R7 | N86: R8 | O86: R9 | P86: R10 | Q86: Long-Term | R86: Total | AN86: Consolidated Decision FCF | AP86: R1 | AQ86: R2 | AR86: R3 | AS86: R4 | AT86: R5 | AU86: R6 | AV86: R7 | AW86: R8 | AX86: R9 | AY86: R10 | AZ86: Long-Term | BA86: Total | BE86: Consolidated Decision FCF | BF86: 0 | BG86: R1 | BH86: R2 | BI86: R3 | BJ86: R4 | BK86: R5 | BL86: R6 | BM86: R7 | BN86: R8 | BO86: R9 | BP86: R10 | BQ86: Long-Term | BR86: Total
E87: Investment | F87: 0 | G87: 0 | H87: 0 | I87: 0 | J87: 0 | K87: 0 | L87: 0 | M87: 0 | N87: 0 | O87: 0 | P87: 0 | R87: 0 | AN87: Investment | AP87: 0 | AQ87: 0 | AR87: 0 | AS87: 0 | AT87: 0 | AU87: 0 | AV87: 0 | AW87: 0 | AX87: 0 | AY87: 0 | BA87: 0 | BE87: Investment | BG87: 0 | BH87: 0 | BI87: 0 | BJ87: 0 | BK87: 0 | BL87: 0 | BM87: 0 | BN87: 0 | BO87: 0 | BP87: 0 | BQ87: 0 | BR87: 0
E88: Implementation Cost | F88: 0 | G88: 0 | H88: 0 | I88: 0 | J88: 0 | K88: 0 | L88: 0 | M88: 0 | N88: 0 | O88: 0 | P88: 0 | R88: 0 | AN88: Implementation Cost | AP88: 0 | AQ88: 0 | AR88: 0 | AS88: 0 | AT88: 0 | AU88: 0 | AV88: 0 | AW88: 0 | AX88: 0 | AY88: 0 | BA88: 0 | BE88: Implementation Cost | BG88: 0 | BH88: 0 | BI88: 0 | BJ88: 0 | BK88: 0 | BL88: 0 | BM88: 0 | BN88: 0 | BO88: 0 | BP88: 0
E89: Acquision | F89: -13050.403 | G89: 0 | H89: 0 | I89: 0 | J89: -13050.403 | K89: 0 | L89: 0 | M89: 0 | N89: 0 | O89: 0 | P89: 0 | R89: -13050.403 | AN89: Acquision | AP89: 0 | AQ89: 0 | AR89: 0 | AS89: -13050.403 | AT89: 0 | AU89: 0 | AV89: 0 | AW89: 0 | AX89: 0 | AY89: 0 | BA89: -13050.403 | BE89: Acquision | BG89: 0 | BH89: 0 | BI89: 0 | BJ89: -13050.403 | BK89: 0 | BL89: 0 | BM89: 0 | BN89: 0 | BO89: 0 | BP89: 0 | BR89: -13050.403
E90: Premium | F90: -2776.1767 | G90: 0 | H90: 0 | I90: 0 | J90: -2776.1767 | K90: 0 | L90: 0 | M90: 0 | N90: 0 | O90: 0 | P90: 0 | R90: -2776.1767 | AN90: Premium | AP90: 0 | AQ90: 0 | AR90: 0 | AS90: -2776.1767 | AT90: 0 | AU90: 0 | AV90: 0 | AW90: 0 | AX90: 0 | AY90: 0 | BA90: -2776.1767 | BE90: Premium
E91: Investments Total | F91: -13050.403 | G91: 0 | H91: 0 | I91: 0 | J91: -15826.58 | K91: 0 | L91: 0 | M91: 0 | N91: 0 | O91: 0 | P91: 0 | R91: -15826.58 | AN91: Investments Total | AP91: 0 | AQ91: 0 | AR91: 0 | AS91: -13050.403 | AT91: 0 | AU91: 0 | AV91: 0 | AW91: 0 | AX91: 0 | AY91: 0 | BA91: -13050.403 | BE91: Investments Total | BG91: 0 | BH91: 0 | BI91: 0 | BJ91: -13050.403 | BK91: 0 | BL91: 0 | BM91: 0 | BN91: 0 | BO91: 0 | BP91: 0 | BQ91: -13050.403 | BR91: -13050.403
E92: Revenue | F92: x | G92: 0 | H92: 0 | I92: 0 | J92: 0 | K92: 8000 | L92: 8000 | M92: 8000 | N92: 8000 | O92: 8000 | P92: 8000 | AN92: Revenue | AP92: 0 | AQ92: 0 | AR92: 0 | AS92: 0 | AT92: 8000 | AU92: 8000 | AV92: 8000 | AW92: 8000 | AX92: 8000 | AY92: 8000 | BE92: Revenue | BG92: 0 | BH92: 0 | BI92: 0 | BJ92: 0 | BK92: 8000 | BL92: 8000 | BM92: 8000 | BN92: 8000 | BO92: 8000 | BP92: 8000
E93: Growth | F93: x | G93: 0 | H93: 0 | I93: 0 | J93: 0 | K93: 0 | L93: 800 | M93: 1680 | N93: 2648 | O93: 3712.8 | P93: 4884.08 | AN93: Growth | AP93: 0 | AQ93: 0 | AR93: 0 | AS93: 0 | AT93: 0 | AU93: 800 | AV93: 1680 | AW93: 2648 | AX93: 3712.8 | AY93: 4884.08 | BE93: Growth | BG93: 0 | BH93: 0 | BI93: 0 | BJ93: 0 | BK93: 0 | BL93: 800 | BM93: 1680 | BN93: 2648 | BO93: 3712.8 | BP93: 4884.08
E94: Revenue Total | G94: 0 | H94: 0 | I94: 0 | J94: 0 | K94: 8000 | L94: 8800 | M94: 9680 | N94: 10648 | O94: 11712.8 | P94: 12884.08 | AN94: Revenue Total | AP94: 0 | AQ94: 0 | AR94: 0 | AS94: 0 | AT94: 8000 | AU94: 8800 | AV94: 9680 | AW94: 10648 | AX94: 11712.8 | AY94: 12884.08 | BE94: Revenue Total | BG94: 0 | BH94: 0 | BI94: 0 | BJ94: 0 | BK94: 8000 | BL94: 8800 | BM94: 9680 | BN94: 10648 | BO94: 11712.8 | BP94: 12884.08
E95: COGS | G95: 0 | H95: 0 | I95: 0 | J95: 0 | K95: -6400 | L95: -7040 | M95: -7744 | N95: -8518.4 | O95: -9370.24 | P95: -10307.264 | AN95: COGS | AP95: 0 | AQ95: 0 | AR95: 0 | AS95: 0 | AT95: -6400 | AU95: -7040 | AV95: -7744 | AW95: -8518.4 | AX95: -9370.24 | AY95: -10307.264 | BE95: COGS | BG95: 0 | BH95: 0 | BI95: 0 | BJ95: 0 | BK95: -6400 | BL95: -7040 | BM95: -7744 | BN95: -8518.4 | BO95: -9370.24 | BP95: -10307.264
E96: SG&A | G96: 0 | H96: 0 | I96: 0 | J96: 0 | K96: -400 | L96: -440 | M96: -484 | N96: -532.4 | O96: -585.64 | P96: -644.204 | AN96: SG&A | AP96: 0 | AQ96: 0 | AR96: 0 | AS96: 0 | AT96: -400 | AU96: -440 | AV96: -484 | AW96: -532.4 | AX96: -585.64 | AY96: -644.204 | BE96: SG&A | BG96: 0 | BH96: 0 | BI96: 0 | BJ96: 0 | BK96: -400 | BL96: -440 | BM96: -484 | BN96: -532.4 | BO96: -585.64 | BP96: -644.204
E97: EBITDA | F97: x | G97: 0 | H97: 0 | I97: 0 | J97: 0 | K97: 1200 | L97: 1320 | M97: 1452 | N97: 1597.2 | O97: 1756.92 | P97: 1932.612 | AN97: EBITDA | AP97: 0 | AQ97: 0 | AR97: 0 | AS97: 0 | AT97: 1200 | AU97: 1320 | AV97: 1452 | AW97: 1597.2 | AX97: 1756.92 | AY97: 1932.612 | BE97: EBITDA | BG97: 0 | BH97: 0 | BI97: 0 | BJ97: 0 | BK97: 1200 | BL97: 1320 | BM97: 1452 | BN97: 1597.2 | BO97: 1756.92 | BP97: 1932.612
E98: COGS savings | F98: x | G98: 0 | H98: 0 | I98: 0 | J98: 0 | K98: 0 | L98: 0 | M98: 0 | N98: 0 | O98: 0 | P98: 0 | AN98: COGS savings | AP98: 0 | AQ98: 0 | AR98: 0 | AS98: 0 | AT98: 0 | AU98: 0 | AV98: 0 | AW98: 0 | AX98: 0 | AY98: 0 | BE98: COGS savings | BG98: 0 | BH98: 0 | BI98: 0 | BJ98: 0 | BK98: 0 | BL98: 0 | BM98: 0 | BN98: 0 | BO98: 0 | BP98: 0
E99: Manufacturing OH savings | G99: 0 | H99: 0 | I99: 0 | J99: 0 | K99: 0 | L99: 0 | M99: 0 | N99: 0 | O99: 0 | P99: 0 | AN99: Manufacturing OH savings | AP99: 0 | AQ99: 0 | AR99: 0 | AS99: 0 | AT99: 0 | AU99: 0 | AV99: 0 | AW99: 0 | AX99: 0 | AY99: 0 | BE99: Manufacturing OH savings | BG99: 0 | BH99: 0 | BI99: 0 | BJ99: 0 | BK99: 0 | BL99: 0 | BM99: 0 | BN99: 0 | BO99: 0 | BP99: 0
E100: SG&A savings | G100: 0 | H100: 0 | I100: 0 | J100: 0 | K100: 0 | L100: 0 | M100: 0 | N100: 0 | O100: 0 | P100: 0 | AN100: SG&A savings | AP100: 0 | AQ100: 0 | AR100: 0 | AS100: 0 | AT100: 0 | AU100: 0 | AV100: 0 | AW100: 0 | AX100: 0 | AY100: 0 | BE100: SG&A savings | BG100: 0 | BH100: 0 | BI100: 0 | BJ100: 0 | BK100: 0 | BL100: 0 | BM100: 0 | BN100: 0 | BO100: 0 | BP100: 0
E101: Synergies | G101: 0 | H101: 0 | I101: 0 | J101: 0 | K101: 240 | L101: 240 | M101: 240 | N101: 240 | O101: 240 | P101: 240 | AN101: Synergies | AP101: 0 | AQ101: 0 | AR101: 0 | AS101: 0 | AT101: 240 | AU101: 240 | AV101: 240 | AW101: 240 | AX101: 240 | AY101: 240 | BE101: Synergies | BG101: 0 | BH101: 0 | BI101: 0 | BJ101: 0 | BK101: 240 | BL101: 240 | BM101: 240 | BN101: 240 | BO101: 240 | BP101: 240
E102: EBITDA | G102: 0 | H102: 0 | I102: 0 | J102: 0 | K102: 1440 | L102: 1560 | M102: 1692 | N102: 1837.2 | O102: 1996.92 | P102: 2172.612 | AN102: EBITDA | AP102: 0 | AQ102: 0 | AR102: 0 | AS102: 0 | AT102: 1440 | AU102: 1560 | AV102: 1692 | AW102: 1837.2 | AX102: 1996.92 | AY102: 2172.612 | BE102: EBITDA | BG102: 0 | BH102: 0 | BI102: 0 | BJ102: 0 | BK102: 1440 | BL102: 1560 | BM102: 1692 | BN102: 1837.2 | BO102: 1996.92 | BP102: 2172.612
E103: Taxes | F103: 0.22 | G103: 0 | H103: 0 | I103: 0 | J103: 0 | K103: -246.4 | L103: -265.76 | M103: -287.056 | N103: -310.4816 | O103: -336.24976 | P103: -364.59474 | AN103: Taxes | AQ103: 0 | AR103: 0 | AS103: 0 | AT103: -246.4 | AU103: -265.76 | AV103: -287.056 | AW103: -310.4816 | AX103: -336.24976 | AY103: -364.59474 | BE103: Taxes | BG103: 0 | BH103: 0 | BI103: 0 | BJ103: 0 | BK103: -246.4 | BL103: -265.76 | BM103: -287.056 | BN103: -310.4816 | BO103: -336.24976 | BP103: -364.59474
E104: Capex maintenance | F104: 0.04 | H104: 0 | I104: 0 | J104: 0 | K104: -320 | L104: -352 | M104: -387.2 | N104: -425.92 | O104: -468.512 | P104: -515.3632 | AN104: Capex maintenance | AQ104: 0 | AR104: 0 | AS104: 0 | AT104: -320 | AU104: -352 | AV104: -387.2 | AW104: -425.92 | AX104: -468.512 | AY104: -515.3632 | BE104: Capex maintenance | BG104: 0 | BH104: 0 | BI104: 0 | BJ104: 0 | BK104: -320 | BL104: -352 | BM104: -387.2 | BN104: -425.92 | BO104: -468.512 | BP104: -515.3632
...

Sheet Output
P2: Ungroup to see Decisions consolidated | AU2: Ungroup to see Intermediate calculations | BK2: Ungroup to see No-Decision Simulation
B4: Simplified financials
B5: Currency: USD Millions
B7: Legend
B8: Calculations and same-sheet references
B9: Formula includes links to other sheets within same file | AG9: Turn On Round | AI9: 1 | AJ9: 1 | AK9: 1 | AL9: 1 | AM9: 1
B10: Assumption/input | AV10: Continuing Value (growth) | AW10: =BG60 -> 0.02 | AY10: WACC | AZ10: =Decisions!F42 -> 0.08
B12: Simulation - Results | Q12: Simulations - Decisions | AG12: Simulation - Intermediate | AH12: Includes the impact of selected Sustain Revenue Decisions. To see No Decision Simulation refer to BL:BX | AV12: Business-As-Usual | BL12: Simulation - No Decisions
C14: =AH14 -> 2025 | D14: =AI14 -> 2026 | E14: =AJ14 -> 2027 | F14: =AK14 -> 2028 | G14: =AL14 -> 2029 | H14: =AM14 -> 2030 | I14: =AN14 -> 2031 | J14: =AO14 -> 2032 | ... N14: =AS14 -> Long-Term | O14: Total | Q14: Consolidated Decision FCF | R14: =AH14 -> 2025 | S14: =AI14 -> 2026 | T14: =AJ14 -> 2027 | U14: =AK14 -> 2028 | V14: =AL14 -> 2029 | W14: =AM14 -> 2030 | X14: =AN14 -> 2031 | Y14: =AO14 -> 2032 | ... AC14: =AS14 -> Long-Term | AD14: Total | AH14: =AW14 -> 2025 | AI14: =AX14 -> 2026 | AJ14: =AY14 -> 2027 | AK14: =AZ14 -> 2028 | AL14: =BA14 -> 2029 | AM14: =BB14 -> 2030 | AN14: =BC14 -> 2031 | AO14: =BD14 -> 2032 | ... AS14: =BH14 -> Long-Term | AT14: Total | AW14: 2025 | AX14: =AW14+1 -> 2026 | AY14: =AX14+1 -> 2027 | AZ14: =AY14+1 -> 2028 | BA14: =AZ14+1 -> 2029 | BB14: =BA14+1 -> 2030 | BC14: =BB14+1 -> 2031 | BD14: =BC14+1 -> 2032 | BE14: =BD14+1 -> 2033 | ... BG14: =BF14+1 -> 2035 | BH14: Long-Term | BM14: =AH14 -> 2025 | BN14: =AI14 -> 2026 | BO14: =AJ14 -> 2027 | BP14: =AK14 -> 2028 | BQ14: =AL14 -> 2029 | BR14: =AM14 -> 2030 | BS14: =AN14 -> 2031 | BT14: =AO14 -> 2032 | ... BX14: =AS14 -> Long-Term
B15: Investment | C15: =R15+AH15 -> 0 | D15: =S15+AI15 -> 0 | E15: =T15+AJ15 -> 0 | F15: =U15+AK15 -> 0 | G15: =V15+AL15 -> 0 | H15: =W15+AM15 -> 0 | I15: =X15+AN15 -> 0 | J15: =Y15+AO15 -> 0 | ... M15: =AB15+AR15 -> 0 | O15: =SUM(D15:M15) -> 0 | Q15: Investment | S15: =Decisions!BG87 -> 0 | T15: =Decisions!BH87 -> 0 | U15: =Decisions!BI87 -> 0 | V15: =Decisions!BJ87 -> 0 | W15: =Decisions!BK87 -> 0 | X15: =Decisions!BL87 -> 0 | Y15: =Decisions!BM87 -> 0 | Z15: =Decisions!BN87 -> 0 | ... AB15: =Decisions!BP87 -> 0 | AD15: =SUM(S15:AB15) -> 0 | AG15: Investment | AV15: Investment | BL15: Investment
B16: Implementation Cost | C16: =R16+AH16 -> 0 | D16: =S16+AI16 -> 0 | E16: =T16+AJ16 -> 0 | F16: =U16+AK16 -> 0 | G16: =V16+AL16 -> 0 | H16: =W16+AM16 -> 0 | I16: =X16+AN16 -> 0 | J16: =Y16+AO16 -> 0 | ... M16: =AB16+AR16 -> 0 | Q16: Implementation Cost | S16: =Decisions!BG88 -> 0 | T16: =Decisions!BH88 -> 0 | U16: =Decisions!BI88 -> 0 | V16: =Decisions!BJ88 -> 0 | W16: =Decisions!BK88 -> 0 | X16: =Decisions!BL88 -> 0 | Y16: =Decisions!BM88 -> 0 | Z16: =Decisions!BN88 -> 0 | ... AB16: =Decisions!BP88 -> 0 | AD16: =SUM(S16:AB16) -> 0 | AG16: Implementation Cost | AV16: Implementation Cost | BL16: Implementation Cost
B17: Acquision | C17: =R17+AH17 -> 0 | D17: =S17+AI17 -> 0 | E17: =T17+AJ17 -> 0 | F17: =U17+AK17 -> 0 | G17: =V17+AL17 -> -13050.403 | H17: =W17+AM17 -> 0 | I17: =X17+AN17 -> 0 | J17: =Y17+AO17 -> 0 | ... M17: =AB17+AR17 -> 0 | Q17: Acquision | S17: =Decisions!BG89 -> 0 | T17: =Decisions!BH89 -> 0 | U17: =Decisions!BI89 -> 0 | V17: =Decisions!BJ89 -> -13050.403 | W17: =Decisions!BK89 -> 0 | X17: =Decisions!BL89 -> 0 | Y17: =Decisions!BM89 -> 0 | Z17: =Decisions!BN89 -> 0 | ... AB17: =Decisions!BP89 -> 0 | AD17: =SUM(S17:AB17) -> -13050.403 | AG17: Acquision | AV17: Acquision | BL17: Acquision
B18: Premium | Q18: Premium | S18: =Decisions!BG90 -> 0 | T18: =Decisions!BH90 -> 0 | U18: =Decisions!BI90 -> 0 | V18: =Decisions!BJ90 -> 0 | W18: =Decisions!BK90 -> 0 | X18: =Decisions!BL90 -> 0 | Y18: =Decisions!BM90 -> 0 | Z18: =Decisions!BN90 -> 0 | ... AB18: =Decisions!BP90 -> 0 | AD18: =SUM(S18:AB18) -> 0 | AG18: Premium | AV18: Premium
B19: Investments Total | C19: =SUM(C15:C17) -> 0 | D19: =SUM(D15:D17) -> 0 | E19: =SUM(E15:E17) -> 0 | F19: =SUM(F15:F17) -> 0 | G19: =SUM(G15:G17) -> -13050.403 | H19: =SUM(H15:H17) -> 0 | I19: =SUM(I15:I17) -> 0 | J19: =SUM(J15:J17) -> 0 | ... M19: =SUM(M15:M17) -> 0 | O19: =SUM(D19:M19) -> -13050.403 | Q19: Investments Total | S19: =SUM(S15:S17) -> 0 | T19: =SUM(T15:T17) -> 0 | U19: =SUM(U15:U17) -> 0 | V19: =SUM(V15:V17) -> -13050.403 | W19: =SUM(W15:W17) -> 0 | X19: =SUM(X15:X17) -> 0 | Y19: =SUM(Y15:Y17) -> 0 | Z19: =SUM(Z15:Z17) -> 0 | ... AB19: =SUM(AB15:AB17) -> 0 | AD19: =SUM(S19:AB19) -> -13050.403 | AG19: Investments Total | AV19: Investments Total | BL19: Investments Total
B20: Revenue | C20: =R20+AH20 -> 42836 | D20: =S20+AI20 -> 42836 | E20: =T20+AJ20 -> 43692.72 | F20: =U20+AK20 -> 44435.496 | G20: =V20+AL20 -> 45102.029 | H20: =W20+AM20 -> 45930.806 | I20: =X20+AN20 -> 52341.112 | J20: =Y20+AO20 -> 52562.818 | ... M20: =AB20+AR20 -> 53234.608 | Q20: Revenue | S20: =Decisions!BG92 -> 0 | T20: =Decisions!BH92 -> 0 | U20: =Decisions!BI92 -> 0 | V20: =Decisions!BJ92 -> 0 | W20: =Decisions!BK92 -> 8000 | X20: =Decisions!BL92 -> 8000 | Y20: =Decisions!BM92 -> 8000 | Z20: =Decisions!BN92 -> 8000 | ... AB20: =Decisions!BP92 -> 8000 | AG20: Revenue | AH20: =AW22 -> 42836 | AI20: =AH20+AH21 -> 42836 | AJ20: =AI20+AI21 -> 43692.72 | AK20: =AJ20+AJ21 -> 44435.496 | AL20: =AK20+AK21 -> 45102.029 | AM20: =AL20+AL21 -> 37930.806 | AN20: =AM20+AM21 -> 44341.112 | AO20: =AN20+AN21 -> 44562.818 | AP20: =AO20+AO21 -> 44785.632 | ... AR20: =AQ20+AQ21 -> 45234.608 | AV20: Revenue | BL20: Revenue | BM20: =AW22 -> 42836 | BN20: =BM20*(1+BN60) -> 43692.72 | BO20: =BN20+BN21 -> 43692.72 | BP20: =BO20+BO21 -> 44435.496 | BQ20: =BP20+BP21 -> 45102.029 | BR20: =BQ20+BQ21 -> 37930.806 | BS20: =BR20+BR21 -> 44341.112 | BT20: =BS20+BS21 -> 44562.818 | BU20: =BT20+BT21 -> 44785.632 | BV20: =BU20+BU21 -> 45009.56 | BW20: =BV20+BV21 -> 45234.608
B21: Growth | C21: =R21+AH21 -> 0 | D21: =S21+AI21 -> 856.72 | E21: =T21+AJ21 -> 742.77624 | F21: =U21+AK21 -> 666.53244 | G21: =V21+AL21 -> -7171.2226 | H21: =W21+AM21 -> 6410.3062 | I21: =X21+AN21 -> 1021.7056 | J21: =Y21+AO21 -> 1902.8141 | ... M21: =AB21+AR21 -> 5110.253 | Q21: Growth | S21: =Decisions!BG93 -> 0 | T21: =Decisions!BH93 -> 0 | U21: =Decisions!BI93 -> 0 | V21: =Decisions!BJ93 -> 0 | W21: =Decisions!BK93 -> 0 | X21: =Decisions!BL93 -> 800 | Y21: =Decisions!BM93 -> 1680 | Z21: =Decisions!BN93 -> 2648 | ... AB21: =Decisions!BP93 -> 4884.08 | AG21: Growth | AI21: =AI60*AI20 -> 856.72 | AJ21: =AJ60*AJ20 -> 742.77624 | AK21: =AK60*AK20 -> 666.53244 | AL21: =AL60*AL20 -> -7171.2226 | AM21: =AM60*AM20 -> 6410.3062 | AN21: =AN60*AN20 -> 221.70556 | AO21: =AO60*AO20 -> 222.81409 | AP21: =AP60*AP20 -> 223.92816 | ... AR21: =AR60*AR20 -> 226.17304 | AV21: Growth | BL21: Growth | BO21: =BO60*BO20 -> 742.77624 | BP21: =BP60*BP20 -> 666.53244 | BQ21: =BQ60*BQ20 -> -7171.2226 | BR21: =BR60*BR20 -> 6410.3062 | BS21: =BS60*BS20 -> 221.70556 | BT21: =BT60*BT20 -> 222.81409 | BU21: =BU60*BU20 -> 223.92816 | BV21: =BV60*BV20 -> 225.0478 | BW21: =BW60*BW20 -> 226.17304
B22: Revenue Total | C22: =C21+C20 -> 42836 | D22: =D21+D20 -> 43692.72 | E22: =E21+E20 -> 44435.496 | F22: =F21+F20 -> 45102.029 | G22: =G21+G20 -> 37930.806 | H22: =H21+H20 -> 52341.112 | I22: =I21+I20 -> 53362.818 | J22: =J21+J20 -> 54465.632 | ... M22: =M21+M20 -> 58344.861 | Q22: Revenue Total | S22: =S21+S20 -> 0 | T22: =T21+T20 -> 0 | U22: =U21+U20 -> 0 | V22: =V21+V20 -> 0 | W22: =W21+W20 -> 8000 | X22: =X21+X20 -> 8800 | Y22: =Y21+Y20 -> 9680 | Z22: =Z21+Z20 -> 10648 | ... AB22: =AB21+AB20 -> 12884.08 | AG22: Revenue Total | AH22: =AH21+AH20 -> 42836 | AI22: =AI21+AI20 -> 43692.72 | AJ22: =AJ21+AJ20 -> 44435.496 | AK22: =AK21+AK20 -> 45102.029 | AL22: =AL21+AL20 -> 37930.806 | AM22: =AM21+AM20 -> 44341.112 | AN22: =AN21+AN20 -> 44562.818 | AO22: =AO21+AO20 -> 44785.632 | ... AS22: =AS21+AS20 -> 0 | AV22: Revenue Total | AW22: =Baseline!C5 -> 42836 | AX22: =AW22*(1+AX60) -> 43692.72 | AY22: =AX22*(1+AY60) -> 44566.574 | AZ22: =AY22*(1+AZ60) -> 45457.906 | BA22: =AZ22*(1+BA60) -> 46367.064 | BB22: =BA22*(1+BB60) -> 47294.405 | BC22: =BB22*(1+BC60) -> 48240.293 | BD22: =BC22*(1+BD60) -> 49205.099 | BE22: =BD22*(1+BE60) -> 50189.201 | ... BG22: =BF22*(1+BG60) -> 52216.845 | BH22: =BH21+BH20 -> 0 | BL22: Revenue Total | BM22: =BM21+BM20 -> 42836 | BN22: =BN21+BN20 -> 43692.72 | BO22: =BO21+BO20 -> 44435.496 | BP22: =BP21+BP20 -> 45102.029 | BQ22: =BQ21+BQ20 -> 37930.806 | BR22: =BR21+BR20 -> 44341.112 | BS22: =BS21+BS20 -> 44562.818 | BT22: =BT21+BT20 -> 44785.632 | ... BW22: =BW21+BW20 -> 45460.781
B23: COGS | C23: =R23+AH23 -> -37037 | D23: =S23+AI23 -> -37777.74 | E23: =T23+AJ23 -> -38419.962 | F23: =U23+AK23 -> -39221.771 | G23: =V23+AL23 -> -32985.51 | H23: =W23+AM23 -> -44960.061 | I23: =X23+AN23 -> -45792.861 | J23: =Y23+AO23 -> -46690.625 | ... M23: =AB23+AR23 -> -49841.014 | Q23: COGS | S23: =Decisions!BG95 -> 0 | T23: =Decisions!BH95 -> 0 | U23: =Decisions!BI95 -> 0 | V23: =Decisions!BJ95 -> 0 | W23: =Decisions!BK95 -> -6400 | X23: =Decisions!BL95 -> -7040 | Y23: =Decisions!BM95 -> -7744 | Z23: =Decisions!BN95 -> -8518.4 | ... AB23: =Decisions!BP95 -> -10307.264 | AG23: COGS | AH23: =AW23 -> -37037 | AI23: =-AI63*AI22 -> -37777.74 | AJ23: =-AJ63*AJ22 -> -38419.962 | AK23: =-AK63*AK22 -> -39221.771 | AL23: =-AL63*AL22 -> -32985.51 | AM23: =-AM63*AM22 -> -38560.061 | AN23: =-AN63*AN22 -> -38752.861 | AO23: =-AO63*AO22 -> -38946.625 | AP23: =-AP63*AP22 -> -39141.358 | ... AR23: =-AR63*AR22 -> -39533.75 | AV23: COGS | AW23: =Baseline!C6 -> -37037 | AX23: =-AX63*AX22 -> -37777.74 | AY23: =-AY63*AY22 -> -38533.295 | AZ23: =-AZ63*AZ22 -> -39303.961 | BA23: =-BA63*BA22 -> -40090.04 | BB23: =-BB63*BB22 -> -40891.841 | BC23: =-BC63*BC22 -> -41709.678 | BD23: =-BD63*BD22 -> -42543.871 | BE23: =-BE63*BE22 -> -43394.748 | ... BG23: =-BG63*BG22 -> -45147.896 | BL23: COGS | BM23: =AW23 -> -37037 | BN23: =-BN63*BN22 -> -37777.74 | BO23: =-BO63*BO22 -> -38419.962 | BP23: =-BP63*BP22 -> -39221.771 | BQ23: =-BQ63*BQ22 -> -32985.51 | BR23: =-BR63*BR22 -> -38560.061 | BS23: =-BS63*BS22 -> -38752.861 | BT23: =-BT63*BT22 -> -38946.625 | BU23: =-BU63*BU22 -> -39141.358 | ... BW23: =-BW63*BW22 -> -39533.75
B24: SG&A | C24: =R24+AH24 -> -2061 | D24: =S24+AI24 -> -2102.22 | E24: =T24+AJ24 -> -2144.2644 | F24: =U24+AK24 -> -2187.1497 | G24: =V24+AL24 -> -2230.8927 | H24: =W24+AM24 -> -2675.5105 | I24: =X24+AN24 -> -2761.0207 | J24: =Y24+AO24 -> -2851.4412 | ... M24: =AB24+AR24 -> -3156.5515 | Q24: SG&A | S24: =Decisions!BG96 -> 0 | T24: =Decisions!BH96 -> 0 | U24: =Decisions!BI96 -> 0 | V24: =Decisions!BJ96 -> 0 | W24: =Decisions!BK96 -> -400 | X24: =Decisions!BL96 -> -440 | Y24: =Decisions!BM96 -> -484 | Z24: =Decisions!BN96 -> -532.4 | ... AB24: =Decisions!BP96 -> -644.204 | AG24: SG&A | AH24: =AW24 -> -2061 | AI24: =(1+AI65)*AH24 -> -2102.22 | AJ24: =(1+AJ65)*AI24 -> -2144.2644 | AK24: =(1+AK65)*AJ24 -> -2187.1497 | AL24: =(1+AL65)*AK24 -> -2230.8927 | AM24: =(1+AM65)*AL24 -> -2275.5105 | AN24: =(1+AN65)*AM24 -> -2321.0207 | AO24: =(1+AO65)*AN24 -> -2367.4412 | AP24: =(1+AP65)*AO24 -> -2414.79 | ... AR24: =(1+AR65)*AQ24 -> -2512.3475 | AV24: SG&A | AW24: =Baseline!C7 -> -2061 | AX24: =-AX64*AX22 -> -2102.22 | AY24: =-AY64*AY22 -> -2144.2644 | AZ24: =-AZ64*AZ22 -> -2187.1497 | BA24: =-BA64*BA22 -> -2230.8927 | BB24: =-BB64*BB22 -> -2275.5105 | BC24: =-BC64*BC22 -> -2321.0207 | BD24: =-BD64*BD22 -> -2367.4412 | BE24: =-BE64*BE22 -> -2414.79 | ... BG24: =-BG64*BG22 -> -2512.3475 | BL24: SG&A | BM24: =AW24 -> -2061 | BN24: =(1+BN65)*BM24 -> -2102.22 | BO24: =(1+BO65)*BN24 -> -2144.2644 | BP24: =(1+BP65)*BO24 -> -2187.1497 | BQ24: =(1+BQ65)*BP24 -> -2230.8927 | BR24: =(1+BR65)*BQ24 -> -2275.5105 | BS24: =(1+BS65)*BR24 -> -2321.0207 | BT24: =(1+BT65)*BS24 -> -2367.4412 | BU24: =(1+BU65)*BT24 -> -2414.79 | ... BW24: =(1+BW65)*BV24 -> -2512.3475
B25: EBITDA | C25: =SUM(C22,C23,C24) -> 3738 | D25: =SUM(D22,D23,D24) -> 3812.76 | E25: =SUM(E22,E23,E24) -> 3871.2703 | F25: =SUM(F22,F23,F24) -> 3693.1078 | G25: =SUM(G22,G23,G24) -> 2714.4039 | H25: =SUM(H22,H23,H24) -> 4705.5412 | I25: =SUM(I22,I23,I24) -> 4808.9362 | J25: =SUM(J22,J23,J24) -> 4923.5656 | ... M25: =SUM(M22,M23,M24) -> 5347.295 | Q25: EBITDA | S25: =SUM(S22,S23,S24) -> 0 | T25: =SUM(T22,T23,T24) -> 0 | U25: =SUM(U22,U23,U24) -> 0 | V25: =SUM(V22,V23,V24) -> 0 | W25: =SUM(W22,W23,W24) -> 1200 | X25: =SUM(X22,X23,X24) -> 1320 | Y25: =SUM(Y22,Y23,Y24) -> 1452 | Z25: =SUM(Z22,Z23,Z24) -> 1597.2 | ... AB25: =SUM(AB22,AB23,AB24) -> 1932.612 | AG25: EBITDA | AH25: =SUM(AH22,AH23,AH24) -> 3738 | AI25: =SUM(AI22,AI23,AI24) -> 3812.76 | AJ25: =SUM(AJ22,AJ23,AJ24) -> 3871.2703 | AK25: =SUM(AK22,AK23,AK24) -> 3693.1078 | AL25: =SUM(AL22,AL23,AL24) -> 2714.4039 | AM25: =SUM(AM22,AM23,AM24) -> 3505.5412 | AN25: =SUM(AN22,AN23,AN24) -> 3488.9362 | AO25: =SUM(AO22,AO23,AO24) -> 3471.5656 | ... AR25: =SUM(AR22,AR23,AR24) -> 3414.683 | AV25: EBITDA | AW25: =SUM(AW22,AW23,AW24) -> 3738 | AX25: =SUM(AX22,AX23,AX24) -> 3812.76 | AY25: =SUM(AY22,AY23,AY24) -> 3889.0152 | AZ25: =SUM(AZ22,AZ23,AZ24) -> 3966.7955 | BA25: =SUM(BA22,BA23,BA24) -> 4046.1314 | BB25: =SUM(BB22,BB23,BB24) -> 4127.054 | BC25: =SUM(BC22,BC23,BC24) -> 4209.5951 | BD25: =SUM(BD22,BD23,BD24) -> 4293.787 | ... BG25: =SUM(BG22,BG23,BG24) -> 4556.6011 | BL25: EBITDA | BM25: =SUM(BM22,BM23,BM24) -> 3738 | BN25: =SUM(BN22,BN23,BN24) -> 3812.76 | BO25: =SUM(BO22,BO23,BO24) -> 3871.2703 | BP25: =SUM(BP22,BP23,BP24) -> 3693.1078 | BQ25: =SUM(BQ22,BQ23,BQ24) -> 2714.4039 | BR25: =SUM(BR22,BR23,BR24) -> 3505.5412 | BS25: =SUM(BS22,BS23,BS24) -> 3488.9362 | BT25: =SUM(BT22,BT23,BT24) -> 3471.5656 | ... BW25: =SUM(BW22,BW23,BW24) -> 3414.683
B26: COGS savings | C26: =R26+AH26 -> 0 | D26: =S26+AI26 -> 0 | E26: =T26+AJ26 -> 0 | F26: =U26+AK26 -> 0 | G26: =V26+AL26 -> 0 | H26: =W26+AM26 -> 0 | I26: =X26+AN26 -> 0 | J26: =Y26+AO26 -> 0 | ... M26: =AB26+AR26 -> 0 | Q26: COGS savings | S26: =Decisions!BG98 -> 0 | T26: =Decisions!BH98 -> 0 | U26: =Decisions!BI98 -> 0 | V26: =Decisions!BJ98 -> 0 | W26: =Decisions!BK98 -> 0 | X26: =Decisions!BL98 -> 0 | Y26: =Decisions!BM98 -> 0 | Z26: =Decisions!BN98 -> 0 | ... AB26: =Decisions!BP98 -> 0 | AG26: COGS savings | AV26: COGS savings | BL26: COGS savings
B27: Manufacturing OH savings | D27: =S27+AI27 -> 0 | E27: =T27+AJ27 -> 0 | F27: =U27+AK27 -> 0 | G27: =V27+AL27 -> 0 | H27: =W27+AM27 -> 0 | I27: =X27+AN27 -> 0 | J27: =Y27+AO27 -> 0 | K27: =Z27+AP27 -> 0 | ... M27: =AB27+AR27 -> 0 | Q27: Manufacturing OH savings | S27: =Decisions!BG99 -> 0 | T27: =Decisions!BH99 -> 0 | U27: =Decisions!BI99 -> 0 | V27: =Decisions!BJ99 -> 0 | W27: =Decisions!BK99 -> 0 | X27: =Decisions!BL99 -> 0 | Y27: =Decisions!BM99 -> 0 | Z27: =Decisions!BN99 -> 0 | ... AB27: =Decisions!BP99 -> 0 | AG27: Manufacturing OH savings | AV27: Manufacturing OH savings
B28: SG&A savings | C28: =R28+AH28 -> 0 | D28: =S28+AI28 -> 0 | E28: =T28+AJ28 -> 0 | F28: =U28+AK28 -> 0 | G28: =V28+AL28 -> 0 | H28: =W28+AM28 -> 0 | I28: =X28+AN28 -> 0 | J28: =Y28+AO28 -> 0 | ... M28: =AB28+AR28 -> 0 | Q28: SG&A savings | S28: =Decisions!BG100 -> 0 | T28: =Decisions!BH100 -> 0 | U28: =Decisions!BI100 -> 0 | V28: =Decisions!BJ100 -> 0 | W28: =Decisions!BK100 -> 0 | X28: =Decisions!BL100 -> 0 | Y28: =Decisions!BM100 -> 0 | Z28: =Decisions!BN100 -> 0 | ... AB28: =Decisions!BP100 -> 0 | AG28: SG&A savings | AV28: SG&A savings | BL28: SG&A savings
B29: Synergies | Q29: Synergies | S29: =Decisions!BG101 -> 0 | T29: =Decisions!BH101 -> 0 | U29: =Decisions!BI101 -> 0 | V29: =Decisions!BJ101 -> 0 | W29: =Decisions!BK101 -> 240 | X29: =Decisions!BL101 -> 240 | Y29: =Decisions!BM101 -> 240 | Z29: =Decisions!BN101 -> 240 | ... AB29: =Decisions!BP101 -> 240 | AG29: Synergies | AV29: Synergies
B30: EBITDA | C30: =SUM(C25:C29) -> 3738 | D30: =SUM(D25:D29) -> 3812.76 | E30: =SUM(E25:E29) -> 3871.2703 | F30: =SUM(F25:F29) -> 3693.1078 | G30: =SUM(G25:G29) -> 2714.4039 | H30: =SUM(H25:H29) -> 4705.5412 | I30: =SUM(I25:I29) -> 4808.9362 | J30: =SUM(J25:J29) -> 4923.5656 | ... M30: =SUM(M25:M29) -> 5347.295 | O30: =SUM(D30:M30)-AD30-AT30 -> -1440 | Q30: EBITDA | S30: =SUM(S25:S29) -> 0 | T30: =SUM(T25:T29) -> 0 | U30: =SUM(U25:U29) -> 0 | V30: =SUM(V25:V29) -> 0 | W30: =SUM(W25:W29) -> 1440 | X30: =SUM(X25:X29) -> 1560 | Y30: =SUM(Y25:Y29) -> 1692 | Z30: =SUM(Z25:Z29) -> 1837.2 | ... AB30: =SUM(AB25:AB29) -> 2172.612 | AD30: =SUM(S30:AB30) -> 10698.732 | AG30: EBITDA | AI30: =SUM(AI25:AI29) -> 3812.76 | AJ30: =SUM(AJ25:AJ29) -> 3871.2703 | AK30: =SUM(AK25:AK29) -> 3693.1078 | AL30: =SUM(AL25:AL29) -> 2714.4039 | AM30: =SUM(AM25:AM29) -> 3505.5412 | AN30: =SUM(AN25:AN29) -> 3488.9362 | AO30: =SUM(AO25:AO29) -> 3471.5656 | AP30: =SUM(AP25:AP29) -> 3453.4118 | ... AR30: =SUM(AR25:AR29) -> 3414.683 | AT30: =SUM(AI30:AR30) -> 34860.137 | AV30: EBITDA | AW30: =AW26+AW25 -> 3738 | AX30: =SUM(AX25:AX28) -> 3812.76 | AY30: =SUM(AY25:AY28) -> 3889.0152 | AZ30: =SUM(AZ25:AZ28) -> 3966.7955 | BA30: =SUM(BA25:BA28) -> 4046.1314 | BB30: =SUM(BB25:BB28) -> 4127.054 | BC30: =SUM(BC25:BC28) -> 4209.5951 | BD30: =SUM(BD25:BD28) -> 4293.787 | BE30: =SUM(BE25:BE28) -> 4379.6628 | ... BG30: =SUM(BG25:BG28) -> 4556.6011 | BL30: EBITDA | BM30: =SUM(BM25,BM26,BM28) -> 3738 | BN30: =SUM(BN25,BN26,BN28) -> 3812.76 | BO30: =SUM(BO25,BO26,BO28) -> 3871.2703 | BP30: =SUM(BP25,BP26,BP28) -> 3693.1078 | BQ30: =SUM(BQ25,BQ26,BQ28) -> 2714.4039 | BR30: =SUM(BR25,BR26,BR28) -> 3505.5412 | BS30: =SUM(BS25,BS26,BS28) -> 3488.9362 | BT30: =SUM(BT25,BT26,BT28) -> 3471.5656 | ... BW30: =SUM(BW25,BW26,BW28) -> 3414.683
B31: D&A | D31: =S31+AI31 -> -1747.7088 | E31: =T31+AJ31 -> -1777.4198 | F31: =U31+AK31 -> -1804.0811 | G31: =V31+AL31 -> -1517.2322 | H31: =W31+AM31 -> -2093.6445 | I31: =X31+AN31 -> -2134.5127 | J31: =Y31+AO31 -> -2178.6253 | K31: =Z31+AP31 -> -2226.3024 | ... M31: =AB31+AR31 -> -2333.7944 | Q31: D&A | S31: =S36 -> 0 | T31: =T36 -> 0 | U31: =U36 -> 0 | V31: =V36 -> 0 | W31: =W36 -> -320 | X31: =X36 -> -352 | Y31: =Y36 -> -387.2 | Z31: =Z36 -> -425.92 | ... AB31: =AB36 -> -515.3632 | AG31: D&A | AH31: =AW31 -> -1622 | AI31: =AI36 -> -1747.7088 | AJ31: =AJ36 -> -1777.4198 | AK31: =AK36 -> -1804.0811 | AL31: =AL36 -> -1517.2322 | AM31: =AM36 -> -1773.6445 | AN31: =AN36 -> -1782.5127 | AO31: =AO36 -> -1791.4253 | AP31: =AP36 -> -1800.3824 | ... AR31: =AR36 -> -1818.4312 | AV31: D&A | AW31: =Baseline!C9+Baseline!C10 -> -1622 | AX31: =AX36 -> -1747.7088 | AY31: =AY36 -> -1782.663 | AZ31: =AZ36 -> -1818.3162 | BA31: =BA36 -> -1854.6826 | BB31: =BB36 -> -1891.7762 | BC31: =BC36 -> -1929.6117 | BD31: =BD36 -> -1968.204 | BE31: =BE36 -> -2007.568 | ... BG31: =BG36 -> -2088.6738 | BL31: D&A | BM31: =AW31 -> -1622 | BN31: =BN36 -> -1747.7088 | BO31: =BO36 -> -1777.4198 | BP31: =BP36 -> -1804.0811 | BQ31: =BQ36 -> -1517.2322 | BR31: =BR36 -> -1773.6445 | BS31: =BS36 -> -1782.5127 | BT31: =BT36 -> -1791.4253 | BU31: =BU36 -> -1800.3824 | ... BW31: =BW36 -> -1818.4312
B32: EBIT operating | C32: =C30+C31 -> 3738 | D32: =D30+D31 -> 2065.0512 | E32: =E30+E31 -> 2093.8504 | F32: =F30+F31 -> 1889.0267 | G32: =G30+G31 -> 1197.1717 | H32: =H30+H31 -> 2611.8967 | I32: =I30+I31 -> 2674.4235 | J32: =J30+J31 -> 2744.9403 | ... M32: =M30+M31 -> 3013.5006 | N32: =M32*(1+$AW$10) -> 3073.7706 | O32: =SUM(D32:M32)-AD32-AT32 -> -1440 | P32: check | Q32: EBIT | S32: =S30+S31 -> 0 | T32: =T30+T31 -> 0 | U32: =U30+U31 -> 0 | V32: =V30+V31 -> 0 | W32: =W30+W31 -> 1120 | X32: =X30+X31 -> 1208 | Y32: =Y30+Y31 -> 1304.8 | Z32: =Z30+Z31 -> 1411.28 | ... AB32: =AB30+AB31 -> 1657.2488 | AC32: =AB32*(1+$AW$10) -> 1690.3938 | AD32: =SUM(S32:AB32) -> 8229.7368 | AG32: EBIT | AH32: =AH30+AH31 -> -1622 | AI32: =AI30+AI31 -> 2065.0512 | AJ32: =AJ30+AJ31 -> 2093.8504 | AK32: =AK30+AK31 -> 1889.0267 | AL32: =AL30+AL31 -> 1197.1717 | AM32: =AM30+AM31 -> 1731.8967 | AN32: =AN30+AN31 -> 1706.4235 | AO32: =AO30+AO31 -> 1680.1403 | ... AR32: =AR30+AR31 -> 1596.2518 | AS32: =AR32*(1+$AW$10) -> 1628.1768 | AT32: =SUM(AI32:AR32) -> 17237.914 | AV32: EBIT | AW32: =AW30+AW31 -> 2116 | AX32: =AX30+AX31 -> 2065.0512 | AY32: =AY30+AY31 -> 2106.3522 | AZ32: =AZ30+AZ31 -> 2148.4793 | BA32: =BA30+BA31 -> 2191.4489 | BB32: =BB30+BB31 -> 2235.2778 | BC32: =BC30+BC31 -> 2279.9834 | BD32: =BD30+BD31 -> 2325.5831 | ... BG32: =BG30+BG31 -> 2467.9273 | BH32: =BG32*(1+$AW$10) -> 2517.2859 | BL32: EBIT | BM32: =BM30+BM31 -> 2116 | BN32: =BN30+BN31 -> 2065.0512 | BO32: =BO30+BO31 -> 2093.8504 | BP32: =BP30+BP31 -> 1889.0267 | BQ32: =BQ30+BQ31 -> 1197.1717 | BR32: =BR30+BR31 -> 1731.8967 | BS32: =BS30+BS31 -> 1706.4235 | BT32: =BT30+BT31 -> 1680.1403 | ... BW32: =BW30+BW31 -> 1596.2518 | BX32: =BW32*(1+$AW$10) -> 1628.1768
B33: =B16 -> Implementation Cost | C33: =R33+AH33 -> 0 | D33: =S33+AI33 -> 0 | E33: =T33+AJ33 -> 0 | F33: =U33+AK33 -> 0 | G33: =V33+AL33 -> 0 | H33: =W33+AM33 -> 0 | I33: =X33+AN33 -> 0 | J33: =Y33+AO33 -> 0 | ... M33: =AB33+AR33 -> 0 | Q33: =Q16 -> Implementation Cost | S33: =S16 -> 0 | T33: =T16 -> 0 | U33: =U16 -> 0 | V33: =V16 -> 0 | W33: =W16 -> 0 | X33: =X16 -> 0 | Y33: =Y16 -> 0 | Z33: =Z16 -> 0 | ... AB33: =AB16 -> 0 | AG33: Non-operating expenses | AI33: =AI16 -> 0 | AJ33: =AJ16 -> 0 | AK33: =AK16 -> 0 | AL33: =AL16 -> 0 | AM33: =AM16 -> 0 | AN33: =AN16 -> 0 | AO33: =AO16 -> 0 | AP33: =AP16 -> 0 | ... AR33: =AR16 -> 0 | AV33: Non-operating expenses | AX33: =AX16 -> 0 | AY33: =AY16 -> 0 | AZ33: =AZ16 -> 0 | BA33: =BA16 -> 0 | BB33: =BB16 -> 0 | BC33: =BC16 -> 0 | BD33: =BD16 -> 0 | BE33: =BE16 -> 0 | ... BG33: =BG16 -> 0 | BL33: Non-operating expenses
B34: Taxes | D34: =MIN(0,-SUM(D32,D33)*$R$34) -> -454.31126 | E34: =MIN(0,-SUM(E32,E33)*$R$34) -> -460.64709 | F34: =MIN(0,-SUM(F32,F33)*$R$34) -> -415.58587 | G34: =MIN(0,-SUM(G32,G33)*$R$34) -> -263.37777 | H34: =MIN(0,-SUM(H32,H33)*$R$34) -> -574.61727 | I34: =MIN(0,-SUM(I32,I33)*$R$34) -> -588.37317 | J34: =MIN(0,-SUM(J32,J33)*$R$34) -> -603.88687 | K34: =MIN(0,-SUM(K32,K33)*$R$34) -> -621.34807 | ... N34: =MIN(0,-SUM(N32,N33)*$R$34) -> -676.22953 | O34: =SUM(D34:M34)-AD34-AT34 -> 316.8 | P34: check, tax can differ due to consolidation | Q34: Taxes | R34: =Decisions!$F$41 -> 0.22 | S34: =MIN(0,-SUM(S32,S33)*$R$34) -> 0 | T34: =MIN(0,-SUM(T32,T33)*$R$34) -> 0 | U34: =MIN(0,-SUM(U32,U33)*$R$34) -> 0 | V34: =MIN(0,-SUM(V32,V33)*$R$34) -> 0 | W34: =MIN(0,-SUM(W32,W33)*$R$34) -> -246.4 | X34: =MIN(0,-SUM(X32,X33)*$R$34) -> -265.76 | Y34: =MIN(0,-SUM(Y32,Y33)*$R$34) -> -287.056 | Z34: =MIN(0,-SUM(Z32,Z33)*$R$34) -> -310.4816 | ... AC34: =MIN(0,-SUM(AC32,AC33)*$R$34) -> -371.88663 | AD34: =SUM(S34:AB34) -> -1810.5421 | AG34: Taxes | AI34: =MIN(0,-SUM(AI32,AI33)*$R$34) -> -454.31126 | AJ34: =MIN(0,-SUM(AJ32,AJ33)*$R$34) -> -460.64709 | AK34: =MIN(0,-SUM(AK32,AK33)*$R$34) -> -415.58587 | AL34: =MIN(0,-SUM(AL32,AL33)*$R$34) -> -263.37777 | AM34: =MIN(0,-SUM(AM32,AM33)*$R$34) -> -381.01727 | AN34: =MIN(0,-SUM(AN32,AN33)*$R$34) -> -375.41317 | AO34: =MIN(0,-SUM(AO32,AO33)*$R$34) -> -369.63087 | AP34: =MIN(0,-SUM(AP32,AP33)*$R$34) -> -363.66647 | ... AS34: =MIN(0,-SUM(AS32,AS33)*$R$34) -> -358.1989 | AT34: =SUM(AI34:AR34) -> -3792.3412 | AV34: Taxes | AX34: =MIN(0,-SUM(AX32,AX33)*$R$34) -> -454.31126 | AY34: =MIN(0,-SUM(AY32,AY33)*$R$34) -> -463.39749 | AZ34: =MIN(0,-SUM(AZ32,AZ33)*$R$34) -> -472.66544 | BA34: =MIN(0,-SUM(BA32,BA33)*$R$34) -> -482.11875 | BB34: =MIN(0,-SUM(BB32,BB33)*$R$34) -> -491.76112 | BC34: =MIN(0,-SUM(BC32,BC33)*$R$34) -> -501.59635 | BD34: =MIN(0,-SUM(BD32,BD33)*$R$34) -> -511.62827 | BE34: =MIN(0,-SUM(BE32,BE33)*$R$34) -> -521.86084 | ... BH34: =MIN(0,-SUM(BH32,BH33)*$R$34) -> -553.8029 | BL34: Taxes | BN34: =MIN(0,-SUM(BN32,BN33)*$R$34) -> -454.31126 | BO34: =MIN(0,-SUM(BO32,BO33)*$R$34) -> -460.64709 | BP34: =MIN(0,-SUM(BP32,BP33)*$R$34) -> -415.58587 | BQ34: =MIN(0,-SUM(BQ32,BQ33)*$R$34) -> -263.37777 | BR34: =MIN(0,-SUM(BR32,BR33)*$R$34) -> -381.01727 | BS34: =MIN(0,-SUM(BS32,BS33)*$R$34) -> -375.41317 | BT34: =MIN(0,-SUM(BT32,BT33)*$R$34) -> -369.63087 | BU34: =MIN(0,-SUM(BU32,BU33)*$R$34) -> -363.66647 | ... BX34: =MIN(0,-SUM(BX32,BX33)*$R$34) -> -358.1989
AG35: Net Income
B36: Capex maintenance | C36: =R36 -> 0 | D36: =S36+AI36 -> -1747.7088 | E36: =T36+AJ36 -> -1777.4198 | F36: =U36+AK36 -> -1804.0811 | G36: =V36+AL36 -> -1517.2322 | H36: =W36+AM36 -> -2093.6445 | I36: =X36+AN36 -> -2134.5127 | J36: =Y36+AO36 -> -2178.6253 | K36: =Z36+AP36 -> -2226.3024 | ... M36: =AB36+AR36 -> -2333.7944 | O36: =SUM(D36:M36)-AD36-AT36 -> 0 | P36: check | Q36: Capex maintenance | R36: =Decisions!AO104 -> 0 | S36: =Decisions!BG104 -> 0 | T36: =Decisions!BH104 -> 0 | U36: =Decisions!BI104 -> 0 | V36: =Decisions!BJ104 -> 0 | W36: =Decisions!BK104 -> -320 | X36: =Decisions!BL104 -> -352 | Y36: =Decisions!BM104 -> -387.2 | Z36: =Decisions!BN104 -> -425.92 | ... AB36: =Decisions!BP104 -> -515.3632 | AD36: =SUM(S36:AB36) -> -2468.9952 | AG36: Capex maintenance | AH36: =AW36 -> -1713.44 | AI36: =-AI22*AI66 -> -1747.7088 | AJ36: =-AJ22*AJ66 -> -1777.4198 | AK36: =-AK22*AK66 -> -1804.0811 | AL36: =-AL22*AL66 -> -1517.2322 | AM36: =-AM22*AM66 -> -1773.6445 | AN36: =-AN22*AN66 -> -1782.5127 | AO36: =-AO22*AO66 -> -1791.4253 | AP36: =-AP22*AP66 -> -1800.3824 | ... AR36: =-AR22*AR66 -> -1818.4312 | AT36: =SUM(AI36:AR36) -> -17622.222 | AV36: Capex maintenance | AW36: =Baseline!C15 -> -1713.44 | AX36: =-AX22*AX66 -> -1747.7088 | AY36: =-AY22*AY66 -> -1782.663 | AZ36: =-AZ22*AZ66 -> -1818.3162 | BA36: =-BA22*BA66 -> -1854.6826 | BB36: =-BB22*BB66 -> -1891.7762 | BC36: =-BC22*BC66 -> -1929.6117 | BD36: =-BD22*BD66 -> -1968.204 | BE36: =-BE22*BE66 -> -2007.568 | ... BG36: =-BG22*BG66 -> -2088.6738 | BL36: Capex maintenance | BM36: =AH36 -> -1713.44 | BN36: =-BN22*BN66 -> -1747.7088 | BO36: =-BO22*BO66 -> -1777.4198 | BP36: =-BP22*BP66 -> -1804.0811 | BQ36: =-BQ22*BQ66 -> -1517.2322 | BR36: =-BR22*BR66 -> -1773.6445 | BS36: =-BS22*BS66 -> -1782.5127 | BT36: =-BT22*BT66 -> -1791.4253 | BU36: =-BU22*BU66 -> -1800.3824 | ... BW36: =-BW22*BW66 -> -1818.4312
B37: New Investments | D37: =S37+AI37 -> 0 | E37: =T37+AJ37 -> 0 | F37: =U37+AK37 -> 0 | G37: =V37+AL37 -> 0 | H37: =W37+AM37 -> 0 | I37: =X37+AN37 -> -79.1386 | J37: =Y37+AO37 -> -79.534293 | K37: =Z37+AP37 -> -79.931964 | ... M37: =AB37+AR37 -> -80.733282 | O37: =SUM(D37:M37)-AD37-AT37 -> 0 | P37: check | Q37: New Investments | S37: =S15 -> 0 | T37: =T15 -> 0 | U37: =U15 -> 0 | V37: =V15 -> 0 | W37: =W15 -> 0 | X37: =X15 -> 0 | Y37: =Y15 -> 0 | Z37: =Z15 -> 0 | ... AB37: =AB15 -> 0 | AD37: =SUM(S37:AB37) -> 0 | AG37: New Investments | AI37: =AH73-AI73 -> 0 | AJ37: =AI73-AJ73 -> 0 | AK37: =AJ73-AK73 -> 0 | AL37: =AK73-AL73 -> 0 | AM37: =AL73-AM73 -> 0 | AN37: =AM73-AN73 -> -79.1386 | AO37: =AN73-AO73 -> -79.534293 | AP37: =AO73-AP73 -> -79.931964 | ... AR37: =AQ73-AR73 -> -80.733282 | AT37: =SUM(AI37:AR37) -> -399.66976 | AV37: New Investments | AX37: =AW73-AX73 -> 0 | AY37: =AX73-AY73 -> 0 | AZ37: =AY73-AZ73 -> 0 | BA37: =AZ73-BA73 -> 0 | BB37: =BA73-BB73 -> 0 | BC37: =BB73-BC73 -> -316.5544 | BD37: =BC73-BD73 -> -322.88549 | BE37: =BD73-BE73 -> -329.3432 | ... BG37: =BF73-BG73 -> -342.64866 | BL37: New Investments | BN37: =BM73-BN73 -> 0 | BO37: =BN73-BO73 -> 0 | BP37: =BO73-BP73 -> 0 | BQ37: =BP73-BQ73 -> 0 | BR37: =BQ73-BR73 -> 0 | BS37: =BR73-BS73 -> -79.1386 | BT37: =BS73-BT73 -> -79.534293 | BU37: =BT73-BU73 -> -79.931964 | ... BW37: =BV73-BW73 -> -80.733282
B38: Acquisition / Divestments | D38: =S38+AI38 -> 0 | E38: =T38+AJ38 -> 0 | F38: =U38+AK38 -> 0 | G38: =V38+AL38 -> -13050.403 | H38: =W38+AM38 -> 0 | I38: =X38+AN38 -> 0 | J38: =Y38+AO38 -> 0 | K38: =Z38+AP38 -> 0 | ... M38: =AB38+AR38 -> 0 | Q38: Acquisition / Divestments | S38: =S17 -> 0 | T38: =T17 -> 0 | U38: =U17 -> 0 | V38: =V17 -> -13050.403 | W38: =W17 -> 0 | X38: =X17 -> 0 | Y38: =Y17 -> 0 | Z38: =Z17 -> 0 | ... AB38: =AB17 -> 0 | AG38: Acquisition / Divestments | AI38: =AI17 -> 0 | AJ38: =AJ17 -> 0 | AK38: =AK17 -> 0 | AL38: =AL17 -> 0 | AM38: =AM17 -> 0 | AN38: =AN17 -> 0 | AO38: =AO17 -> 0 | AP38: =AP17 -> 0 | ... AR38: =AR17 -> 0 | AV38: Acquisition / Divestments | AX38: =AX17 -> 0 | AY38: =AY17 -> 0 | AZ38: =AZ17 -> 0 | BA38: =BA17 -> 0 | BB38: =BB17 -> 0 | BC38: =BC17 -> 0 | BD38: =BD17 -> 0 | BE38: =BE17 -> 0 | ... BG38: =BG17 -> 0 | BL38: Acquisition / Divestments
B39: Free Cash Flow | D39: =SUM(D30,D33:D38) -> 1610.7399 | E39: =SUM(E30,E33:E38) -> 1633.2033 | F39: =SUM(F30,F33:F38) -> 1473.4408 | G39: =SUM(G30,G33:G38) -> -12116.609 | H39: =SUM(H30,H33:H38) -> 2037.2794 | I39: =SUM(I30,I33:I38) -> 2006.9117 | J39: =SUM(J30,J33:J38) -> 2061.5192 | K39: =SUM(K30,K33:K38) -> 2123.0294 | ... M39: =SUM(M30,M33:M38) -> 2269.7972 | O39: =SUM(D39:M39)-AD39-AT39 -> -1123.2 | P39: check | Q39: Free Cash Flow | S39: =SUM(S30,S33:S38) -> 0 | T39: =SUM(T30,T33:T38) -> 0 | U39: =SUM(U30,U33:U38) -> 0 | V39: =SUM(V30,V33:V38) -> -13050.403 | W39: =SUM(W30,W33:W38) -> 873.6 | X39: =SUM(X30,X33:X38) -> 942.24 | Y39: =SUM(Y30,Y33:Y38) -> 1017.744 | Z39: =SUM(Z30,Z33:Z38) -> 1100.7984 | ... AB39: =SUM(AB30,AB33:AB38) -> 1292.6541 | AD39: =SUM(S39:AB39) -> -6631.2084 | AG39: Free Cash Flow | AI39: =SUM(AI30,AI33:AI38) -> 1610.7399 | AJ39: =SUM(AJ30,AJ34:AJ38) -> 1633.2033 | AK39: =SUM(AK30,AK34:AK38) -> 1473.4408 | AL39: =SUM(AL30,AL34:AL38) -> 933.7939 | AM39: =SUM(AM30,AM34:AM38) -> 1350.8794 | AN39: =SUM(AN30,AN34:AN38) -> 1251.8717 | AO39: =SUM(AO30,AO34:AO38) -> 1230.9752 | AP39: =SUM(AP30,AP34:AP38) -> 1209.431 | AQ39: =SUM(AQ30,AQ34:AQ38) -> 1187.2251 | AR39: =SUM(AR30,AR34:AR38) -> 1164.3431 | AT39: =SUM(AI39:AR39) -> 13045.903 | AV39: Free Cash Flow | AX39: =SUM(AX30,AX33:AX38) -> 1610.7399 | AY39: =SUM(AY30,AY34:AY38) -> 1642.9547 | AZ39: =SUM(AZ30,AZ34:AZ38) -> 1675.8138 | BA39: =SUM(BA30,BA34:BA38) -> 1709.3301 | BB39: =SUM(BB30,BB34:BB38) -> 1743.5167 | BC39: =SUM(BC30,BC34:BC38) -> 1461.8326 | BD39: =SUM(BD30,BD34:BD38) -> 1491.0693 | BE39: =SUM(BE30,BE34:BE38) -> 1520.8907 | BF39: =SUM(BF30,BF34:BF38) -> 1551.3085 | BG39: =SUM(BG30,BG34:BG38) -> 1582.3347 | BL39: Free Cash Flow | BN39: =SUM(BN30,BN33:BN38) -> 1610.7399 | BO39: =SUM(BO30,BO34:BO38) -> 1633.2033 | BP39: =SUM(BP30,BP34:BP38) -> 1473.4408 | BQ39: =SUM(BQ30,BQ34:BQ38) -> 933.7939 | BR39: =SUM(BR30,BR34:BR38) -> 1350.8794 | BS39: =SUM(BS30,BS34:BS38) -> 1251.8717 | BT39: =SUM(BT30,BT34:BT38) -> 1230.9752 | BU39: =SUM(BU30,BU34:BU38) -> 1209.431 | BV39: =SUM(BV30,BV34:BV38) -> 1187.2251 | BW39: =SUM(BW30,BW34:BW38) -> 1164.3431
B40: Continuing Value | M40: =SUM(N32,N34)*(1-$AW$10/M59)/($AZ$10-$AW$10) -> 30004.568 | Q40: Continuing Value | AB40: =SUM(AC32,AC34)*(1-IFERROR($AW$10/$AB$59,0))/($AZ$10-$AW$10) -> 17537.982 | AG40: Continuing Value | AR40: =SUM(AS32,AS34)*(1-$AW$10/$AR$59)/($AZ$10-$AW$10) -> 15648.986 | AV40: Continuing Value | BG40: =(BH32+BH34)*(1-$AW$10/$BG$59)/($AZ$10-$AW$10) -> 26783.189 | BL40: Continuing Value | BW40: =SUM(BX32,BX34)*(1-$AW$10/BW59)/($AZ$10-$AW$10) -> 15648.986
B41: Discount Factor | D41: =1/(1+$AZ$10) -> 0.92592593 | E41: =D41/(1+$AZ$10) -> 0.85733882 | F41: =E41/(1+$AZ$10) -> 0.79383224 | G41: =F41/(1+$AZ$10) -> 0.73502985 | H41: =G41/(1+$AZ$10) -> 0.6805832 | I41: =H41/(1+$AZ$10) -> 0.63016963 | J41: =I41/(1+$AZ$10) -> 0.5834904 | K41: =J41/(1+$AZ$10) -> 0.54026888 | L41: =K41/(1+$AZ$10) -> 0.50024897 | M41: =L41/(1+$AZ$10) -> 0.46319349 | Q41: Discount Factor | S41: =1/(1+$AZ$10) -> 0.92592593 | T41: =S41/(1+$AZ$10) -> 0.85733882 | U41: =T41/(1+$AZ$10) -> 0.79383224 | V41: =U41/(1+$AZ$10) -> 0.73502985 | W41: =V41/(1+$AZ$10) -> 0.6805832 | X41: =W41/(1+$AZ$10) -> 0.63016963 | Y41: =X41/(1+$AZ$10) -> 0.5834904 | Z41: =Y41/(1+$AZ$10) -> 0.54026888 | AA41: =Z41/(1+$AZ$10) -> 0.50024897 | AB41: =AA41/(1+$AZ$10) -> 0.46319349 | AG41: Discount Factor | AI41: =1/(1+$AZ$10) -> 0.92592593 | AJ41: =AI41/(1+$AZ$10) -> 0.85733882 | AK41: =AJ41/(1+$AZ$10) -> 0.79383224 | AL41: =AK41/(1+$AZ$10) -> 0.73502985 | AM41: =AL41/(1+$AZ$10) -> 0.6805832 | AN41: =AM41/(1+$AZ$10) -> 0.63016963 | AO41: =AN41/(1+$AZ$10) -> 0.5834904 | AP41: =AO41/(1+$AZ$10) -> 0.54026888 | AQ41: =AP41/(1+$AZ$10) -> 0.50024897 | AR41: =AQ41/(1+$AZ$10) -> 0.46319349 | AV41: Discount Factor | AX41: =1/(1+$AZ$10) -> 0.92592593 | AY41: =AX41/(1+$AZ$10) -> 0.85733882 | AZ41: =AY41/(1+$AZ$10) -> 0.79383224 | BA41: =AZ41/(1+$AZ$10) -> 0.73502985 | BB41: =BA41/(1+$AZ$10) -> 0.6805832 | BC41: =BB41/(1+$AZ$10) -> 0.63016963 | BD41: =BC41/(1+$AZ$10) -> 0.5834904 | BE41: =BD41/(1+$AZ$10) -> 0.54026888 | BF41: =BE41/(1+$AZ$10) -> 0.50024897 | BG41: =BF41/(1+$AZ$10) -> 0.46319349 | BL41: Discount Factor | BN41: =1/(1+$AZ$10) -> 0.92592593 | BO41: =BN41/(1+$AZ$10) -> 0.85733882 | BP41: =BO41/(1+$AZ$10) -> 0.79383224 | BQ41: =BP41/(1+$AZ$10) -> 0.73502985 | BR41: =BQ41/(1+$AZ$10) -> 0.6805832 | BS41: =BR41/(1+$AZ$10) -> 0.63016963 | BT41: =BS41/(1+$AZ$10) -> 0.5834904 | BU41: =BT41/(1+$AZ$10) -> 0.54026888 | BV41: =BU41/(1+$AZ$10) -> 0.50024897 | BW41: =BV41/(1+$AZ$10) -> 0.46319349
B42: Discounted Free Cash Flow | D42: =(D39+D40)*D41 -> 1491.4259 | E42: =(E39+E40)*E41 -> 1400.2086 | F42: =(F39+F40)*F41 -> 1169.6648 | G42: =(G39+G40)*G41 -> -8906.0695 | H42: =(H39+H40)*H41 -> 1386.5381 | I42: =(I39+I40)*I41 -> 1264.6948 | J42: =(J39+J40)*J41 -> 1202.8766 | K42: =(K39+K40)*K41 -> 1147.0067 | ... M42: =(M39+M40)*M41 -> 14949.276 | Q42: Discounted Free Cash Flow | S42: =(S39+S40)*S41 -> 0 | T42: =(T39+T40)*T41 -> 0 | U42: =(U39+U40)*U41 -> 0 | V42: =(V39+V40)*V41 -> -9592.4359 | W42: =(W39+W40)*W41 -> 594.55748 | X42: =(X39+X40)*X41 -> 593.77103 | Y42: =(Y39+Y40)*Y41 -> 593.84385 | Z42: =(Z39+Z40)*Z41 -> 594.72712 | ... AB42: =(AB39+AB40)*AB41 -> 8722.228 | AG42: Discounted Free Cash Flow | AI42: =(AI39+AI40)*AI41 -> 1491.4259 | AJ42: =(AJ39+AJ40)*AJ41 -> 1400.2086 | AK42: =(AK39+AK40)*AK41 -> 1169.6648 | AL42: =(AL39+AL40)*AL41 -> 686.36639 | AM42: =(AM39+AM40)*AM41 -> 919.38583 | AN42: =(AN39+AN40)*AN41 -> 788.89154 | AO42: =(AO39+AO40)*AO41 -> 718.26218 | AP42: =(AP39+AP40)*AP41 -> 653.41792 | ... AR42: =(AR39+AR40)*AR41 -> 7787.8245 | AV42: Discounted Free Cash Flow | AX42: =(AX39+AX40)*AX41 -> 1491.4259 | AY42: =(AY39+AY40)*AY41 -> 1408.5689 | AZ42: =(AZ39+AZ40)*AZ41 -> 1330.315 | BA42: =(BA39+BA40)*BA41 -> 1256.4087 | BB42: =(BB39+BB40)*BB41 -> 1186.6082 | BC42: =(BC39+BC40)*BC41 -> 921.20253 | BD42: =(BD39+BD40)*BD41 -> 870.02461 | BE42: =(BE39+BE40)*BE41 -> 821.68991 | ... BG42: =(BG39+BG40)*BG41 -> 13138.726 | BL42: Discounted Free Cash Flow | BN42: =(BN39+BN40)*BN41 -> 1491.4259 | BO42: =(BO39+BO40)*BO41 -> 1400.2086 | BP42: =(BP39+BP40)*BP41 -> 1169.6648 | BQ42: =(BQ39+BQ40)*BQ41 -> 686.36639 | BR42: =(BR39+BR40)*BR41 -> 919.38583 | BS42: =(BS39+BS40)*BS41 -> 788.89154 | BT42: =(BT39+BT40)*BT41 -> 718.26218 | BU42: =(BU39+BU40)*BU41 -> 653.41792 | ... BW42: =(BW39+BW40)*BW41 -> 7787.8245
B44: Beginning Cash | D44: =C48 -> 1247 | E44: =D48 -> 2857.7399 | F44: =E48 -> 4490.9433 | G44: =F48 -> 5964.3841 | H44: =G48 -> -6152.2251 | I44: =H48 -> -4114.9457 | J44: =I48 -> -2108.034 | K44: =J48 -> -46.514825 | ... M44: =L48 -> 4268.6979 | Q44: Beginning Cash | S44: =R48 -> 0 | T44: =S48 -> 0 | U44: =T48 -> 0 | V44: =U48 -> 0 | W44: =V48 -> -13050.403 | X44: =W48 -> -12176.803 | Y44: =X48 -> -11234.563 | Z44: =Y48 -> -10216.819 | ... AB44: =AA48 -> -7923.8625 | AG44: Beginning Cash | AI44: =AH48 -> 1247 | AJ44: =AI48 -> 2857.7399 | AK44: =AJ48 -> 4490.9433 | AL44: =AK48 -> 5964.3841 | AM44: =AL48 -> 6898.178 | AN44: =AM48 -> 8249.0574 | AO44: =AN48 -> 9500.9291 | AP44: =AO48 -> 10731.904 | ... AR44: =AQ48 -> 13128.56 | AV44: Beginning Cash | AX44: =AW48 -> 1247 | AY44: =AX48 -> 2857.7399 | AZ44: =AY48 -> 4500.6947 | BA44: =AZ48 -> 6176.5085 | BB44: =BA48 -> 7885.8386 | BC44: =BB48 -> 9629.3553 | BD44: =BC48 -> 11091.188 | BE44: =BD48 -> 12582.257 | ... BG44: =BF48 -> 15654.456 | BL44: Beginning Cash | BN44: =BM48 -> 1247 | BO44: =BN48 -> 2857.7399 | BP44: =BO48 -> 4490.9433 | BQ44: =BP48 -> 5964.3841 | BR44: =BQ48 -> 6898.178 | BS44: =BR48 -> 8249.0574 | BT44: =BS48 -> 9500.9291 | BU44: =BT48 -> 10731.904 | ... BW44: =BV48 -> 13128.56
B45: Free Cash Flow | D45: =D39 -> 1610.7399 | E45: =E39 -> 1633.2033 | F45: =F39 -> 1473.4408 | G45: =G39 -> -12116.609 | H45: =H39 -> 2037.2794 | I45: =I39 -> 2006.9117 | J45: =J39 -> 2061.5192 | K45: =K39 -> 2123.0294 | ... M45: =M39 -> 2269.7972 | Q45: Free Cash Flow | S45: =S39 -> 0 | T45: =T39 -> 0 | U45: =U39 -> 0 | V45: =V39 -> -13050.403 | W45: =W39 -> 873.6 | X45: =X39 -> 942.24 | Y45: =Y39 -> 1017.744 | Z45: =Z39 -> 1100.7984 | ... AB45: =AB39 -> 1292.6541 | AG45: Free Cash Flow | AI45: =AI39 -> 1610.7399 | AJ45: =AJ39 -> 1633.2033 | AK45: =AK39 -> 1473.4408 | AL45: =AL39 -> 933.7939 | AM45: =AM39 -> 1350.8794 | AN45: =AN39 -> 1251.8717 | AO45: =AO39 -> 1230.9752 | AP45: =AP39 -> 1209.431 | ... AR45: =AR39 -> 1164.3431 | AV45: Free Cash Flow | AX45: =AX39 -> 1610.7399 | AY45: =AY39 -> 1642.9547 | AZ45: =AZ39 -> 1675.8138 | BA45: =BA39 -> 1709.3301 | BB45: =BB39 -> 1743.5167 | BC45: =BC39 -> 1461.8326 | BD45: =BD39 -> 1491.0693 | BE45: =BE39 -> 1520.8907 | ... BG45: =BG39 -> 1582.3347 | BL45: Free Cash Flow | BN45: =BN39 -> 1610.7399 | BO45: =BO39 -> 1633.2033 | BP45: =BP39 -> 1473.4408 | BQ45: =BQ39 -> 933.7939 | BR45: =BR39 -> 1350.8794 | BS45: =BS39 -> 1251.8717 | BT45: =BT39 -> 1230.9752 | BU45: =BU39 -> 1209.431 | ... BW45: =BW39 -> 1164.3431
B46: Share Buybacks | Q46: Share Buybacks | AG46: Share Buybacks | AV46: Share Buybacks | BL46: Share Buybacks
B47: Dividends | Q47: Dividends | AG47: Dividends | AV47: Dividends | BL47: Dividends
B48: Ending Cash | C48: =R48+AH48 -> 1247 | D48: =SUM(D44:D47) -> 2857.7399 | E48: =SUM(E44:E47) -> 4490.9433 | F48: =SUM(F44:F47) -> 5964.3841 | G48: =SUM(G44:G47) -> -6152.2251 | H48: =SUM(H44:H47) -> -4114.9457 | I48: =SUM(I44:I47) -> -2108.034 | J48: =SUM(J44:J47) -> -46.514825 | K48: =SUM(K44:K47) -> 2076.5145 | ... M48: =SUM(M44:M47) -> 6538.495 | Q48: Ending Cash | R48: 0 | S48: =SUM(S44:S47) -> 0 | T48: =SUM(T44:T47) -> 0 | U48: =SUM(U44:U47) -> 0 | V48: =SUM(V44:V47) -> -13050.403 | W48: =SUM(W44:W47) -> -12176.803 | X48: =SUM(X44:X47) -> -11234.563 | Y48: =SUM(Y44:Y47) -> -10216.819 | Z48: =SUM(Z44:Z47) -> -9116.0207 | ... AB48: =SUM(AB44:AB47) -> -6631.2084 | AG48: Ending Cash | AH48: =AW48 -> 1247 | AI48: =SUM(AI44:AI47) -> 2857.7399 | AJ48: =SUM(AJ44:AJ47) -> 4490.9433 | AK48: =SUM(AK44:AK47) -> 5964.3841 | AL48: =SUM(AL44:AL47) -> 6898.178 | AM48: =SUM(AM44:AM47) -> 8249.0574 | AN48: =SUM(AN44:AN47) -> 9500.9291 | AO48: =SUM(AO44:AO47) -> 10731.904 | AP48: =SUM(AP44:AP47) -> 11941.335 | ... AR48: =SUM(AR44:AR47) -> 14292.903 | AV48: Ending Cash | AW48: =Baseline!C21 -> 1247 | AX48: =SUM(AX44:AX47) -> 2857.7399 | AY48: =SUM(AY44:AY47) -> 4500.6947 | AZ48: =SUM(AZ44:AZ47) -> 6176.5085 | BA48: =SUM(BA44:BA47) -> 7885.8386 | BB48: =SUM(BB44:BB47) -> 9629.3553 | BC48: =SUM(BC44:BC47) -> 11091.188 | BD48: =SUM(BD44:BD47) -> 12582.257 | BE48: =SUM(BE44:BE47) -> 14103.148 | ... BG48: =SUM(BG44:BG47) -> 17236.791 | BL48: Ending Cash | BM48: =AH48 -> 1247 | BN48: =SUM(BN44:BN47) -> 2857.7399 | BO48: =SUM(BO44:BO47) -> 4490.9433 | BP48: =SUM(BP44:BP47) -> 5964.3841 | BQ48: =SUM(BQ44:BQ47) -> 6898.178 | BR48: =SUM(BR44:BR47) -> 8249.0574 | BS48: =SUM(BS44:BS47) -> 9500.9291 | BT48: =SUM(BT44:BT47) -> 10731.904 | BU48: =SUM(BU44:BU47) -> 11941.335 | ... BW48: =SUM(BW44:BW47) -> 14292.903
B50: NPV / Enterprise Value | C50: =SUM(D42:N42) -> 16202.259 | Q50: NPV / Enterprise Value | R50: =SUM(S42:AC42) -> 2103.0676 | AG50: NPV / Enterprise Value | AH50: =SUM(AI42:AS42) -> 16209.356 | AV50: NPV / Enterprise Value | AW50: =SUM(AX42:BH42) -> 23201.01 | BL50: NPV / Enterprise Value | BM50: =SUM(BN42:BX42) -> 16209.356
B51: Debt | C51: =-Baseline!$C$23 -> -7765 | AG51: Debt | AH51: =-Baseline!$C$23 -> -7765 | AV51: Debt | AW51: =-Baseline!$C$23 -> -7765 | BL51: Debt | BM51: =-Baseline!$C$23 -> -7765
B52: Minority | C52: =-Baseline!$C$24 -> -418 | AG52: Minority | AH52: =-Baseline!$C$24 -> -418 | AV52: Minority | AW52: =-Baseline!$C$24 -> -418 | BL52: Minority | BM52: =-Baseline!$C$24 -> -418
B53: Equity Value | C53: =C50+C51+C52 -> 8019.2593 | Q53: Equity Value | R53: =R50 -> 2103.0676 | AG53: Equity Value | AH53: =AH50+AH51+AH52 -> 8026.3558 | AV53: Equity Value | AW53: =AW50+AW51+AW52 -> 15018.01 | BL53: Equity Value | BM53: =BM50+BM51+BM52 -> 8026.3558
B54: Shares outstanding, in millions | C54: =Baseline!$C$25 -> 287.34 | Q54: Shares outstanding, in millions | R54: =Baseline!$C$25 -> 287.34 | AG54: Shares outstanding, in millions | AH54: =Baseline!$C$25 -> 287.34 | AV54: Shares outstanding, in millions | AW54: =Baseline!$C$25 -> 287.34 | BL54: Shares outstanding, in millions | BM54: =Baseline!$C$25 -> 287.34
B55: Share price | C55: =C53/C54 -> 27.908608 | Q55: Share price | R55: =R53/R54 -> 7.3190908 | AG55: Share price | AH55: =AH53/AH54 -> 27.933305 | AV55: Share price | AW55: =AW53/AW54 -> 52.265643 | BL55: Share price | BM55: =BM53/BM54 -> 27.933305
B56: TSR | C56: =_xlfn.RRI(5,AW55,C55*(1+Decisions!$F$43)^5) -> -0.035894553
B58: Perfomance metrics | Q58: Perfomance metrics | AG58: Perfomance metrics | AV58: Perfomance metrics
B59: ROIC | D59: =(D62)*(1-D67) * D22/D73 -> 0.10176702 | E59: =(E62)*(1-E67) * E22/E73 -> 0.10318627 | F59: =(F62)*(1-F67) * F22/F73 -> 0.093092424 | G59: =(G62)*(1-G67) * G22/G73 -> 0.032335685 | H59: =(H62)*(1-H67) * H22/H73 -> 0.070547501 | I59: =(I62)*(1-I67) * I22/I73 -> 0.072038936 | J59: =(J62)*(1-J67) * J22/J73 -> 0.073735871 | K59: =(K62)*(1-K67) * K22/K73 -> 0.075659646 | ... M59: =(M62)*(1-M67) * M22/M73 -> 0.080283731 | Q59: ROIC | S59: =IFERROR((S61-S66)*(1-S67) * -$W$22/$AC$19,"") | T59: =IFERROR((T32+T34)/T73,"") | U59: =IFERROR((U32+U34)/U73,"") | V59: =IFERROR((V32+V34)/V73,"") -> 0 | W59: =IFERROR((W32+W34)/W73,"") -> 0.066940461 | X59: =IFERROR((X32+X34)/X73,"") -> 0.072200069 | Y59: =IFERROR((Y32+Y34)/Y73,"") -> 0.077985637 | Z59: =IFERROR((Z32+Z34)/Z73,"") -> 0.084349762 | AA59: =IFERROR((AA32+AA34)/AA73,"") -> 0.0913503 | AB59: =IFERROR((AB32+AB34)/AB73,"") -> 0.099050892 | AG59: ROIC | AI59: =(AI61-AI66)*(1-AI67) * AI22/AI73 -> 0.10176702 | AJ59: =(AJ61-AJ66)*(1-AJ67) * AJ22/AJ73 -> 0.10318627 | AK59: =(AK61-AK66)*(1-AK67) * AK22/AK73 -> 0.093092424 | AL59: =(AL61-AL66)*(1-AL67) * AL22/AL73 -> 0.058997373 | AM59: =(AM61-AM66)*(1-AM67) * AM22/AM73 -> 0.085348958 | AN59: =(AN61-AN66)*(1-AN67) * AN22/AN73 -> 0.083675248 | AO59: =(AO61-AO66)*(1-AO67) * AO22/AO73 -> 0.081976557 | AP59: =(AP61-AP66)*(1-AP67) * AP22/AP73 -> 0.080252512 | ... AR59: =(AR61-AR66)*(1-AR67) * AR22/AR73 -> 0.076726843 | AV59: ROIC | AW59: =(AW62)*(1-AW67) * AW22/AW73 -> 0.10427781 | AX59: =(AX62)*(1-AX67) * AX22/AX73 -> 0.10176702 | AY59: =(AY62)*(1-AY67) * AY22/AY73 -> 0.10380236 | AZ59: =(AZ62)*(1-AZ67) * AZ22/AZ73 -> 0.10587841 | BA59: =(BA62)*(1-BA67) * BA22/BA73 -> 0.10799598 | BB59: =(BB62)*(1-BB67) * BB22/BB73 -> 0.1101559 | BC59: =(BC62)*(1-BC67) * BC22/BC73 -> 0.1101559 | BD59: =(BD62)*(1-BD67) * BD22/BD73 -> 0.1101559 | ... BG59: =(BG62)*(1-BG67) * BG22/BG73 -> 0.1101559 | BL59: ROIC | BN59: =(BN61-BN66)*(1-BN67) * BN22/BN73 -> 0.10176702 | BO59: =(BO61-BO66)*(1-BO67) * BO22/BO73 -> 0.10318627 | BP59: =(BP61-BP66)*(1-BP67) * BP22/BP73 -> 0.093092424 | BQ59: =(BQ61-BQ66)*(1-BQ67) * BQ22/BQ73 -> 0.058997373 | BR59: =(BR61-BR66)*(1-BR67) * BR22/BR73 -> 0.085348958 | BS59: =(BS61-BS66)*(1-BS67) * BS22/BS73 -> 0.083675248 | BT59: =(BT61-BT66)*(1-BT67) * BT22/BT73 -> 0.081976557 | BU59: =(BU61-BU66)*(1-BU67) * BU22/BU73 -> 0.080252512 | ... BW59: =(BW61-BW66)*(1-BW67) * BW22/BW73 -> 0.076726843
B60: Revenue Growth | D60: =D22/C22-1 -> 0.02 | E60: =E22/D22-1 -> 0.017 | F60: =F22/E22-1 -> 0.015 | G60: =G22/F22-1 -> -0.159 | H60: =H22/G22-1 -> 0.37991036 | I60: =I22/H22-1 -> 0.019520135 | J60: =J22/I22-1 -> 0.020666339 | K60: =K22/J22-1 -> 0.021884042 | ... M60: =M22/L22-1 -> 0.024539362 | Q60: Revenue Growth | R60: =IFERROR(R22/Q22-1,"") | S60: =IFERROR(S22/R22-1,"") | T60: =IFERROR(T22/S22-1,"") | U60: =IFERROR(U22/T22-1,"") | V60: =IFERROR(V22/U22-1,"") | W60: =IFERROR(W22/V22-1,"") | X60: =IFERROR(X22/W22-1,"") -> 0.1 | Y60: =IFERROR(Y22/X22-1,"") -> 0.1 | ... AB60: =IFERROR(AB22/AA22-1,"") -> 0.1 | AG60: Revenue Growth | AH60: 0 | AI60: =IF(SUM($AI$9:$AM$9)=1,AI95,IF(SUM($AI$9:$AM$9)=2,AI96,IF(SUM($AI$9:$AM$9)=3,AI97,IF(SUM($AI$9:$AM$9)=4,AI98,IF(SUM($AI$9:$AM$9)=5,AI99,AX60))))) -> 0.02 | AJ60: =IF(SUM($AI$9:$AM$9)=1,AJ95,IF(SUM($AI$9:$AM$9)=2,AJ96,IF(SUM($AI$9:$AM$9)=3,AJ97,IF(SUM($AI$9:$AM$9)=4,AJ98,IF(SUM($AI$9:$AM$9)=5,AJ99,AY60))))) -> 0.017 | AK60: =IF(SUM($AI$9:$AM$9)=1,AK95,IF(SUM($AI$9:$AM$9)=2,AK96,IF(SUM($AI$9:$AM$9)=3,AK97,IF(SUM($AI$9:$AM$9)=4,AK98,IF(SUM($AI$9:$AM$9)=5,AK99,AZ60))))) -> 0.015 | AL60: =IF(SUM($AI$9:$AM$9)=1,AL95,IF(SUM($AI$9:$AM$9)=2,AL96,IF(SUM($AI$9:$AM$9)=3,AL97,IF(SUM($AI$9:$AM$9)=4,AL98,IF(SUM($AI$9:$AM$9)=5,AL99,BA60))))) -> -0.159 | AM60: =IF(SUM($AI$9:$AM$9)=1,AM95,IF(SUM($AI$9:$AM$9)=2,AM96,IF(SUM($AI$9:$AM$9)=3,AM97,IF(SUM($AI$9:$AM$9)=4,AM98,IF(SUM($AI$9:$AM$9)=5,AM99,BB60))))) -> 0.169 | AN60: =IF(SUM($AI$9:$AM$9)=1,AN95,IF(SUM($AI$9:$AM$9)=2,AN96,IF(SUM($AI$9:$AM$9)=3,AN97,IF(SUM($AI$9:$AM$9)=4,AN98,IF(SUM($AI$9:$AM$9)=5,AN99,BC60))))) -> 0.005 | AO60: =IF(SUM($AI$9:$AM$9)=1,AO95,IF(SUM($AI$9:$AM$9)=2,AO96,IF(SUM($AI$9:$AM$9)=3,AO97,IF(SUM($AI$9:$AM$9)=4,AO98,IF(SUM($AI$9:$AM$9)=5,AO99,BD60))))) -> 0.005 | AP60: =IF(SUM($AI$9:$AM$9)=1,AP95,IF(SUM($AI$9:$AM$9)=2,AP96,IF(SUM($AI$9:$AM$9)=3,AP97,IF(SUM($AI$9:$AM$9)=4,AP98,IF(SUM($AI$9:$AM$9)=5,AP99,BE60))))) -> 0.005 | ... AR60: =IF(SUM($AI$9:$AM$9)=1,AR95,IF(SUM($AI$9:$AM$9)=2,AR96,IF(SUM($AI$9:$AM$9)=3,AR97,IF(SUM($AI$9:$AM$9)=4,AR98,IF(SUM($AI$9:$AM$9)=5,AR99,BG60))))) -> 0.005 | AV60: Revenue Growth | AW60: 0 | AX60: 0.02 | AY60: =AX60 -> 0.02 | AZ60: =AY60 -> 0.02 | BA60: =AZ60 -> 0.02 | BB60: =BA60 -> 0.02 | BC60: =BB60 -> 0.02 | BD60: =BC60 -> 0.02 | BE60: =BD60 -> 0.02 | BF60: =BE60 -> 0.02 | BG60: =BF60 -> 0.02 | BL60: Revenue Growth | BN60: =(AI80<>0)*AI80 + (AI81<>0)*AI81 + AX60 * (AI80 =0)*(AI81=0) + BN90 -> 0.02 | BO60: =(AJ80<>0)*AJ80 + (AJ81<>0)*AJ81 + AY60 * (AJ80 =0)*(AJ81=0) + BO90 -> 0.017 | BP60: =(AK80<>0)*AK80 + (AK81<>0)*AK81 + AZ60 * (AK80 =0)*(AK81=0) + BP90 -> 0.015 | BQ60: =(AL80<>0)*AL80 + (AL81<>0)*AL81 + BA60 * (AL80 =0)*(AL81=0) + BQ90 -> -0.159 | BR60: =(AM80<>0)*AM80 + (AM81<>0)*AM81 + BB60 * (AM80 =0)*(AM81=0) + BR90 -> 0.169 | BS60: =(AN80<>0)*AN80 + (AN81<>0)*AN81 + BC60 * (AN80 =0)*(AN81=0) + BS90 -> 0.005 | BT60: =(AO80<>0)*AO80 + (AO81<>0)*AO81 + BD60 * (AO80 =0)*(AO81=0) + BT90 -> 0.005 | BU60: =(AP80<>0)*AP80 + (AP81<>0)*AP81 + BE60 * (AP80 =0)*(AP81=0) + BU90 -> 0.005 | ... BW60: =(AR80<>0)*AR80 + (AR81<>0)*AR81 + BG60 * (AR80 =0)*(AR81=0) + BW90 -> 0.005
B61: EBITDA margin | D61: =D30/D22 -> 0.08726305 | E61: =E30/E22 -> 0.087121121 | F61: =F30/F22 -> 0.081883409 | G61: =G30/G22 -> 0.071561988 | H61: =H30/H22 -> 0.089901436 | I61: =I30/I22 -> 0.090117734 | J61: =J30/J22 -> 0.090397658 | K61: =K30/K22 -> 0.090744398 | ... M61: =M30/M22 -> 0.091649803 | Q61: EBITDA margin | S61: =IFERROR(S30/S22,"") | T61: =IFERROR(T30/T22,"") | U61: =IFERROR(U30/U22,"") | V61: =IFERROR(V30/V22,"") | W61: =IFERROR(W30/W22,"") -> 0.18 | X61: =IFERROR(X30/X22,"") -> 0.17727273 | Y61: =IFERROR(Y30/Y22,"") -> 0.17479339 | Z61: =IFERROR(Z30/Z22,"") -> 0.17253944 | ... AB61: =IFERROR(AB30/AB22,"") -> 0.16862764 | AG61: EBITDA margin | AH61: =AH25/AH22 -> 0.08726305 | AI61: =AI30/AI22 -> 0.08726305 | AJ61: =AJ30/AJ22 -> 0.087121121 | AK61: =AK30/AK22 -> 0.081883409 | AL61: =AL30/AL22 -> 0.071561988 | AM61: =AM30/AM22 -> 0.079058485 | AN61: =AN30/AN22 -> 0.07829254 | AO61: =AO30/AO22 -> 0.077515164 | AP61: =AP30/AP22 -> 0.076726184 | ... AR61: =AR30/AR22 -> 0.075112722 | AV61: EBITDA margin | AW61: =AW25/AW22 -> 0.08726305 | AX61: =AX30/AX22 -> 0.08726305 | AY61: =AY30/AY22 -> 0.08726305 | AZ61: =AZ30/AZ22 -> 0.08726305 | BA61: =BA30/BA22 -> 0.08726305 | BB61: =BB30/BB22 -> 0.08726305 | BC61: =BC30/BC22 -> 0.08726305 | BD61: =BD30/BD22 -> 0.08726305 | BE61: =BE30/BE22 -> 0.08726305 | ... BG61: =BG30/BG22 -> 0.08726305 | BL61: EBITDA margin | BM61: =BM25/BM22 -> 0.08726305 | BN61: =BN30/BN22 -> 0.08726305 | BO61: =BO30/BO22 -> 0.087121121 | BP61: =BP30/BP22 -> 0.081883409 | BQ61: =BQ30/BQ22 -> 0.071561988 | BR61: =BR30/BR22 -> 0.079058485 | BS61: =BS30/BS22 -> 0.07829254 | BT61: =BT30/BT22 -> 0.077515164 | BU61: =BU30/BU22 -> 0.076726184 | ... BW61: =BW30/BW22 -> 0.075112722
B62: EBIT margin | D62: =D32/D22 -> 0.04726305 | E62: =E32/E22 -> 0.047121121 | F62: =F32/F22 -> 0.041883409 | G62: =G32/G22 -> 0.031561988 | H62: =H32/H22 -> 0.049901436 | I62: =I32/I22 -> 0.050117734 | J62: =J32/J22 -> 0.050397658 | K62: =K32/K22 -> 0.050744398 | ... M62: =M32/M22 -> 0.051649803 | Q62: EBIT margin | AG62: EBIT margin | AV62: EBIT margin | AW62: =AW32/AW22 -> 0.049397703 | AX62: =AX32/AX22 -> 0.04726305 | AY62: =AY32/AY22 -> 0.04726305 | AZ62: =AZ32/AZ22 -> 0.04726305 | BA62: =BA32/BA22 -> 0.04726305 | BB62: =BB32/BB22 -> 0.04726305 | BC62: =BC32/BC22 -> 0.04726305 | BD62: =BD32/BD22 -> 0.04726305 | ... BG62: =BG32/BG22 -> 0.04726305 | BL62: EBIT margin | BN62: =BN32/BN22 -> 0.04726305 | BO62: =BO32/BO22 -> 0.047121121 | BP62: =BP32/BP22 -> 0.041883409 | BQ62: =BQ32/BQ22 -> 0.031561988 | BR62: =BR32/BR22 -> 0.039058485 | BS62: =BS32/BS22 -> 0.03829254 | BT62: =BT32/BT22 -> 0.037515164 | BU62: =BU32/BU22 -> 0.036726184 | ... BW62: =BW32/BW22 -> 0.035112722
B63: COGS/Revenue | D63: =-(D26+D23+D27)/D22 -> 0.86462321 | E63: =-(E26+E23+E27)/E22 -> 0.86462321 | F63: =-(F26+F23+F27)/F22 -> 0.86962321 | G63: =-(G26+G23+G27)/G22 -> 0.86962321 | H63: =-(H26+H23+H27)/H22 -> 0.85898176 | I63: =-(I26+I23+I27)/I22 -> 0.85814173 | J63: =-(J26+J23+J27)/J22 -> 0.85724931 | K63: =-(K26+K23+K27)/K22 -> 0.85630341 | ... M63: =-(M26+M23+M27)/M22 -> 0.85424858 | Q63: COGS/Revenue | S63: =IFERROR(-S23/S22,"") | T63: =IFERROR(-(T23+T26+T27)/T22,"") | U63: =IFERROR(-(U23+U26+U27)/U22,"") | V63: =IFERROR(-(V23+V26+V27)/V22,"") | W63: =IFERROR(-(W23+W26+W27)/W22,"") -> 0.8 | X63: =IFERROR(-(X23+X26+X27)/X22,"") -> 0.8 | Y63: =IFERROR(-(Y23+Y26+Y27)/Y22,"") -> 0.8 | Z63: =IFERROR(-(Z23+Z26+Z27)/Z22,"") -> 0.8 | AA63: =IFERROR(-(AA23+AA26+AA27)/AA22,"") -> 0.8 | AB63: =IFERROR(-(AB23+AB26+AB27)/AB22,"") -> 0.8 | AG63: COGS/Revenue | AH63: =-AH23/AH22 -> 0.86462321 | AI63: =AH63+AI79*AI9 -> 0.86462321 | AJ63: =AI63+AJ79*AJ9 -> 0.86462321 | AK63: =AJ63+AK79*AK9 -> 0.86962321 | AL63: =AK63+AL79*AL9 -> 0.86962321 | AM63: =AL63+AM79*AM9 -> 0.86962321 | AN63: =AM63+AN79*AN9 -> 0.86962321 | AO63: =AN63+AO79*AO9 -> 0.86962321 | AP63: =AO63+AP79*AP9 -> 0.86962321 | ... AR63: =AQ63+AR79*AR9 -> 0.86962321 | AV63: COGS/Revenue | AW63: =-AW23/AW22 -> 0.86462321 | AX63: =AW63 -> 0.86462321 | AY63: =AX63 -> 0.86462321 | AZ63: =AY63 -> 0.86462321 | BA63: =AZ63 -> 0.86462321 | BB63: =BA63 -> 0.86462321 | BC63: =BB63 -> 0.86462321 | BD63: =BC63 -> 0.86462321 | BE63: =BD63 -> 0.86462321 | ... BG63: =BF63 -> 0.86462321 | BL63: COGS/Revenue | BN63: =AI63 -> 0.86462321 | BO63: =AJ63 -> 0.86462321 | BP63: =AK63 -> 0.86962321 | BQ63: =AL63 -> 0.86962321 | BR63: =AM63 -> 0.86962321 | BS63: =AN63 -> 0.86962321 | BT63: =AO63 -> 0.86962321 | BU63: =AP63 -> 0.86962321 | ... BW63: =AR63 -> 0.86962321
B64: SGA/Revenue | D64: =-(D24+D28)/D22 -> 0.048113736 | E64: =-(E24+E28)/E22 -> 0.048255665 | F64: =-(F24+F28)/F22 -> 0.048493377 | G64: =-(G24+G28)/G22 -> 0.058814798 | H64: =-(H24+H28)/H22 -> 0.051116807 | I64: =-(I24+I28)/I22 -> 0.051740535 | J64: =-(J24+J28)/J22 -> 0.052353035 | K64: =-(K24+K28)/K22 -> 0.052952195 | ... M64: =-(M24+M28)/M22 -> 0.05410162 | Q64: SGA/Revenue | S64: =IFERROR(-S24/S22,"") | T64: =IFERROR(-(T24+T28)/T22,"") | U64: =IFERROR(-(U24+U28)/U22,"") | V64: =IFERROR(-(V24+V28)/V22,"") | W64: =IFERROR(-(W24+W28)/W22,"") -> 0.05 | X64: =IFERROR(-(X24+X28)/X22,"") -> 0.05 | Y64: =IFERROR(-(Y24+Y28)/Y22,"") -> 0.05 | Z64: =IFERROR(-(Z24+Z28)/Z22,"") -> 0.05 | AA64: =IFERROR(-(AA24+AA28)/AA22,"") -> 0.05 | AB64: =IFERROR(-(AB24+AB28)/AB22,"") -> 0.05 | AG64: SGA/Revenue | AH64: =-AH24/AH22 -> 0.048113736 | AI64: =-AI24/AI22 -> 0.048113736 | AJ64: =-AJ24/AJ22 -> 0.048255665 | AK64: =-AK24/AK22 -> 0.048493377 | AL64: =-AL24/AL22 -> 0.058814798 | AM64: =-AM24/AM22 -> 0.051318301 | AN64: =-AN24/AN22 -> 0.052084245 | AO64: =-AO24/AO22 -> 0.052861622 | ... AR64: =-AR24/AR22 -> 0.055264064 | AV64: SGA/Revenue | AW64: =-AW24/AW22 -> 0.048113736 | AX64: =AW64 -> 0.048113736 | AY64: =AX64 -> 0.048113736 | AZ64: =AY64 -> 0.048113736 | BA64: =AZ64 -> 0.048113736 | BB64: =BA64 -> 0.048113736 | BC64: =BB64 -> 0.048113736 | BD64: =BC64 -> 0.048113736 | BE64: =BD64 -> 0.048113736 | ... BG64: =BF64 -> 0.048113736 | BL64: SGA/Revenue | BM64: =-BM24/BM22 -> 0.048113736 | BN64: =-BN24/BN22 -> 0.048113736 | BO64: =-BO24/BO22 -> 0.048255665 | BP64: =-BP24/BP22 -> 0.048493377 | BQ64: =-BQ24/BQ22 -> 0.058814798 | BR64: =-BR24/BR22 -> 0.051318301 | BS64: =-BS24/BS22 -> 0.052084245 | BT64: =-BT24/BT22 -> 0.052861622 | ... BW64: =-BW24/BW22 -> 0.055264064
AG65: SGA Growth, yoy | AI65: =AX60 -> 0.02 | AJ65: =AI65 -> 0.02 | AK65: =AJ65 -> 0.02 | AL65: =AK65 -> 0.02 | AM65: =AL65 -> 0.02 | AN65: =AM65 -> 0.02 | AO65: =AN65 -> 0.02 | AP65: =AO65 -> 0.02 | AQ65: =AP65 -> 0.02 | AR65: =AQ65 -> 0.02 | AV65: SGA Growth, yoy | AX65: =AX60 -> 0.02 | AY65: =AX65 -> 0.02 | AZ65: =AY65 -> 0.02 | BA65: =AZ65 -> 0.02 | BB65: =BA65 -> 0.02 | BC65: =BB65 -> 0.02 | BD65: =BC65 -> 0.02 | BE65: =BD65 -> 0.02 | BF65: =BE65 -> 0.02 | BG65: =BF65 -> 0.02 | BL65: SGA Growth, yoy | BN65: =AI65 -> 0.02 | BO65: =AJ65 -> 0.02 | BP65: =AK65 -> 0.02 | BQ65: =AL65 -> 0.02 | BR65: =AM65 -> 0.02 | BS65: =AN65 -> 0.02 | BT65: =AO65 -> 0.02 | BU65: =AP65 -> 0.02 | ... BW65: =AR65 -> 0.02
B66: CAPEX/Revenue | D66: =-D36/D22 -> 0.04 | E66: =-E36/E22 -> 0.04 | F66: =-F36/F22 -> 0.04 | G66: =-G36/G22 -> 0.04 | H66: =-H36/H22 -> 0.04 | I66: =-I36/I22 -> 0.04 | J66: =-J36/J22 -> 0.04 | K66: =-K36/K22 -> 0.04 | ... M66: =-M36/M22 -> 0.04 | Q66: CAPEX/Revenue | S66: =IFERROR(-S36/S22,"") | T66: =IFERROR(-T36/T22,"") | U66: =IFERROR(-U36/U22,"") | V66: =IFERROR(-V36/V22,"") | W66: =IFERROR(-W36/W22,"") -> 0.04 | X66: =IFERROR(-X36/X22,"") -> 0.04 | Y66: =IFERROR(-Y36/Y22,"") -> 0.04 | Z66: =IFERROR(-Z36/Z22,"") -> 0.04 | ... AB66: =IFERROR(-AB36/AB22,"") -> 0.04 | AG66: CAPEX/Revenue | AH66: =-AH36/AH22 -> 0.04 | AI66: =Decisions!$F$40 -> 0.04 | AJ66: =Decisions!$F$40 -> 0.04 | AK66: =Decisions!$F$40 -> 0.04 | AL66: =Decisions!$F$40 -> 0.04 | AM66: =Decisions!$F$40 -> 0.04 | AN66: =Decisions!$F$40 -> 0.04 | AO66: =Decisions!$F$40 -> 0.04 | AP66: =Decisions!$F$40 -> 0.04 | ... AR66: =Decisions!$F$40 -> 0.04 | AV66: CAPEX/Revenue | AW66: =-AW36/AW22 -> 0.04 | AX66: =Decisions!$F$40 -> 0.04 | AY66: =Decisions!$F$40 -> 0.04 | AZ66: =Decisions!$F$40 -> 0.04 | BA66: =Decisions!$F$40 -> 0.04 | BB66: =Decisions!$F$40 -> 0.04 | BC66: =Decisions!$F$40 -> 0.04 | BD66: =Decisions!$F$40 -> 0.04 | BE66: =Decisions!$F$40 -> 0.04 | ... BG66: =Decisions!$F$40 -> 0.04 | BL66: CAPEX/Revenue | BN66: =AI66 -> 0.04 | BO66: =AJ66 -> 0.04 | BP66: =AK66 -> 0.04 | BQ66: =AL66 -> 0.04 | BR66: =AM66 -> 0.04 | BS66: =AN66 -> 0.04 | BT66: =AO66 -> 0.04 | BU66: =AP66 -> 0.04 | ... BW66: =AR66 -> 0.04
B67: Taxes | D67: =AI67 -> 0.22 | E67: =AJ67 -> 0.22 | F67: =AK67 -> 0.22 | G67: =AL67 -> 0.22 | H67: =AM67 -> 0.22 | I67: =AN67 -> 0.22 | J67: =AO67 -> 0.22 | K67: =AP67 -> 0.22 | ... M67: =AR67 -> 0.22 | Q67: Taxes | S67: =AI67 -> 0.22 | T67: =AJ67 -> 0.22 | U67: =AK67 -> 0.22 | V67: =AL67 -> 0.22 | W67: =AM67 -> 0.22 | X67: =AN67 -> 0.22 | Y67: =AO67 -> 0.22 | Z67: =AP67 -> 0.22 | ... AB67: =AR67 -> 0.22 | AG67: Taxes | AI67: =Decisions!$F$41 -> 0.22 | AJ67: =Decisions!$F$41 -> 0.22 | AK67: =Decisions!$F$41 -> 0.22 | AL67: =Decisions!$F$41 -> 0.22 | AM67: =Decisions!$F$41 -> 0.22 | AN67: =Decisions!$F$41 -> 0.22 | AO67: =Decisions!$F$41 -> 0.22 | AP67: =Decisions!$F$41 -> 0.22 | ... AR67: =Decisions!$F$41 -> 0.22 | AV67: Taxes | AW67: =Decisions!$F$41 -> 0.22 | AX67: =Decisions!$F$41 -> 0.22 | AY67: =Decisions!$F$41 -> 0.22 | AZ67: =Decisions!$F$41 -> 0.22 | BA67: =Decisions!$F$41 -> 0.22 | BB67: =Decisions!$F$41 -> 0.22 | BC67: =Decisions!$F$41 -> 0.22 | BD67: =Decisions!$F$41 -> 0.22 | ... BG67: =Decisions!$F$41 -> 0.22 | BL67: Taxes | BN67: =AI67 -> 0.22 | BO67: =AJ67 -> 0.22 | BP67: =AK67 -> 0.22 | BQ67: =AL67 -> 0.22 | BR67: =AM67 -> 0.22 | BS67: =AN67 -> 0.22 | BT67: =AO67 -> 0.22 | BU67: =AP67 -> 0.22 | ... BW67: =AR67 -> 0.22
AX69: =AX61-AX66 -> 0.04726305
B71: Invested Capital | Q71: Invested Capital | AG71: Invested Capital | AV71: Invested Capital | BL71: Invested Capital
B72: Invested Capital beginning | D72: =C73 -> 15827.72 | E72: =D73 -> 15827.72 | F72: =E73 -> 15827.72 | G72: =F73 -> 15827.72 | H72: =G73 -> 28878.123 | I72: =H73 -> 28878.123 | J72: =I73 -> 28957.262 | K72: =J73 -> 29036.796 | ... M72: =L73 -> 29197.06 | Q72: Invested Capital beginning | S72: =R73 -> 0 | T72: =S73 -> 0 | U72: =T73 -> 0 | V72: =U73 -> 0 | W72: =V73 -> 13050.403 | X72: =W73 -> 13050.403 | Y72: =X73 -> 13050.403 | Z72: =Y73 -> 13050.403 | ... AB72: =AA73 -> 13050.403 | AG72: Invested Capital beginning | AI72: =AH73 -> 15827.72 | AJ72: =AI73 -> 15827.72 | AK72: =AJ73 -> 15827.72 | AL72: =AK73 -> 15827.72 | AM72: =AL73 -> 15827.72 | AN72: =AM73 -> 15827.72 | AO72: =AN73 -> 15906.859 | AP72: =AO73 -> 15986.393 | ... AR72: =AQ73 -> 16146.656 | AV72: Invested Capital beginning | AX72: =AW73 -> 15827.72 | AY72: =AX73 -> 15827.72 | AZ72: =AY73 -> 15827.72 | BA72: =AZ73 -> 15827.72 | BB72: =BA73 -> 15827.72 | BC72: =BB73 -> 15827.72 | BD72: =BC73 -> 16144.274 | BE72: =BD73 -> 16467.16 | ... BG72: =BF73 -> 17132.433 | BL72: Invested Capital beginning | BN72: =BM73 -> 15827.72 | BO72: =BN73 -> 15827.72 | BP72: =BO73 -> 15827.72 | BQ72: =BP73 -> 15827.72 | BR72: =BQ73 -> 15827.72 | BS72: =BR73 -> 15827.72 | BT72: =BS73 -> 15906.859 | BU72: =BT73 -> 15986.393 | ... BW72: =BV73 -> 16146.656
B73: Invested Capital ending | C73: =AH73 -> 15827.72 | D73: =D72-D37-D17 -> 15827.72 | E73: =E72-E37-E17 -> 15827.72 | F73: =F72-F37-F17 -> 15827.72 | G73: =G72-G37-G17 -> 28878.123 | H73: =H72-H37-H17 -> 28878.123 | I73: =I72-I37-I17 -> 28957.262 | J73: =J72-J37-J17 -> 29036.796 | K73: =K72-K37-K17 -> 29116.728 | ... M73: =M72-M37-M17 -> 29277.793 | N73: =M73=AB73+AR73 -> TRUE | Q73: Invested Capital ending | R73: 0 | S73: =S72-S37-S17 -> 0 | T73: =T72-T37-T17 -> 0 | U73: =U72-U37-U17 -> 0 | V73: =V72-V37-V17 -> 13050.403 | W73: =W72-W37-W17 -> 13050.403 | X73: =X72-X37-X17 -> 13050.403 | Y73: =Y72-Y37-Y17 -> 13050.403 | Z73: =Z72-Z37-Z17 -> 13050.403 | ... AB73: =AB72-AB37-AB17 -> 13050.403 | AG73: Invested Capital ending | AH73: =AW73 -> 15827.72 | AI73: =AI72 -> 15827.72 | AJ73: =AJ72 -> 15827.72 | AK73: =AK72 -> 15827.72 | AL73: =AL72 -> 15827.72 | AM73: =AM72 -> 15827.72 | AN73: =1/$AM$74*AN22 -> 15906.859 | AO73: =1/$AM$74*AO22 -> 15986.393 | AP73: =1/$AM$74*AP22 -> 16066.325 | AQ73: =1/$AM$74*AQ22 -> 16146.656 | AR73: =1/$AM$74*AR22 -> 16227.39 | AV73: Invested Capital ending | AW73: 15827.72 | AX73: =AX72 -> 15827.72 | AY73: =AY72 -> 15827.72 | AZ73: =AZ72 -> 15827.72 | BA73: =BA72 -> 15827.72 | BB73: =BB72 -> 15827.72 | BC73: =1/$BB$74*BC22 -> 16144.274 | BD73: =1/$BB$74*BD22 -> 16467.16 | BE73: =1/$BB$74*BE22 -> 16796.503 | BF73: =1/$BB$74*BF22 -> 17132.433 | BG73: =1/$BB$74*BG22 -> 17475.082 | BL73: Invested Capital ending | BM73: =AH73 -> 15827.72 | BN73: =BN72 -> 15827.72 | BO73: =BO72 -> 15827.72 | BP73: =BP72 -> 15827.72 | BQ73: =BQ72 -> 15827.72 | BR73: =BR72 -> 15827.72 | BS73: =1/$BR$74*BS22 -> 15906.859 | BT73: =1/$BR$74*BT22 -> 15986.393 | BU73: =1/$BR$74*BU22 -> 16066.325 | BV73: =1/$BR$74*BV22 -> 16146.656 | BW73: =1/$BR$74*BW22 -> 16227.39
B74: Capital turnover | C74: =C22/C73 -> 2.7063911 | D74: =D22/D73 -> 2.7605189 | E74: =E22/E73 -> 2.8074477 | F74: =F22/F73 -> 2.8495594 | G74: =G22/G73 -> 1.3134789 | H74: =H22/H73 -> 1.8124832 | Q74: Capital turnover | T74: =T20/T73 -> #DIV/0! | U74: =U20/U73 -> #DIV/0! | V74: =V20/V73 -> 0 | W74: =W20/W73 -> 0.61300788 | X74: =X20/X73 -> 0.61300788 | Y74: =Y20/Y73 -> 0.61300788 | Z74: =Z20/Z73 -> 0.61300788 | AA74: =AA20/AA73 -> 0.61300788 | AB74: =AB20/AB73 -> 0.61300788 | AG74: Capital turnover | AH74: =AH22/AH73 -> 2.7063911 | AI74: =AI22/AI73 -> 2.7605189 | AJ74: =AJ22/AJ73 -> 2.8074477 | AK74: =AK22/AK73 -> 2.8495594 | AL74: =AL22/AL73 -> 2.3964795 | AM74: =AM22/AM73 -> 2.8014845 | AV74: Capital turnover | AW74: =AW22/AW73 -> 2.7063911 | AX74: =AX22/AX73 -> 2.7605189 | AY74: =AY22/AY73 -> 2.8157293 | AZ74: =AZ22/AZ73 -> 2.8720439 | BA74: =BA22/BA73 -> 2.9294847 | BB74: =BB22/BB73 -> 2.9880744 | BL74: Capital turnover | BM74: =BM22/BM73 -> 2.7063911 | BN74: =BN22/BN73 -> 2.7605189 | BO74: =BO22/BO73 -> 2.8074477 | BP74: =BP22/BP73 -> 2.8495594 | BQ74: =BQ22/BQ73 -> 2.3964795 | BR74: =BR22/BR73 -> 2.8014845
B77: Funds Available by Rounds | AG77: Macro scenarios assumptions | AI77: Round | AJ77: Round | AK77: Round | AL77: Round | AM77: Round
B78: Ending Cash | C78: =C48 -> 1247 | D78: =D48 -> 2857.7399 | E78: =E48 -> 4490.9433 | F78: =F48 -> 5964.3841 | G78: =G48 -> -6152.2251 | H78: =H48 -> -4114.9457 | I78: =I48 -> -2108.034 | J78: =J48 -> -46.514825 | ... M78: =M48 -> 6538.495 | AI78: 1 | AJ78: 2 | AK78: 3 | AL78: 4 | AM78: 5
B79: Cash on hand | C79: =-$C$94*C20 -> -856.72 | D79: =-$C$94*D20 -> -856.72 | E79: =-$C$94*E20 -> -873.8544 | F79: =-$C$94*F20 -> -888.70992 | G79: =-$C$94*G20 -> -902.04057 | H79: =-$C$94*H20 -> -918.61612 | I79: =-$C$94*I20 -> -1046.8222 | J79: =-$C$94*J20 -> -1051.2564 | ... M79: =-$C$94*M20 -> -1064.6922 | AG79: Cost Pressures | AH79: COGS/ Revenue | AK79: 0.005
B80: Debt raising capacity | D80: =MAX(0,$C$93*D30-D87) -> 0 | E80: =MAX(0,$C$93*E30-E87) -> 0 | F80: =MAX(0,$C$93*F30-F87) -> 0 | G80: =MAX(0,$C$93*G30-G87) -> 0 | H80: =MAX(0,$C$93*H30-H87) -> 0 | I80: =MAX(0,$C$93*I30-I87) -> 0 | J80: =MAX(0,$C$93*J30-J87) -> 0 | K80: =MAX(0,$C$93*K30-K87) -> 0 | ... M80: =MAX(0,$C$93*M30-M87) -> 0 | AG80: Recession | AH80: yoy change in Revenue | AL80: -0.15
B81: Access / Shortfall cash | C81: =C78+C79+C80 -> 390.28 | D81: =D78+D79+D80 -> 2001.0199 | E81: =E78+E79+E80 -> 3617.0889 | F81: =F78+F79+F80 -> 5075.6742 | G81: =G78+G79+G80 -> -7054.2657 | H81: =H78+H79+H80 -> -5033.5618 | I81: =I78+I79+I80 -> -3154.8562 | J81: =J78+J79+J80 -> -1097.7712 | ... M81: =M78+M79+M80 -> 5473.8029 | AG81: Recovery | AH81: yoy change in Revenue | AM81: 0.18
B83: Funds Available by Round End | C83: =C81 -> 390.28 | D83: =MAX(D81,0) -> 2001.0199 | E83: =MAX(E81,0) -> 3617.0889 | F83: =MAX(F81,0) -> 5075.6742 | G83: =MAX(G81,0) -> 0 | AG83: Revenue loss | AH83: yoy change in Revenue | AI83: -0.001 | AJ83: -0.001 | AK83: -0.001 | AL83: -0.001 | AM83: -0.001
B84: Flag | C84: =IF(-D19>C83,"Not OK","OK") -> OK | D84: =IF(-E19>D83,"Not OK","OK") -> OK | E84: =IF(-F19>E83,"Not OK","OK") -> OK | F84: =IF(-G19>F83,"Not OK","OK") -> Not OK | G84: =IF(-H19>G83,"Not OK","OK") -> OK
AG85: Sustain Add-In
AG86: Number of decisions | AJ86: =COUNTIFS(Decisions!$W$6:$W$80,Decisions!$A$10,Decisions!$AB$6:$AB$80,AI78) -> 3 | AK86: =COUNTIFS(Decisions!$W$6:$W$80,Decisions!$A$10,Decisions!$AB$6:$AB$80,AJ78) -> 2 | AL86: =COUNTIFS(Decisions!$W$6:$W$80,Decisions!$A$10,Decisions!$AB$6:$AB$80,AK78) -> 4 | AM86: =COUNTIFS(Decisions!$W$6:$W$80,Decisions!$A$10,Decisions!$AB$6:$AB$80,AL78) -> 2 | AN86: =COUNTIFS(Decisions!$W$6:$W$80,Decisions!$A$10,Decisions!$AB$6:$AB$80,AM78) -> 4 | BL86: Number of decisions | BO86: =COUNTIFS(Decisions!$W$6:$W$80,Decisions!$A$10,Decisions!$AB$6:$AB$80,AI78) -> 3 | BP86: =COUNTIFS(Decisions!$W$6:$W$80,Decisions!$A$10,Decisions!$AB$6:$AB$80,AJ78) -> 2 | BQ86: =COUNTIFS(Decisions!$W$6:$W$80,Decisions!$A$10,Decisions!$AB$6:$AB$80,AK78) -> 4 | BR86: =COUNTIFS(Decisions!$W$6:$W$80,Decisions!$A$10,Decisions!$AB$6:$AB$80,AL78) -> 2 | BS86: =COUNTIFS(Decisions!$W$6:$W$80,Decisions!$A$10,Decisions!$AB$6:$AB$80,AM78) -> 4
B87: Debt beginning | D87: =C89 -> 9012 | E87: =D89 -> 9012 | F87: =E89 -> 9012 | G87: =F89 -> 9012 | H87: =G89 -> 16986.729 | I87: =H89 -> 16986.729 | J87: =I89 -> 16986.729 | K87: =J89 -> 16986.729 | ... M87: =L89 -> 16986.729 | AG87: Decisions not taken | AJ87: =SUMIFS(Decisions!$W$122:$W$196,Decisions!$AB$6:$AB$80,AI78) -> 3 | AK87: =SUMIFS(Decisions!$W$122:$W$196,Decisions!$AB$6:$AB$80,AJ78) -> 2 | AL87: =SUMIFS(Decisions!$W$122:$W$196,Decisions!$AB$6:$AB$80,AK78) -> 4 | AM87: =SUMIFS(Decisions!$W$122:$W$196,Decisions!$AB$6:$AB$80,AL78) -> 2 | AN87: =SUMIFS(Decisions!$W$122:$W$196,Decisions!$AB$6:$AB$80,AM78) -> 4 | BL87: Decisions not taken | BO87: =SUMIFS(Decisions!$W$122:$W$196,Decisions!$AB$6:$AB$80,AI78) -> 3 | BP87: =SUMIFS(Decisions!$W$122:$W$196,Decisions!$AB$6:$AB$80,AJ78) -> 2 | BQ87: =SUMIFS(Decisions!$W$122:$W$196,Decisions!$AB$6:$AB$80,AK78) -> 4 | BR87: =SUMIFS(Decisions!$W$122:$W$196,Decisions!$AB$6:$AB$80,AL78) -> 2 | BS87: =SUMIFS(Decisions!$W$122:$W$196,Decisions!$AB$6:$AB$80,AM78) -> 4
B88: New Debt | D88: =MAX(-D19-C83,0) -> 0 | E88: =MAX(-E19-D83,0) -> 0 | F88: =MAX(-F19-E83,0) -> 0 | G88: =MAX(-G19-F83,0) -> 7974.7289 | H88: =MAX(-H19-G83,0) -> 0 | I88: =MAX(-I19-H83,0) -> 0 | J88: =MAX(-J19-I83,0) -> 0 | K88: =MAX(-K19-J83,0) -> 0 | ... M88: =MAX(-M19-L83,0) -> 0
B89: Debt Ending | C89: =-C51+C48 -> 9012 | D89: =D87+D88 -> 9012 | E89: =E87+E88 -> 9012 | F89: =F87+F88 -> 9012 | G89: =G87+G88 -> 16986.729 | H89: =H87+H88 -> 16986.729 | I89: =I87+I88 -> 16986.729 | J89: =J87+J88 -> 16986.729 | K89: =K87+K88 -> 16986.729 | ... M89: =M87+M88 -> 16986.729 | AG89: Impact on Revenue (individual) | AJ89: =AI83 -> -0.001 | AK89: =AJ83 -> -0.001 | AL89: =AK83 -> -0.001 | AM89: =AL83 -> -0.001 | AN89: =AM83 -> -0.001 | BL89: Impact on Revenue (individual) | BO89: -0.001 | BP89: -0.001 | BQ89: -0.001 | BR89: -0.001 | BS89: -0.001
AG90: Total Impact on Revenue | AJ90: =AJ87*AJ89 -> -0.003 | AK90: =AK87*AK89+AJ90 -> -0.005 | AL90: =AL87*AL89+AK90 -> -0.009 | AM90: =AM87*AM89+AL90 -> -0.011 | AN90: =AN87*AN89+AM90 -> -0.015 | AO90: =AN90 -> -0.015 | AP90: =AO90 -> -0.015 | AQ90: =AP90 -> -0.015 | AR90: =AQ90 -> -0.015 | BL90: Total Impact on Revenue | BO90: =BO86*BO89 -> -0.003 | BP90: =BP86*BP89+BO90 -> -0.005 | BQ90: =BQ86*BQ89+BP90 -> -0.009 | BR90: =BR86*BR89+BQ90 -> -0.011 | BS90: =BS86*BS89+BR90 -> -0.015 | BT90: =BT86*BT89+BS90 -> -0.015 | BU90: =BU86*BU89+BT90 -> -0.015 | BV90: =BV86*BV89+BU90 -> -0.015 | BW90: =BW86*BW89+BV90 -> -0.015
B91: Net Debt | D91: =MAX(0,D87-MAX(0,D48)) -> 6154.2601 | E91: =MAX(0,E87-MAX(0,E48)) -> 4521.0567 | F91: =MAX(0,F87-MAX(0,F48)) -> 3047.6159 | G91: =MAX(0,G87-MAX(0,G48)) -> 9012 | H91: =MAX(0,H87-MAX(0,H48)) -> 16986.729 | I91: =MAX(0,I87-MAX(0,I48)) -> 16986.729 | J91: =MAX(0,J87-MAX(0,J48)) -> 16986.729 | K91: =MAX(0,K87-MAX(0,K48)) -> 14910.214 | ... M91: =MAX(0,M87-MAX(0,M48)) -> 10448.234 | AG91: Total Impact
B93: Net Debt/ EBITDA | C93: 2 | AG93: check | AI93: =AI22/AH22-1 -> 0.02 | AJ93: =AJ22/AI22-1 -> 0.017 | AK93: =AK22/AJ22-1 -> 0.015 | AL93: =AL22/AK22-1 -> -0.159 | AM93: =AM22/AL22-1 -> 0.169 | AN93: =AN22/AM22-1 -> 0.005 | AO93: =AO22/AN22-1 -> 0.005 | AP93: =AP22/AO22-1 -> 0.005 | ... AR93: =AR22/AQ22-1 -> 0.005 | BL93: check | BN93: =BN22/BM22-1 -> 0.02 | BO93: =BO22/BN22-1 -> 0.017 | BP93: =BP22/BO22-1 -> 0.015 | BQ93: =BQ22/BP22-1 -> -0.159 | BR93: =BR22/BQ22-1 -> 0.169 | BS93: =BS22/BR22-1 -> 0.005 | BT93: =BT22/BS22-1 -> 0.005 | BU93: =BU22/BT22-1 -> 0.005 | ... BW93: =BW22/BV22-1 -> 0.005
B94: Operating Cash | C94: 0.02 | D94: of revenue
AG95: Round 1 | AI95: =AX60 -> 0.02 | AJ95: =AI95+AJ90 -> 0.017 | AK95: =AJ95 -> 0.017 | AL95: =AK95 -> 0.017 | AM95: =AL95 -> 0.017 | AN95: =AM95 -> 0.017 | AO95: =AN95 -> 0.017 | AP95: =AO95 -> 0.017 | AQ95: =AP95 -> 0.017 | AR95: =AQ95 -> 0.017
AG96: Round 2 | AI96: =AI95 -> 0.02 | AJ96: =AJ95 -> 0.017 | AK96: =AK95 + AK89*AK87 -> 0.015 | AL96: =AK96 -> 0.015 | AM96: =AL96 -> 0.015 | AN96: =AM96 -> 0.015 | AO96: =AN96 -> 0.015 | AP96: =AO96 -> 0.015 | AQ96: =AP96 -> 0.015 | AR96: =AQ96 -> 0.015
AG97: Round 3 | AI97: =AI96 -> 0.02 | AJ97: =AI97+AJ89*AJ87 -> 0.017 | AK97: =AJ97+AK89*AK87 -> 0.015 | AL97: =AK97+AL89*AL87 -> 0.011 | AM97: =AL97 -> 0.011 | AN97: =AM97 -> 0.011 | AO97: =AN97 -> 0.011 | AP97: =AO97 -> 0.011 | AQ97: =AP97 -> 0.011 | AR97: =AQ97 -> 0.011
AG98: Round 4 | AI98: =AI97 -> 0.02 | AJ98: =AJ97 -> 0.017 | AK98: =AK97 -> 0.015 | AL98: =AL80+AL90 -> -0.159 | AM98: =AM97+AM89*AM87 -> 0.009 | AN98: =AM98 -> 0.009 | AO98: =AN98 -> 0.009 | AP98: =AO98 -> 0.009 | AQ98: =AP98 -> 0.009 | AR98: =AQ98 -> 0.009
AG99: Round 5 | AI99: =AI98 -> 0.02 | AJ99: =AJ98 -> 0.017 | AK99: =AK98 -> 0.015 | AL99: =AL98 -> -0.159 | AM99: =AM81+AM90 -> 0.169 | AN99: =AI93+AN90 -> 0.005 | AO99: =AN99 -> 0.005 | AP99: =AO99 -> 0.005 | AQ99: =AP99 -> 0.005 | AR99: =AQ99 -> 0.005

Sheet Assumptions
C3: NPV assumption | D3: Description
B4: Continuing value WACC | C4: 0.08 | D4: X% required rate of return | F4: Maybe add to below table for round assumptions
B5: Long-term growth | C5: 0.02 | D5: X% revenue growth rate beyond 10-year forecast
B7: Metric | C7: Round 1 assumptions
B8: Depreciation | C8: 0.1
B9: Amortization | C9: 0
B10: Cash Taxes | C10: 0.22
B11: Change in Working Capital | C11: 0.05
B12: WACC | C12: 0.08
B13: CapEx | C13: 0.04

Sheet Fundamentals
B2: TSX:MG
B5: Fundamentals | C5: Magna | D5: Peers avg | E5: Unit | F5: Source | I5: Financial Health
B6: Base Revenue | C6: 42836 | E6: $ USD | F6: Annual report 2024 | I6: Total Debt | J6: 8694 | K6: Sep 31, 2025
B7: Capital Productivity | C7: =E31 -> 2.8933801 | D7: =E40 -> 3.2540103 | E7: turns | F7: MVI, 2024 | I7: Net Debt | J7: 8203 | K7: Sep 31, 2025
B8: Adj EBITDA | C8: =E19/100 -> 0.10332431 | D8: =E28 -> 0.1142138 | E8: % | F8: MVI, 2024
B9: Adj EBITA | C9: =I19/100 -> 0.054333209 | D9: =I28 -> 0.067452341 | E9: % | F9: MVI, 2024 | I9: EBITDA NTM | J9: 4263 | K9: Sep 31, 2025
B10: COGS | C10: =M19/100 -> 0.85088284 | D10: =M28 -> 0.80665871 | E10: % | F10: MVI, 2024 | I10: Net Debt/EBITDA | J10: =J7/J9 -> 1.9242318
B11: SGA | C11: =Q19/100 -> 0.048113736 | D11: =Q28 -> 0.05573483 | E11: % | F11: MVI, 2024 | I11: Credit Rating | J11: =_xll.ciqfunctions.udf.CIQ(B2,"IQ_SP_issuer_rating") -> A- | K11: 2.1
B12: ROIC | C12: =I31/100 -> 0.12403603 | D12: =I40 -> 0.16064079 | E12: % | F12: MVI, 2024 | J12: =K11*J9-J7 -> 749.3
B13: Capex to Revenue | C13: =L31/100 -> 0.050845084 | D13: =ROUND(L40,2) -> 0.04 | E13: % | F13: MVI, 2024
B14: R&D to Revenue | C14: =874/42836 -> 0.020403399
B18: Company Name | C18: Data Item Name | D18: Period | E18: Value | G18: Data Item Name | H18: Period | I18: Value | K18: Data Item Name | L18: Period | M18: Value | O18: Data Item Name | P18: Period | Q18: Value
B19: Magna International Inc. | C19: ebitda_adj_marg_ind | D19: 2024 | E19: 10.332431 | G19: ebita_adj_marg_ind | H19: 2024 | I19: 5.4333209 | K19: cogstorevenues_ind | L19: 2024 | M19: 85.088284 | O19: sgatorevenues_ind | P19: 2024 | Q19: 4.8113736
B20: Lear Corporation | C20: ebitda_adj_marg_ind | D20: 2024 | E20: 7.885523 | G20: ebita_adj_marg_ind | H20: 2024 | I20: 4.835511 | K20: cogstorevenues_ind | L20: 2024 | M20: 89.3262 | O20: sgatorevenues_ind | P20: 2024 | Q20: 2.9009697
B21: BorgWarner Inc. | C21: ebitda_adj_marg_ind | D21: 2024 | E21: 13.96422 | G21: ebita_adj_marg_ind | H21: 2024 | I21: 9.8112902 | K21: cogstorevenues_ind | L21: 2024 | M21: 76.558415 | O21: sgatorevenues_ind | P21: 2024 | Q21: 9.6762743
B22: Continental Aktiengesellschaft | C22: ebitda_adj_marg_ind | D22: 2024 | E22: 11.314484 | G22: ebita_adj_marg_ind | H22: 2024 | I22: 6.2312747 | K22: cogstorevenues_ind | L22: 2024 | M22: 72.368388 | O22: sgatorevenues_ind | P22: 2024 | Q22: 9.693094
B23: Valeo SE | C23: ebitda_adj_marg_ind | D23: 2024 | E23: 12.930393 | G23: ebita_adj_marg_ind | H23: 2024 | I23: 4.7831751 | K23: cogstorevenues_ind | L23: 2024 | M23: 72.52466 | O23: sgatorevenues_ind | P23: 2024 | Q23: 4.9599851
B24: Forvia SE | C24: ebitda_adj_marg_ind | D24: 2024 | E24: 12.338457 | G24: ebita_adj_marg_ind | H24: 2024 | I24: 5.3247177 | K24: cogstorevenues_ind | L24: 2024 | M24: 79.486324 | O24: sgatorevenues_ind | P24: 2024 | Q24: 4.7823476
B25: Aptiv PLC | C25: ebitda_adj_marg_ind | D25: 2024 | E25: 16.48151 | G25: ebita_adj_marg_ind | H25: 2024 | I25: 12.060592 | K25: cogstorevenues_ind | L25: 2024 | M25: 76.64234 | O25: sgatorevenues_ind | P25: 2024 | Q25: 7.1577132
B26: Adient plc | C26: ebitda_adj_marg_ind | D26: 2024 | E26: 5.6985294 | G26: ebita_adj_marg_ind | H26: 2024 | I26: 3.2405485 | K26: cogstorevenues_ind | L26: 2024 | M26: 90.903947 | O26: sgatorevenues_ind | P26: 2024 | Q26: 1.1097495
B27: Visteon Corporation | C27: ebitda_adj_marg_ind | D27: 2024 | E27: 11.84687 | G27: ebita_adj_marg_ind | H27: 2024 | I27: 8.9866763 | K27: cogstorevenues_ind | L27: 2024 | M27: 83.094281 | O27: sgatorevenues_ind | P27: 2024 | Q27: 5.0698396
E28: =AVERAGE(E19:E27)/100 -> 0.1142138 | I28: =AVERAGE(I19:I27)/100 -> 0.067452341 | M28: =AVERAGE(M19:M27)/100 -> 0.80665871 | Q28: =AVERAGE(Q19:Q27)/100 -> 0.05573483
I29: =MEDIAN(I19:I27)/100 -> 0.054333209 | M29: =MEDIAN(M19:M27)/100 -> 0.79486324 | Q29: =MEDIAN(Q19:Q27)/100 -> 0.049599851
B30: Company Name | C30: Data Item Name | D30: Period | E30: Value | L30: Value | M30: Units
B31: Magna International Inc. | C31: capitalturns_adj_ind | D31: 2024 | E31: 2.8933801 | G31: roic_adj_ind | H31: 2024 | I31: 12.403603 | K31: capextorevenues_ind | L31: 5.0845084 | M31: In Percent
B32: Lear Corporation | C32: capitalturns_adj_ind | D32: 2024 | E32: 3.5310629 | G32: roic_adj_ind | H32: 2024 | I32: 13.318105 | K32: capextorevenues_ind | L32: 2.3972368 | M32: In Percent
B33: BorgWarner Inc. | C33: capitalturns_adj_ind | D33: 2024 | E33: 2.4736844 | G33: roic_adj_ind | H33: 2024 | I33: 18.202527 | K33: capextorevenues_ind | L33: 4.7635951 | M33: In Percent
B34: Continental Aktiengesellschaft | C34: capitalturns_adj_ind | D34: 2024 | E34: 2.1716721 | G34: roic_adj_ind | H34: 2024 | I34: 9.8785683 | K34: capextorevenues_ind | L34: 4.8792769 | M34: In Percent
B35: Valeo SE | C35: capitalturns_adj_ind | D35: 2024 | E35: 2.5488134 | G35: roic_adj_ind | H35: 2024 | I35: 8.5339946 | K35: capextorevenues_ind | L35: 5.2949935 | M35: In Percent
B36: Forvia SE | C36: capitalturns_adj_ind | D36: 2024 | E36: 3.2669314 | G36: roic_adj_ind | H36: 2024 | I36: 12.394285 | K36: capextorevenues_ind | L36: 3.5719317 | M36: In Percent
B37: Aptiv PLC | C37: capitalturns_adj_ind | D37: 2024 | E37: 2.7647423 | G37: roic_adj_ind | H37: 2024 | I37: 28.67621 | K37: capextorevenues_ind | L37: 4.2104195 | M37: In Percent
B38: Adient plc | C38: capitalturns_adj_ind | D38: 2024 | E38: 5.6032625 | G38: roic_adj_ind | H38: 2024 | I38: 13.79073 | K38: capextorevenues_ind | L38: 1.8110022 | M38: In Percent
B39: Visteon Corporation | C39: capitalturns_adj_ind | D39: 2024 | E39: 4.0325441 | G39: roic_adj_ind | H39: 2024 | I39: 27.378691 | K39: capextorevenues_ind | L39: 3.5437144 | M39: In Percent | S39: 5.3
E40: =AVERAGE(E31:E39) -> 3.2540103 | I40: =AVERAGE(I31:I39)/100 -> 0.16064079 | L40: =AVERAGE(L31:L39)/100 -> 0.03950742 | S40: 5.8
I41: =MEDIAN(I31:I39)/100 -> 0.13318105 | L41: =MEDIAN(L31:L39)/100 -> 0.042104195 | S41: 7.2
S42: 4.1
S43: 3.7
B44: Summary Comparison | S44: 6.8
S45: 5.2
B46: Company | C46: R&D Spending (USD M) | D46: Sales (USD M) | E46: R&D/Sales | S46: 5.1
B47: Magna | C47: 874 | D47: 42836 | E47: 0.02
B48: Visteon | C48: 191 | D48: 3866 | E48: 0.049
B49: Lear | C49: 635 | D49: 23306 | E49: 0.027
B50: Aptiv | C50: 1097 | D50: 19713 | E50: 0.056
B51: TE Connectivity | C51: 699 | D51: 17262 | E51: 0.04
B52: BorgWarner Inc. | E52: 0.052
E53: =AVERAGE(E48:E52) -> 0.0448
E54: =E53-E47 -> 0.0248
B62: Growth Ranking
B63: New Product
B64: Business-model innovation difficult to replicate
B65: Convince customers to buy more
B66: Attracting new customers
B67: Enter fast-growing market
B68: Incremental product/service innovation
B69: Price increase
B70: Programmatic M&A
B71: M&A with high premium
B72: Other

Sheet Baseline
B2: Source: MVI, 2024 Magna Annual Report
B4: Metric | C4: 2024 | D4: Source
B5: Revenue | C5: 42836 | D5: Annual report
B6: COGS | C6: -37037 | D6: Annual report
B7: SG&A | C7: -2061 | D7: Annual report
B8: EBITDA | C8: =SUM(C5:C7) -> 3738 | D8: Revenue - COGS - SG&A
B9: Depreciation | C9: -1510 | D9: Annual report
B10: Amortization | C10: -112
B11: EBIT | C11: =SUM(C8:C10) -> 2116 | D11: EBITDA - Depreciation - Amortization
B13: Cash Taxes | C13: =-0.22*C11 -> -465.52 | D13: Assume 22% of incremental EBIT
B14: Change in Working Capital | C14: =0.05*(C5-42797) -> 1.95 | D14: Assume 5% of revenue; 2023 revenue was $42,797M
B15: CapEx | C15: =-0.04*C5 -> -1713.44 | D15: Assume 4% of revenue (average CAPEX as % of revenue over last 5 years, 2020-25)
B16: Acquisitions | C16: -86 | D16: Annual report
B17: Divestitures | C17: 219 | D17: Annual report
B18: Share Buybacks | C18: -207 | D18: Annual report
B19: Dividends | C19: -539 | D19: Annual report
B21: Ending Cash | C21: 1247
B23: Net Debt and Equivalents | C23: 7765 | D23: MVI
B24: Minority Interest | C24: 418
B25: Shares outstanding, in millions | C25: 287.34 | D25: MVI
B27: Invested Capital | C27: =14782.72+1045 -> 15827.72 | D27: MVI, adjusted to reclassify Equity Investments as operating
B28: Cost of Equity | C28: 0.093
